Workbook
Name SyncBankC: Sync!$C$6:$C$15
Name SyncBankD: Sync!$D$6:$D$15
Name AcctTblA: Sync!$F$6:$I$565
Name PkPartyA: Sync!$T$6:$T$565
Name NPartyA: Sync!$S$565
Name PkExpA: Sync!$X$6:$X$105
Name NExpA: Sync!$W$105
Name CalcDebit: Calc!$I$6:$I$2005
Name CalcCredit: Calc!$J$6:$J$2005
Name CalcAmt: Calc!$H$6:$H$2005
Name CalcDep: Calc!$F$6:$F$2005
Name CalcWit: Calc!$G$6:$G$2005
Name CalcGroup: Calc!$D$6:$D$2005
Name CalcDebit2: Calc!$O$6:$O$505
Name CalcCredit2: Calc!$P$6:$P$505
Name CalcAmt2: Calc!$M$6:$M$505
Name CalcAmt3: Calc!$X$6:$X$1005
Name CalcDebit3: Calc!$Z$6:$Z$1005
Name CalcCredit3: Calc!$AA$6:$AA$1005
Name AcctCodesA: Sync!$F$6:$F$565
Name IssueNosA: Sync!$AG$6:$AG$505
Name PkFixedA: Sync!$AO$6:$AO$565
Name NFixedA: Sync!$AN$565
Name PkLoanA: Sync!$AR$6:$AR$565
Name NLoanA: Sync!$AQ$565
Name PkCapA: Sync!$AU$6:$AU$565
Name NCapA: Sync!$AT$565
Name CalcProb1: Calc!$K$6:$K$2005
Name CalcRank1: Calc!$W$6:$W$2005
Name CalcProb2: Calc!$R$6:$R$505
Name CalcRank2: Calc!$T$6:$T$505
Name TrialType: Trial!$D$10:$D$2365
Name TrialDr: Trial!$E$10:$E$2365
Name TrialCr: Trial!$F$10:$F$2365
Name TrialBal: Trial!$G$10:$G$2365

Sheet Trial
A1: =IF(Sync!$P$6="","مازندشت",Sync!$P$6)&" — "&IF(Sync!$P$9="","سورتینگ و بسته‌بندی مرکبات",Sync!$P$9)
A2: =IF(Sync!$P$7="","باغدشت، بخش مرکزی، شهرستان قائم‌شهر، استان مازندران، ایران",Sync!$P$7)&" | MAZANDASHT · CITRUS SORTING & PACKING"
A3: تراز آزمایشی — تشخیص خودکار بدهکار/بستانکار از تراکنش‌ها و چک‌ها
A4: هر تراکنش دوطرفه است: واریز ← بدهکار بانک / بستانکار طرف · برداشت هزینه ← بدهکار «هزینه: زیرگروه» / بستانکار بانک · برداشت خرید ← بدهکار طرف / بستانکار بانک · «پاس چک» ← بدهکار اسناد چک / بستانکار بانک · صدور چک ← بدهکار ذی‌نفع / بستانکار اسناد چک. طرف حساب با ماهیت «دارایی ثابت» در دارایی‌ها، «وام و تسهیلات» در بدهی‌ها و «سرمایه و آورده صاحبان» در حقوق ترازنامه می‌نشیند. کد طرفِ تعریف‌نشده یا بدون گروه، به «متفرقه» می‌رود و در شیت Control فهرست می‌شود. «شخصی قاسم» طبق تعریف شما خارج از حساب‌های شرکت است و فقط برای توازن نمایش داده می‌شود. خرید سبد (دفتر Baskets): بدهکار «سبد و ظروف» / بستانکار فروشنده سبد — پس مانده هر فروشنده سبد دقیقاً مطابق کارتکس فایل Baskets می‌شود.
A5: جمع کل بدهکار (ریال) | C5: جمع کل بستانکار (ریال) | E5: کنترل توازن | G5: تعداد حساب‌های دارای گردش
A6: =E2366 | C6: =F2366 | E6: =IF(ROUND(E2366-F2366,0)=0,"√ تراز است","▲ مغایرت") | G6: =COUNTIF($G$10:$G$2365,"<>0")
A7: ردیف | B7: حساب | C7: کد / کلید | D7: نوع | E7: جمع بدهکار (ریال) | F7: جمع بستانکار (ریال) | G7: مانده (ریال) | H7: وضعیت
A8: No. | B8: Account | C8: Code / Key | D8: Type | E8: Total Debit | F8: Total Credit | G8: Balance | H8: State
A10: =IF($B10="","",1) | B10: =IF(Sync!$A6="","",Sync!$A6&" — "&Sync!$B6) | C10: =IF($B10="","",Sync!$A6) | D10: =IF($B10="","","b") | E10: =IF($B10="","",SUMIF(CalcDebit,Sync!$A6,CalcAmt)+IF(Sync!$D6="بله",IF(Sync!$C6="",0,Sync!$C6),0)) | F10: =IF($B10="","",SUMIF(CalcCredit,Sync!$A6,CalcAmt)) | G10: =IF($B10="","",ROUND($E10-$F10,0)) | H10: =IF($B10="","",IF(ROUND($G10,0)>0,"بدهکار",IF(ROUND($G10,0)<0,"بستانکار","تسویه")))
A11: =IF($B11="","",2) | B11: =IF(Sync!$A7="","",Sync!$A7&" — "&Sync!$B7) | C11: =IF($B11="","",Sync!$A7) | D11: =IF($B11="","","b") | E11: =IF($B11="","",SUMIF(CalcDebit,Sync!$A7,CalcAmt)+IF(Sync!$D7="بله",IF(Sync!$C7="",0,Sync!$C7),0)) | F11: =IF($B11="","",SUMIF(CalcCredit,Sync!$A7,CalcAmt)) | G11: =IF($B11="","",ROUND($E11-$F11,0)) | H11: =IF($B11="","",IF(ROUND($G11,0)>0,"بدهکار",IF(ROUND($G11,0)<0,"بستانکار","تسویه")))
A12: =IF($B12="","",3) | B12: =IF(Sync!$A8="","",Sync!$A8&" — "&Sync!$B8) | C12: =IF($B12="","",Sync!$A8) | D12: =IF($B12="","","b") | E12: =IF($B12="","",SUMIF(CalcDebit,Sync!$A8,CalcAmt)+IF(Sync!$D8="بله",IF(Sync!$C8="",0,Sync!$C8),0)) | F12: =IF($B12="","",SUMIF(CalcCredit,Sync!$A8,CalcAmt)) | G12: =IF($B12="","",ROUND($E12-$F12,0)) | H12: =IF($B12="","",IF(ROUND($G12,0)>0,"بدهکار",IF(ROUND($G12,0)<0,"بستانکار","تسویه")))
A13: =IF($B13="","",4) | B13: =IF(Sync!$A9="","",Sync!$A9&" — "&Sync!$B9) | C13: =IF($B13="","",Sync!$A9) | D13: =IF($B13="","","b") | E13: =IF($B13="","",SUMIF(CalcDebit,Sync!$A9,CalcAmt)+IF(Sync!$D9="بله",IF(Sync!$C9="",0,Sync!$C9),0)) | F13: =IF($B13="","",SUMIF(CalcCredit,Sync!$A9,CalcAmt)) | G13: =IF($B13="","",ROUND($E13-$F13,0)) | H13: =IF($B13="","",IF(ROUND($G13,0)>0,"بدهکار",IF(ROUND($G13,0)<0,"بستانکار","تسویه")))
A14: =IF($B14="","",5) | B14: =IF(Sync!$A10="","",Sync!$A10&" — "&Sync!$B10) | C14: =IF($B14="","",Sync!$A10) | D14: =IF($B14="","","b") | E14: =IF($B14="","",SUMIF(CalcDebit,Sync!$A10,CalcAmt)+IF(Sync!$D10="بله",IF(Sync!$C10="",0,Sync!$C10),0)) | F14: =IF($B14="","",SUMIF(CalcCredit,Sync!$A10,CalcAmt)) | G14: =IF($B14="","",ROUND($E14-$F14,0)) | H14: =IF($B14="","",IF(ROUND($G14,0)>0,"بدهکار",IF(ROUND($G14,0)<0,"بستانکار","تسویه")))
A15: =IF($B15="","",6) | B15: =IF(Sync!$A11="","",Sync!$A11&" — "&Sync!$B11) | C15: =IF($B15="","",Sync!$A11) | D15: =IF($B15="","","b") | E15: =IF($B15="","",SUMIF(CalcDebit,Sync!$A11,CalcAmt)+IF(Sync!$D11="بله",IF(Sync!$C11="",0,Sync!$C11),0)) | F15: =IF($B15="","",SUMIF(CalcCredit,Sync!$A11,CalcAmt)) | G15: =IF($B15="","",ROUND($E15-$F15,0)) | H15: =IF($B15="","",IF(ROUND($G15,0)>0,"بدهکار",IF(ROUND($G15,0)<0,"بستانکار","تسویه")))
A16: =IF($B16="","",7) | B16: =IF(Sync!$A12="","",Sync!$A12&" — "&Sync!$B12) | C16: =IF($B16="","",Sync!$A12) | D16: =IF($B16="","","b") | E16: =IF($B16="","",SUMIF(CalcDebit,Sync!$A12,CalcAmt)+IF(Sync!$D12="بله",IF(Sync!$C12="",0,Sync!$C12),0)) | F16: =IF($B16="","",SUMIF(CalcCredit,Sync!$A12,CalcAmt)) | G16: =IF($B16="","",ROUND($E16-$F16,0)) | H16: =IF($B16="","",IF(ROUND($G16,0)>0,"بدهکار",IF(ROUND($G16,0)<0,"بستانکار","تسویه")))
A17: =IF($B17="","",8) | B17: =IF(Sync!$A13="","",Sync!$A13&" — "&Sync!$B13) | C17: =IF($B17="","",Sync!$A13) | D17: =IF($B17="","","b") | E17: =IF($B17="","",SUMIF(CalcDebit,Sync!$A13,CalcAmt)+IF(Sync!$D13="بله",IF(Sync!$C13="",0,Sync!$C13),0)) | F17: =IF($B17="","",SUMIF(CalcCredit,Sync!$A13,CalcAmt)) | G17: =IF($B17="","",ROUND($E17-$F17,0)) | H17: =IF($B17="","",IF(ROUND($G17,0)>0,"بدهکار",IF(ROUND($G17,0)<0,"بستانکار","تسویه")))
A18: =IF($B18="","",9) | B18: =IF(Sync!$A14="","",Sync!$A14&" — "&Sync!$B14) | C18: =IF($B18="","",Sync!$A14) | D18: =IF($B18="","","b") | E18: =IF($B18="","",SUMIF(CalcDebit,Sync!$A14,CalcAmt)+IF(Sync!$D14="بله",IF(Sync!$C14="",0,Sync!$C14),0)) | F18: =IF($B18="","",SUMIF(CalcCredit,Sync!$A14,CalcAmt)) | G18: =IF($B18="","",ROUND($E18-$F18,0)) | H18: =IF($B18="","",IF(ROUND($G18,0)>0,"بدهکار",IF(ROUND($G18,0)<0,"بستانکار","تسویه")))
A19: =IF($B19="","",10) | B19: =IF(Sync!$A15="","",Sync!$A15&" — "&Sync!$B15) | C19: =IF($B19="","",Sync!$A15) | D19: =IF($B19="","","b") | E19: =IF($B19="","",SUMIF(CalcDebit,Sync!$A15,CalcAmt)+IF(Sync!$D15="بله",IF(Sync!$C15="",0,Sync!$C15),0)) | F19: =IF($B19="","",SUMIF(CalcCredit,Sync!$A15,CalcAmt)) | G19: =IF($B19="","",ROUND($E19-$F19,0)) | H19: =IF($B19="","",IF(ROUND($G19,0)>0,"بدهکار",IF(ROUND($G19,0)<0,"بستانکار","تسویه")))
A20: =IF($B20="","",11) | B20: ="اسناد چک پرداختی" | C20: =IF($B20="","","چک پرداختی") | D20: =IF($B20="","","q") | E20: =IF($B20="","",SUMIF(CalcDebit,"چک پرداختی",CalcAmt)) | F20: =IF($B20="","",SUMIF(CalcCredit2,"چک پرداختی",CalcAmt2)) | G20: =IF($B20="","",ROUND($E20-$F20,0)) | H20: =IF($B20="","",IF(ROUND($G20,0)>0,"بدهکار",IF(ROUND($G20,0)<0,"بستانکار","تسویه")))
A21: =IF($B21="","",12) | B21: ="افتتاحیه (مانده اولیه بانک‌ها)" | C21: =IF($B21="","","افتتاحیه") | D21: =IF($B21="","","o") | E21: =IF($B21="","",0) | F21: =IF($B21="","",SUMIFS(SyncBankC,SyncBankD,"بله")) | G21: =IF($B21="","",ROUND($E21-$F21,0)) | H21: =IF($B21="","",IF(ROUND($G21,0)>0,"بدهکار",IF(ROUND($G21,0)<0,"بستانکار","تسویه")))
A22: =IF($B22="","",13) | B22: ="متفرقه / بدون طبقه" | C22: =IF($B22="","","متفرقه") | D22: =IF($B22="","","m") | E22: =IF($B22="","",SUMIF(CalcDebit,"متفرقه",CalcAmt)+SUMIF(CalcDebit2,"متفرقه",CalcAmt2)+SUMIF(CalcDebit3,"متفرقه",CalcAmt3)) | F22: =IF($B22="","",SUMIF(CalcCredit,"متفرقه",CalcAmt)+SUMIF(CalcCredit2,"متفرقه",CalcAmt2)+SUMIF(CalcCredit3,"متفرقه",CalcAmt3)) | G22: =IF($B22="","",ROUND($E22-$F22,0)) | H22: =IF($B22="","",IF(ROUND($G22,0)>0,"بدهکار",IF(ROUND($G22,0)<0,"بستانکار","تسویه")))
A23: =IF($B23="","",14) | B23: ="شخصی قاسم (خارج از حساب‌های شرکت)" | C23: =IF($B23="","","شخصی قاسم") | D23: =IF($B23="","","x") | E23: =IF($B23="","",SUMIF(CalcDebit,"شخصی قاسم",CalcAmt)) | F23: =IF($B23="","",SUMIF(CalcCredit,"شخصی قاسم",CalcAmt)) | G23: =IF($B23="","",ROUND($E23-$F23,0)) | H23: =IF($B23="","",IF(ROUND($G23,0)>0,"بدهکار",IF(ROUND($G23,0)<0,"بستانکار","تسویه")))
A24: =IF($B24="","",15) | B24: ="سبد و ظروف — از دفتر Baskets" | C24: =IF($B24="","","سبد و ظروف") | D24: =IF($B24="","","s") | E24: =IF($B24="","",SUMIF(CalcDebit3,"سبد و ظروف",CalcAmt3)) | F24: =IF($B24="","",0) | G24: =IF($B24="","",ROUND($E24-$F24,0)) | H24: =IF($B24="","",IF(ROUND($G24,0)>0,"بدهکار",IF(ROUND($G24,0)<0,"بستانکار","تسویه")))
A25: =IF($B25="","",16) | B25: =IF(1>NPartyA,"",IFERROR(IF(VLOOKUP(INDEX(PkPartyA,1),AcctTblA,4,0)="","(بدون نام)",VLOOKUP(INDEX(PkPartyA,1),AcctTblA,4,0)),"—")) | C25: =IF($B25="","",IF(1>NPartyA,"",INDEX(PkPartyA,1))) | D25: =IF($B25="","","p") | E25: =IF($B25="","",IF(1>NPartyA,0,SUMIF(CalcDebit,INDEX(PkPartyA,1),CalcAmt)+SUMIF(CalcDebit2,INDEX(PkPartyA,1),CalcAmt2)+SUMIF(CalcDebit3,INDEX(PkPartyA,1),CalcAmt3))) | F25: =IF($B25="","",IF(1>NPartyA,0,SUMIF(CalcCredit,INDEX(PkPartyA,1),CalcAmt)+SUMIF(CalcCredit2,INDEX(PkPartyA,1),CalcAmt2)+SUMIF(CalcCredit3,INDEX(PkPartyA,1),CalcAmt3))) | G25: =IF($B25="","",ROUND($E25-$F25,0)) | H25: =IF($B25="","",IF(ROUND($G25,0)>0,"بدهکار",IF(ROUND($G25,0)<0,"بستانکار","تسویه")))
A26: =IF($B26="","",17) | B26: =IF(2>NPartyA,"",IFERROR(IF(VLOOKUP(INDEX(PkPartyA,2),AcctTblA,4,0)="","(بدون نام)",VLOOKUP(INDEX(PkPartyA,2),AcctTblA,4,0)),"—")) | C26: =IF($B26="","",IF(2>NPartyA,"",INDEX(PkPartyA,2))) | D26: =IF($B26="","","p") | E26: =IF($B26="","",IF(2>NPartyA,0,SUMIF(CalcDebit,INDEX(PkPartyA,2),CalcAmt)+SUMIF(CalcDebit2,INDEX(PkPartyA,2),CalcAmt2)+SUMIF(CalcDebit3,INDEX(PkPartyA,2),CalcAmt3))) | F26: =IF($B26="","",IF(2>NPartyA,0,SUMIF(CalcCredit,INDEX(PkPartyA,2),CalcAmt)+SUMIF(CalcCredit2,INDEX(PkPartyA,2),CalcAmt2)+SUMIF(CalcCredit3,INDEX(PkPartyA,2),CalcAmt3))) | G26: =IF($B26="","",ROUND($E26-$F26,0)) | H26: =IF($B26="","",IF(ROUND($G26,0)>0,"بدهکار",IF(ROUND($G26,0)<0,"بستانکار","تسویه")))
A27: =IF($B27="","",18) | B27: =IF(3>NPartyA,"",IFERROR(IF(VLOOKUP(INDEX(PkPartyA,3),AcctTblA,4,0)="","(بدون نام)",VLOOKUP(INDEX(PkPartyA,3),AcctTblA,4,0)),"—")) | C27: =IF($B27="","",IF(3>NPartyA,"",INDEX(PkPartyA,3))) | D27: =IF($B27="","","p") | E27: =IF($B27="","",IF(3>NPartyA,0,SUMIF(CalcDebit,INDEX(PkPartyA,3),CalcAmt)+SUMIF(CalcDebit2,INDEX(PkPartyA,3),CalcAmt2)+SUMIF(CalcDebit3,INDEX(PkPartyA,3),CalcAmt3))) | F27: =IF($B27="","",IF(3>NPartyA,0,SUMIF(CalcCredit,INDEX(PkPartyA,3),CalcAmt)+SUMIF(CalcCredit2,INDEX(PkPartyA,3),CalcAmt2)+SUMIF(CalcCredit3,INDEX(PkPartyA,3),CalcAmt3))) | G27: =IF($B27="","",ROUND($E27-$F27,0)) | H27: =IF($B27="","",IF(ROUND($G27,0)>0,"بدهکار",IF(ROUND($G27,0)<0,"بستانکار","تسویه")))
A28: =IF($B28="","",19) | B28: =IF(4>NPartyA,"",IFERROR(IF(VLOOKUP(INDEX(PkPartyA,4),AcctTblA,4,0)="","(بدون نام)",VLOOKUP(INDEX(PkPartyA,4),AcctTblA,4,0)),"—")) | C28: =IF($B28="","",IF(4>NPartyA,"",INDEX(PkPartyA,4))) | D28: =IF($B28="","","p") | E28: =IF($B28="","",IF(4>NPartyA,0,SUMIF(CalcDebit,INDEX(PkPartyA,4),CalcAmt)+SUMIF(CalcDebit2,INDEX(PkPartyA,4),CalcAmt2)+SUMIF(CalcDebit3,INDEX(PkPartyA,4),CalcAmt3))) | F28: =IF($B28="","",IF(4>NPartyA,0,SUMIF(CalcCredit,INDEX(PkPartyA,4),CalcAmt)+SUMIF(CalcCredit2,INDEX(PkPartyA,4),CalcAmt2)+SUMIF(CalcCredit3,INDEX(PkPartyA,4),CalcAmt3))) | G28: =IF($B28="","",ROUND($E28-$F28,0)) | H28: =IF($B28="","",IF(ROUND($G28,0)>0,"بدهکار",IF(ROUND($G28,0)<0,"بستانکار","تسویه")))
A29: =IF($B29="","",20) | B29: =IF(5>NPartyA,"",IFERROR(IF(VLOOKUP(INDEX(PkPartyA,5),AcctTblA,4,0)="","(بدون نام)",VLOOKUP(INDEX(PkPartyA,5),AcctTblA,4,0)),"—")) | C29: =IF($B29="","",IF(5>NPartyA,"",INDEX(PkPartyA,5))) | D29: =IF($B29="","","p") | E29: =IF($B29="","",IF(5>NPartyA,0,SUMIF(CalcDebit,INDEX(PkPartyA,5),CalcAmt)+SUMIF(CalcDebit2,INDEX(PkPartyA,5),CalcAmt2)+SUMIF(CalcDebit3,INDEX(PkPartyA,5),CalcAmt3))) | F29: =IF($B29="","",IF(5>NPartyA,0,SUMIF(CalcCredit,INDEX(PkPartyA,5),CalcAmt)+SUMIF(CalcCredit2,INDEX(PkPartyA,5),CalcAmt2)+SUMIF(CalcCredit3,INDEX(PkPartyA,5),CalcAmt3))) | G29: =IF($B29="","",ROUND($E29-$F29,0)) | H29: =IF($B29="","",IF(ROUND($G29,0)>0,"بدهکار",IF(ROUND($G29,0)<0,"بستانکار","تسویه")))
A30: =IF($B30="","",21) | B30: =IF(6>NPartyA,"",IFERROR(IF(VLOOKUP(INDEX(PkPartyA,6),AcctTblA,4,0)="","(بدون نام)",VLOOKUP(INDEX(PkPartyA,6),AcctTblA,4,0)),"—")) | C30: =IF($B30="","",IF(6>NPartyA,"",INDEX(PkPartyA,6))) | D30: =IF($B30="","","p") | E30: =IF($B30="","",IF(6>NPartyA,0,SUMIF(CalcDebit,INDEX(PkPartyA,6),CalcAmt)+SUMIF(CalcDebit2,INDEX(PkPartyA,6),CalcAmt2)+SUMIF(CalcDebit3,INDEX(PkPartyA,6),CalcAmt3))) | F30: =IF($B30="","",IF(6>NPartyA,0,SUMIF(CalcCredit,INDEX(PkPartyA,6),CalcAmt)+SUMIF(CalcCredit2,INDEX(PkPartyA,6),CalcAmt2)+SUMIF(CalcCredit3,INDEX(PkPartyA,6),CalcAmt3))) | G30: =IF($B30="","",ROUND($E30-$F30,0)) | H30: =IF($B30="","",IF(ROUND($G30,0)>0,"بدهکار",IF(ROUND($G30,0)<0,"بستانکار","تسویه")))
A31: =IF($B31="","",22) | B31: =IF(7>NPartyA,"",IFERROR(IF(VLOOKUP(INDEX(PkPartyA,7),AcctTblA,4,0)="","(بدون نام)",VLOOKUP(INDEX(PkPartyA,7),AcctTblA,4,0)),"—")) | C31: =IF($B31="","",IF(7>NPartyA,"",INDEX(PkPartyA,7))) | D31: =IF($B31="","","p") | E31: =IF($B31="","",IF(7>NPartyA,0,SUMIF(CalcDebit,INDEX(PkPartyA,7),CalcAmt)+SUMIF(CalcDebit2,INDEX(PkPartyA,7),CalcAmt2)+SUMIF(CalcDebit3,INDEX(PkPartyA,7),CalcAmt3))) | F31: =IF($B31="","",IF(7>NPartyA,0,SUMIF(CalcCredit,INDEX(PkPartyA,7),CalcAmt)+SUMIF(CalcCredit2,INDEX(PkPartyA,7),CalcAmt2)+SUMIF(CalcCredit3,INDEX(PkPartyA,7),CalcAmt3))) | G31: =IF($B31="","",ROUND($E31-$F31,0)) | H31: =IF($B31="","",IF(ROUND($G31,0)>0,"بدهکار",IF(ROUND($G31,0)<0,"بستانکار","تسویه")))
A32: =IF($B32="","",23) | B32: =IF(8>NPartyA,"",IFERROR(IF(VLOOKUP(INDEX(PkPartyA,8),AcctTblA,4,0)="","(بدون نام)",VLOOKUP(INDEX(PkPartyA,8),AcctTblA,4,0)),"—")) | C32: =IF($B32="","",IF(8>NPartyA,"",INDEX(PkPartyA,8))) | D32: =IF($B32="","","p") | E32: =IF($B32="","",IF(8>NPartyA,0,SUMIF(CalcDebit,INDEX(PkPartyA,8),CalcAmt)+SUMIF(CalcDebit2,INDEX(PkPartyA,8),CalcAmt2)+SUMIF(CalcDebit3,INDEX(PkPartyA,8),CalcAmt3))) | F32: =IF($B32="","",IF(8>NPartyA,0,SUMIF(CalcCredit,INDEX(PkPartyA,8),CalcAmt)+SUMIF(CalcCredit2,INDEX(PkPartyA,8),CalcAmt2)+SUMIF(CalcCredit3,INDEX(PkPartyA,8),CalcAmt3))) | G32: =IF($B32="","",ROUND($E32-$F32,0)) | H32: =IF($B32="","",IF(ROUND($G32,0)>0,"بدهکار",IF(ROUND($G32,0)<0,"بستانکار","تسویه")))
A33: =IF($B33="","",24) | B33: =IF(9>NPartyA,"",IFERROR(IF(VLOOKUP(INDEX(PkPartyA,9),AcctTblA,4,0)="","(بدون نام)",VLOOKUP(INDEX(PkPartyA,9),AcctTblA,4,0)),"—")) | C33: =IF($B33="","",IF(9>NPartyA,"",INDEX(PkPartyA,9))) | D33: =IF($B33="","","p") | E33: =IF($B33="","",IF(9>NPartyA,0,SUMIF(CalcDebit,INDEX(PkPartyA,9),CalcAmt)+SUMIF(CalcDebit2,INDEX(PkPartyA,9),CalcAmt2)+SUMIF(CalcDebit3,INDEX(PkPartyA,9),CalcAmt3))) | F33: =IF($B33="","",IF(9>NPartyA,0,SUMIF(CalcCredit,INDEX(PkPartyA,9),CalcAmt)+SUMIF(CalcCredit2,INDEX(PkPartyA,9),CalcAmt2)+SUMIF(CalcCredit3,INDEX(PkPartyA,9),CalcAmt3))) | G33: =IF($B33="","",ROUND($E33-$F33,0)) | H33: =IF($B33="","",IF(ROUND($G33,0)>0,"بدهکار",IF(ROUND($G33,0)<0,"بستانکار","تسویه")))
A34: =IF($B34="","",25) | B34: =IF(10>NPartyA,"",IFERROR(IF(VLOOKUP(INDEX(PkPartyA,10),AcctTblA,4,0)="","(بدون نام)",VLOOKUP(INDEX(PkPartyA,10),AcctTblA,4,0)),"—")) | C34: =IF($B34="","",IF(10>NPartyA,"",INDEX(PkPartyA,10))) | D34: =IF($B34="","","p") | E34: =IF($B34="","",IF(10>NPartyA,0,SUMIF(CalcDebit,INDEX(PkPartyA,10),CalcAmt)+SUMIF(CalcDebit2,INDEX(PkPartyA,10),CalcAmt2)+SUMIF(CalcDebit3,INDEX(PkPartyA,10),CalcAmt3))) | F34: =IF($B34="","",IF(10>NPartyA,0,SUMIF(CalcCredit,INDEX(PkPartyA,10),CalcAmt)+SUMIF(CalcCredit2,INDEX(PkPartyA,10),CalcAmt2)+SUMIF(CalcCredit3,INDEX(PkPartyA,10),CalcAmt3))) | G34: =IF($B34="","",ROUND($E34-$F34,0)) | H34: =IF($B34="","",IF(ROUND($G34,0)>0,"بدهکار",IF(ROUND($G34,0)<0,"بستانکار","تسویه")))
A35: =IF($B35="","",26) | B35: =IF(11>NPartyA,"",IFERROR(IF(VLOOKUP(INDEX(PkPartyA,11),AcctTblA,4,0)="","(بدون نام)",VLOOKUP(INDEX(PkPartyA,11),AcctTblA,4,0)),"—")) | C35: =IF($B35="","",IF(11>NPartyA,"",INDEX(PkPartyA,11))) | D35: =IF($B35="","","p") | E35: =IF($B35="","",IF(11>NPartyA,0,SUMIF(CalcDebit,INDEX(PkPartyA,11),CalcAmt)+SUMIF(CalcDebit2,INDEX(PkPartyA,11),CalcAmt2)+SUMIF(CalcDebit3,INDEX(PkPartyA,11),CalcAmt3))) | F35: =IF($B35="","",IF(11>NPartyA,0,SUMIF(CalcCredit,INDEX(PkPartyA,11),CalcAmt)+SUMIF(CalcCredit2,INDEX(PkPartyA,11),CalcAmt2)+SUMIF(CalcCredit3,INDEX(PkPartyA,11),CalcAmt3))) | G35: =IF($B35="","",ROUND($E35-$F35,0)) | H35: =IF($B35="","",IF(ROUND($G35,0)>0,"بدهکار",IF(ROUND($G35,0)<0,"بستانکار","تسویه")))
A36: =IF($B36="","",27) | B36: =IF(12>NPartyA,"",IFERROR(IF(VLOOKUP(INDEX(PkPartyA,12),AcctTblA,4,0)="","(بدون نام)",VLOOKUP(INDEX(PkPartyA,12),AcctTblA,4,0)),"—")) | C36: =IF($B36="","",IF(12>NPartyA,"",INDEX(PkPartyA,12))) | D36: =IF($B36="","","p") | E36: =IF($B36="","",IF(12>NPartyA,0,SUMIF(CalcDebit,INDEX(PkPartyA,12),CalcAmt)+SUMIF(CalcDebit2,INDEX(PkPartyA,12),CalcAmt2)+SUMIF(CalcDebit3,INDEX(PkPartyA,12),CalcAmt3))) | F36: =IF($B36="","",IF(12>NPartyA,0,SUMIF(CalcCredit,INDEX(PkPartyA,12),CalcAmt)+SUMIF(CalcCredit2,INDEX(PkPartyA,12),CalcAmt2)+SUMIF(CalcCredit3,INDEX(PkPartyA,12),CalcAmt3))) | G36: =IF($B36="","",ROUND($E36-$F36,0)) | H36: =IF($B36="","",IF(ROUND($G36,0)>0,"بدهکار",IF(ROUND($G36,0)<0,"بستانکار","تسویه")))
A37: =IF($B37="","",28) | B37: =IF(13>NPartyA,"",IFERROR(IF(VLOOKUP(INDEX(PkPartyA,13),AcctTblA,4,0)="","(بدون نام)",VLOOKUP(INDEX(PkPartyA,13),AcctTblA,4,0)),"—")) | C37: =IF($B37="","",IF(13>NPartyA,"",INDEX(PkPartyA,13))) | D37: =IF($B37="","","p") | E37: =IF($B37="","",IF(13>NPartyA,0,SUMIF(CalcDebit,INDEX(PkPartyA,13),CalcAmt)+SUMIF(CalcDebit2,INDEX(PkPartyA,13),CalcAmt2)+SUMIF(CalcDebit3,INDEX(PkPartyA,13),CalcAmt3))) | F37: =IF($B37="","",IF(13>NPartyA,0,SUMIF(CalcCredit,INDEX(PkPartyA,13),CalcAmt)+SUMIF(CalcCredit2,INDEX(PkPartyA,13),CalcAmt2)+SUMIF(CalcCredit3,INDEX(PkPartyA,13),CalcAmt3))) | G37: =IF($B37="","",ROUND($E37-$F37,0)) | H37: =IF($B37="","",IF(ROUND($G37,0)>0,"بدهکار",IF(ROUND($G37,0)<0,"بستانکار","تسویه")))
A38: =IF($B38="","",29) | B38: =IF(14>NPartyA,"",IFERROR(IF(VLOOKUP(INDEX(PkPartyA,14),AcctTblA,4,0)="","(بدون نام)",VLOOKUP(INDEX(PkPartyA,14),AcctTblA,4,0)),"—")) | C38: =IF($B38="","",IF(14>NPartyA,"",INDEX(PkPartyA,14))) | D38: =IF($B38="","","p") | E38: =IF($B38="","",IF(14>NPartyA,0,SUMIF(CalcDebit,INDEX(PkPartyA,14),CalcAmt)+SUMIF(CalcDebit2,INDEX(PkPartyA,14),CalcAmt2)+SUMIF(CalcDebit3,INDEX(PkPartyA,14),CalcAmt3))) | F38: =IF($B38="","",IF(14>NPartyA,0,SUMIF(CalcCredit,INDEX(PkPartyA,14),CalcAmt)+SUMIF(CalcCredit2,INDEX(PkPartyA,14),CalcAmt2)+SUMIF(CalcCredit3,INDEX(PkPartyA,14),CalcAmt3))) | G38: =IF($B38="","",ROUND($E38-$F38,0)) | H38: =IF($B38="","",IF(ROUND($G38,0)>0,"بدهکار",IF(ROUND($G38,0)<0,"بستانکار","تسویه")))
A39: =IF($B39="","",30) | B39: =IF(15>NPartyA,"",IFERROR(IF(VLOOKUP(INDEX(PkPartyA,15),AcctTblA,4,0)="","(بدون نام)",VLOOKUP(INDEX(PkPartyA,15),AcctTblA,4,0)),"—")) | C39: =IF($B39="","",IF(15>NPartyA,"",INDEX(PkPartyA,15))) | D39: =IF($B39="","","p") | E39: =IF($B39="","",IF(15>NPartyA,0,SUMIF(CalcDebit,INDEX(PkPartyA,15),CalcAmt)+SUMIF(CalcDebit2,INDEX(PkPartyA,15),CalcAmt2)+SUMIF(CalcDebit3,INDEX(PkPartyA,15),CalcAmt3))) | F39: =IF($B39="","",IF(15>NPartyA,0,SUMIF(CalcCredit,INDEX(PkPartyA,15),CalcAmt)+SUMIF(CalcCredit2,INDEX(PkPartyA,15),CalcAmt2)+SUMIF(CalcCredit3,INDEX(PkPartyA,15),CalcAmt3))) | G39: =IF($B39="","",ROUND($E39-$F39,0)) | H39: =IF($B39="","",IF(ROUND($G39,0)>0,"بدهکار",IF(ROUND($G39,0)<0,"بستانکار","تسویه")))
A40: =IF($B40="","",31) | B40: =IF(16>NPartyA,"",IFERROR(IF(VLOOKUP(INDEX(PkPartyA,16),AcctTblA,4,0)="","(بدون نام)",VLOOKUP(INDEX(PkPartyA,16),AcctTblA,4,0)),"—")) | C40: =IF($B40="","",IF(16>NPartyA,"",INDEX(PkPartyA,16))) | D40: =IF($B40="","","p") | E40: =IF($B40="","",IF(16>NPartyA,0,SUMIF(CalcDebit,INDEX(PkPartyA,16),CalcAmt)+SUMIF(CalcDebit2,INDEX(PkPartyA,16),CalcAmt2)+SUMIF(CalcDebit3,INDEX(PkPartyA,16),CalcAmt3))) | F40: =IF($B40="","",IF(16>NPartyA,0,SUMIF(CalcCredit,INDEX(PkPartyA,16),CalcAmt)+SUMIF(CalcCredit2,INDEX(PkPartyA,16),CalcAmt2)+SUMIF(CalcCredit3,INDEX(PkPartyA,16),CalcAmt3))) | G40: =IF($B40="","",ROUND($E40-$F40,0)) | H40: =IF($B40="","",IF(ROUND($G40,0)>0,"بدهکار",IF(ROUND($G40,0)<0,"بستانکار","تسویه")))
A41: =IF($B41="","",32) | B41: =IF(17>NPartyA,"",IFERROR(IF(VLOOKUP(INDEX(PkPartyA,17),AcctTblA,4,0)="","(بدون نام)",VLOOKUP(INDEX(PkPartyA,17),AcctTblA,4,0)),"—")) | C41: =IF($B41="","",IF(17>NPartyA,"",INDEX(PkPartyA,17))) | D41: =IF($B41="","","p") | E41: =IF($B41="","",IF(17>NPartyA,0,SUMIF(CalcDebit,INDEX(PkPartyA,17),CalcAmt)+SUMIF(CalcDebit2,INDEX(PkPartyA,17),CalcAmt2)+SUMIF(CalcDebit3,INDEX(PkPartyA,17),CalcAmt3))) | F41: =IF($B41="","",IF(17>NPartyA,0,SUMIF(CalcCredit,INDEX(PkPartyA,17),CalcAmt)+SUMIF(CalcCredit2,INDEX(PkPartyA,17),CalcAmt2)+SUMIF(CalcCredit3,INDEX(PkPartyA,17),CalcAmt3))) | G41: =IF($B41="","",ROUND($E41-$F41,0)) | H41: =IF($B41="","",IF(ROUND($G41,0)>0,"بدهکار",IF(ROUND($G41,0)<0,"بستانکار","تسویه")))
A42: =IF($B42="","",33) | B42: =IF(18>NPartyA,"",IFERROR(IF(VLOOKUP(INDEX(PkPartyA,18),AcctTblA,4,0)="","(بدون نام)",VLOOKUP(INDEX(PkPartyA,18),AcctTblA,4,0)),"—")) | C42: =IF($B42="","",IF(18>NPartyA,"",INDEX(PkPartyA,18))) | D42: =IF($B42="","","p") | E42: =IF($B42="","",IF(18>NPartyA,0,SUMIF(CalcDebit,INDEX(PkPartyA,18),CalcAmt)+SUMIF(CalcDebit2,INDEX(PkPartyA,18),CalcAmt2)+SUMIF(CalcDebit3,INDEX(PkPartyA,18),CalcAmt3))) | F42: =IF($B42="","",IF(18>NPartyA,0,SUMIF(CalcCredit,INDEX(PkPartyA,18),CalcAmt)+SUMIF(CalcCredit2,INDEX(PkPartyA,18),CalcAmt2)+SUMIF(CalcCredit3,INDEX(PkPartyA,18),CalcAmt3))) | G42: =IF($B42="","",ROUND($E42-$F42,0)) | H42: =IF($B42="","",IF(ROUND($G42,0)>0,"بدهکار",IF(ROUND($G42,0)<0,"بستانکار","تسویه")))
A43: =IF($B43="","",34) | B43: =IF(19>NPartyA,"",IFERROR(IF(VLOOKUP(INDEX(PkPartyA,19),AcctTblA,4,0)="","(بدون نام)",VLOOKUP(INDEX(PkPartyA,19),AcctTblA,4,0)),"—")) | C43: =IF($B43="","",IF(19>NPartyA,"",INDEX(PkPartyA,19))) | D43: =IF($B43="","","p") | E43: =IF($B43="","",IF(19>NPartyA,0,SUMIF(CalcDebit,INDEX(PkPartyA,19),CalcAmt)+SUMIF(CalcDebit2,INDEX(PkPartyA,19),CalcAmt2)+SUMIF(CalcDebit3,INDEX(PkPartyA,19),CalcAmt3))) | F43: =IF($B43="","",IF(19>NPartyA,0,SUMIF(CalcCredit,INDEX(PkPartyA,19),CalcAmt)+SUMIF(CalcCredit2,INDEX(PkPartyA,19),CalcAmt2)+SUMIF(CalcCredit3,INDEX(PkPartyA,19),CalcAmt3))) | G43: =IF($B43="","",ROUND($E43-$F43,0)) | H43: =IF($B43="","",IF(ROUND($G43,0)>0,"بدهکار",IF(ROUND($G43,0)<0,"بستانکار","تسویه")))
A44: =IF($B44="","",35) | B44: =IF(20>NPartyA,"",IFERROR(IF(VLOOKUP(INDEX(PkPartyA,20),AcctTblA,4,0)="","(بدون نام)",VLOOKUP(INDEX(PkPartyA,20),AcctTblA,4,0)),"—")) | C44: =IF($B44="","",IF(20>NPartyA,"",INDEX(PkPartyA,20))) | D44: =IF($B44="","","p") | E44: =IF($B44="","",IF(20>NPartyA,0,SUMIF(CalcDebit,INDEX(PkPartyA,20),CalcAmt)+SUMIF(CalcDebit2,INDEX(PkPartyA,20),CalcAmt2)+SUMIF(CalcDebit3,INDEX(PkPartyA,20),CalcAmt3))) | F44: =IF($B44="","",IF(20>NPartyA,0,SUMIF(CalcCredit,INDEX(PkPartyA,20),CalcAmt)+SUMIF(CalcCredit2,INDEX(PkPartyA,20),CalcAmt2)+SUMIF(CalcCredit3,INDEX(PkPartyA,20),CalcAmt3))) | G44: =IF($B44="","",ROUND($E44-$F44,0)) | H44: =IF($B44="","",IF(ROUND($G44,0)>0,"بدهکار",IF(ROUND($G44,0)<0,"بستانکار","تسویه")))
A45: =IF($B45="","",36) | B45: =IF(21>NPartyA,"",IFERROR(IF(VLOOKUP(INDEX(PkPartyA,21),AcctTblA,4,0)="","(بدون نام)",VLOOKUP(INDEX(PkPartyA,21),AcctTblA,4,0)),"—")) | C45: =IF($B45="","",IF(21>NPartyA,"",INDEX(PkPartyA,21))) | D45: =IF($B45="","","p") | E45: =IF($B45="","",IF(21>NPartyA,0,SUMIF(CalcDebit,INDEX(PkPartyA,21),CalcAmt)+SUMIF(CalcDebit2,INDEX(PkPartyA,21),CalcAmt2)+SUMIF(CalcDebit3,INDEX(PkPartyA,21),CalcAmt3))) | F45: =IF($B45="","",IF(21>NPartyA,0,SUMIF(CalcCredit,INDEX(PkPartyA,21),CalcAmt)+SUMIF(CalcCredit2,INDEX(PkPartyA,21),CalcAmt2)+SUMIF(CalcCredit3,INDEX(PkPartyA,21),CalcAmt3))) | G45: =IF($B45="","",ROUND($E45-$F45,0)) | H45: =IF($B45="","",IF(ROUND($G45,0)>0,"بدهکار",IF(ROUND($G45,0)<0,"بستانکار","تسویه")))
A46: =IF($B46="","",37) | B46: =IF(22>NPartyA,"",IFERROR(IF(VLOOKUP(INDEX(PkPartyA,22),AcctTblA,4,0)="","(بدون نام)",VLOOKUP(INDEX(PkPartyA,22),AcctTblA,4,0)),"—")) | C46: =IF($B46="","",IF(22>NPartyA,"",INDEX(PkPartyA,22))) | D46: =IF($B46="","","p") | E46: =IF($B46="","",IF(22>NPartyA,0,SUMIF(CalcDebit,INDEX(PkPartyA,22),CalcAmt)+SUMIF(CalcDebit2,INDEX(PkPartyA,22),CalcAmt2)+SUMIF(CalcDebit3,INDEX(PkPartyA,22),CalcAmt3))) | F46: =IF($B46="","",IF(22>NPartyA,0,SUMIF(CalcCredit,INDEX(PkPartyA,22),CalcAmt)+SUMIF(CalcCredit2,INDEX(PkPartyA,22),CalcAmt2)+SUMIF(CalcCredit3,INDEX(PkPartyA,22),CalcAmt3))) | G46: =IF($B46="","",ROUND($E46-$F46,0)) | H46: =IF($B46="","",IF(ROUND($G46,0)>0,"بدهکار",IF(ROUND($G46,0)<0,"بستانکار","تسویه")))
A47: =IF($B47="","",38) | B47: =IF(23>NPartyA,"",IFERROR(IF(VLOOKUP(INDEX(PkPartyA,23),AcctTblA,4,0)="","(بدون نام)",VLOOKUP(INDEX(PkPartyA,23),AcctTblA,4,0)),"—")) | C47: =IF($B47="","",IF(23>NPartyA,"",INDEX(PkPartyA,23))) | D47: =IF($B47="","","p") | E47: =IF($B47="","",IF(23>NPartyA,0,SUMIF(CalcDebit,INDEX(PkPartyA,23),CalcAmt)+SUMIF(CalcDebit2,INDEX(PkPartyA,23),CalcAmt2)+SUMIF(CalcDebit3,INDEX(PkPartyA,23),CalcAmt3))) | F47: =IF($B47="","",IF(23>NPartyA,0,SUMIF(CalcCredit,INDEX(PkPartyA,23),CalcAmt)+SUMIF(CalcCredit2,INDEX(PkPartyA,23),CalcAmt2)+SUMIF(CalcCredit3,INDEX(PkPartyA,23),CalcAmt3))) | G47: =IF($B47="","",ROUND($E47-$F47,0)) | H47: =IF($B47="","",IF(ROUND($G47,0)>0,"بدهکار",IF(ROUND($G47,0)<0,"بستانکار","تسویه")))
A48: =IF($B48="","",39) | B48: =IF(24>NPartyA,"",IFERROR(IF(VLOOKUP(INDEX(PkPartyA,24),AcctTblA,4,0)="","(بدون نام)",VLOOKUP(INDEX(PkPartyA,24),AcctTblA,4,0)),"—")) | C48: =IF($B48="","",IF(24>NPartyA,"",INDEX(PkPartyA,24))) | D48: =IF($B48="","","p") | E48: =IF($B48="","",IF(24>NPartyA,0,SUMIF(CalcDebit,INDEX(PkPartyA,24),CalcAmt)+SUMIF(CalcDebit2,INDEX(PkPartyA,24),CalcAmt2)+SUMIF(CalcDebit3,INDEX(PkPartyA,24),CalcAmt3))) | F48: =IF($B48="","",IF(24>NPartyA,0,SUMIF(CalcCredit,INDEX(PkPartyA,24),CalcAmt)+SUMIF(CalcCredit2,INDEX(PkPartyA,24),CalcAmt2)+SUMIF(CalcCredit3,INDEX(PkPartyA,24),CalcAmt3))) | G48: =IF($B48="","",ROUND($E48-$F48,0)) | H48: =IF($B48="","",IF(ROUND($G48,0)>0,"بدهکار",IF(ROUND($G48,0)<0,"بستانکار","تسویه")))
A49: =IF($B49="","",40) | B49: =IF(25>NPartyA,"",IFERROR(IF(VLOOKUP(INDEX(PkPartyA,25),AcctTblA,4,0)="","(بدون نام)",VLOOKUP(INDEX(PkPartyA,25),AcctTblA,4,0)),"—")) | C49: =IF($B49="","",IF(25>NPartyA,"",INDEX(PkPartyA,25))) | D49: =IF($B49="","","p") | E49: =IF($B49="","",IF(25>NPartyA,0,SUMIF(CalcDebit,INDEX(PkPartyA,25),CalcAmt)+SUMIF(CalcDebit2,INDEX(PkPartyA,25),CalcAmt2)+SUMIF(CalcDebit3,INDEX(PkPartyA,25),CalcAmt3))) | F49: =IF($B49="","",IF(25>NPartyA,0,SUMIF(CalcCredit,INDEX(PkPartyA,25),CalcAmt)+SUMIF(CalcCredit2,INDEX(PkPartyA,25),CalcAmt2)+SUMIF(CalcCredit3,INDEX(PkPartyA,25),CalcAmt3))) | G49: =IF($B49="","",ROUND($E49-$F49,0)) | H49: =IF($B49="","",IF(ROUND($G49,0)>0,"بدهکار",IF(ROUND($G49,0)<0,"بستانکار","تسویه")))
A50: =IF($B50="","",41) | B50: =IF(26>NPartyA,"",IFERROR(IF(VLOOKUP(INDEX(PkPartyA,26),AcctTblA,4,0)="","(بدون نام)",VLOOKUP(INDEX(PkPartyA,26),AcctTblA,4,0)),"—")) | C50: =IF($B50="","",IF(26>NPartyA,"",INDEX(PkPartyA,26))) | D50: =IF($B50="","","p") | E50: =IF($B50="","",IF(26>NPartyA,0,SUMIF(CalcDebit,INDEX(PkPartyA,26),CalcAmt)+SUMIF(CalcDebit2,INDEX(PkPartyA,26),CalcAmt2)+SUMIF(CalcDebit3,INDEX(PkPartyA,26),CalcAmt3))) | F50: =IF($B50="","",IF(26>NPartyA,0,SUMIF(CalcCredit,INDEX(PkPartyA,26),CalcAmt)+SUMIF(CalcCredit2,INDEX(PkPartyA,26),CalcAmt2)+SUMIF(CalcCredit3,INDEX(PkPartyA,26),CalcAmt3))) | G50: =IF($B50="","",ROUND($E50-$F50,0)) | H50: =IF($B50="","",IF(ROUND($G50,0)>0,"بدهکار",IF(ROUND($G50,0)<0,"بستانکار","تسویه")))
A51: =IF($B51="","",42) | B51: =IF(27>NPartyA,"",IFERROR(IF(VLOOKUP(INDEX(PkPartyA,27),AcctTblA,4,0)="","(بدون نام)",VLOOKUP(INDEX(PkPartyA,27),AcctTblA,4,0)),"—")) | C51: =IF($B51="","",IF(27>NPartyA,"",INDEX(PkPartyA,27))) | D51: =IF($B51="","","p") | E51: =IF($B51="","",IF(27>NPartyA,0,SUMIF(CalcDebit,INDEX(PkPartyA,27),CalcAmt)+SUMIF(CalcDebit2,INDEX(PkPartyA,27),CalcAmt2)+SUMIF(CalcDebit3,INDEX(PkPartyA,27),CalcAmt3))) | F51: =IF($B51="","",IF(27>NPartyA,0,SUMIF(CalcCredit,INDEX(PkPartyA,27),CalcAmt)+SUMIF(CalcCredit2,INDEX(PkPartyA,27),CalcAmt2)+SUMIF(CalcCredit3,INDEX(PkPartyA,27),CalcAmt3))) | G51: =IF($B51="","",ROUND($E51-$F51,0)) | H51: =IF($B51="","",IF(ROUND($G51,0)>0,"بدهکار",IF(ROUND($G51,0)<0,"بستانکار","تسویه")))
A52: =IF($B52="","",43) | B52: =IF(28>NPartyA,"",IFERROR(IF(VLOOKUP(INDEX(PkPartyA,28),AcctTblA,4,0)="","(بدون نام)",VLOOKUP(INDEX(PkPartyA,28),AcctTblA,4,0)),"—")) | C52: =IF($B52="","",IF(28>NPartyA,"",INDEX(PkPartyA,28))) | D52: =IF($B52="","","p") | E52: =IF($B52="","",IF(28>NPartyA,0,SUMIF(CalcDebit,INDEX(PkPartyA,28),CalcAmt)+SUMIF(CalcDebit2,INDEX(PkPartyA,28),CalcAmt2)+SUMIF(CalcDebit3,INDEX(PkPartyA,28),CalcAmt3))) | F52: =IF($B52="","",IF(28>NPartyA,0,SUMIF(CalcCredit,INDEX(PkPartyA,28),CalcAmt)+SUMIF(CalcCredit2,INDEX(PkPartyA,28),CalcAmt2)+SUMIF(CalcCredit3,INDEX(PkPartyA,28),CalcAmt3))) | G52: =IF($B52="","",ROUND($E52-$F52,0)) | H52: =IF($B52="","",IF(ROUND($G52,0)>0,"بدهکار",IF(ROUND($G52,0)<0,"بستانکار","تسویه")))
A53: =IF($B53="","",44) | B53: =IF(29>NPartyA,"",IFERROR(IF(VLOOKUP(INDEX(PkPartyA,29),AcctTblA,4,0)="","(بدون نام)",VLOOKUP(INDEX(PkPartyA,29),AcctTblA,4,0)),"—")) | C53: =IF($B53="","",IF(29>NPartyA,"",INDEX(PkPartyA,29))) | D53: =IF($B53="","","p") | E53: =IF($B53="","",IF(29>NPartyA,0,SUMIF(CalcDebit,INDEX(PkPartyA,29),CalcAmt)+SUMIF(CalcDebit2,INDEX(PkPartyA,29),CalcAmt2)+SUMIF(CalcDebit3,INDEX(PkPartyA,29),CalcAmt3))) | F53: =IF($B53="","",IF(29>NPartyA,0,SUMIF(CalcCredit,INDEX(PkPartyA,29),CalcAmt)+SUMIF(CalcCredit2,INDEX(PkPartyA,29),CalcAmt2)+SUMIF(CalcCredit3,INDEX(PkPartyA,29),CalcAmt3))) | G53: =IF($B53="","",ROUND($E53-$F53,0)) | H53: =IF($B53="","",IF(ROUND($G53,0)>0,"بدهکار",IF(ROUND($G53,0)<0,"بستانکار","تسویه")))
A54: =IF($B54="","",45) | B54: =IF(30>NPartyA,"",IFERROR(IF(VLOOKUP(INDEX(PkPartyA,30),AcctTblA,4,0)="","(بدون نام)",VLOOKUP(INDEX(PkPartyA,30),AcctTblA,4,0)),"—")) | C54: =IF($B54="","",IF(30>NPartyA,"",INDEX(PkPartyA,30))) | D54: =IF($B54="","","p") | E54: =IF($B54="","",IF(30>NPartyA,0,SUMIF(CalcDebit,INDEX(PkPartyA,30),CalcAmt)+SUMIF(CalcDebit2,INDEX(PkPartyA,30),CalcAmt2)+SUMIF(CalcDebit3,INDEX(PkPartyA,30),CalcAmt3))) | F54: =IF($B54="","",IF(30>NPartyA,0,SUMIF(CalcCredit,INDEX(PkPartyA,30),CalcAmt)+SUMIF(CalcCredit2,INDEX(PkPartyA,30),CalcAmt2)+SUMIF(CalcCredit3,INDEX(PkPartyA,30),CalcAmt3))) | G54: =IF($B54="","",ROUND($E54-$F54,0)) | H54: =IF($B54="","",IF(ROUND($G54,0)>0,"بدهکار",IF(ROUND($G54,0)<0,"بستانکار","تسویه")))
A55: =IF($B55="","",46) | B55: =IF(31>NPartyA,"",IFERROR(IF(VLOOKUP(INDEX(PkPartyA,31),AcctTblA,4,0)="","(بدون نام)",VLOOKUP(INDEX(PkPartyA,31),AcctTblA,4,0)),"—")) | C55: =IF($B55="","",IF(31>NPartyA,"",INDEX(PkPartyA,31))) | D55: =IF($B55="","","p") | E55: =IF($B55="","",IF(31>NPartyA,0,SUMIF(CalcDebit,INDEX(PkPartyA,31),CalcAmt)+SUMIF(CalcDebit2,INDEX(PkPartyA,31),CalcAmt2)+SUMIF(CalcDebit3,INDEX(PkPartyA,31),CalcAmt3))) | F55: =IF($B55="","",IF(31>NPartyA,0,SUMIF(CalcCredit,INDEX(PkPartyA,31),CalcAmt)+SUMIF(CalcCredit2,INDEX(PkPartyA,31),CalcAmt2)+SUMIF(CalcCredit3,INDEX(PkPartyA,31),CalcAmt3))) | G55: =IF($B55="","",ROUND($E55-$F55,0)) | H55: =IF($B55="","",IF(ROUND($G55,0)>0,"بدهکار",IF(ROUND($G55,0)<0,"بستانکار","تسویه")))
A56: =IF($B56="","",47) | B56: =IF(32>NPartyA,"",IFERROR(IF(VLOOKUP(INDEX(PkPartyA,32),AcctTblA,4,0)="","(بدون نام)",VLOOKUP(INDEX(PkPartyA,32),AcctTblA,4,0)),"—")) | C56: =IF($B56="","",IF(32>NPartyA,"",INDEX(PkPartyA,32))) | D56: =IF($B56="","","p") | E56: =IF($B56="","",IF(32>NPartyA,0,SUMIF(CalcDebit,INDEX(PkPartyA,32),CalcAmt)+SUMIF(CalcDebit2,INDEX(PkPartyA,32),CalcAmt2)+SUMIF(CalcDebit3,INDEX(PkPartyA,32),CalcAmt3))) | F56: =IF($B56="","",IF(32>NPartyA,0,SUMIF(CalcCredit,INDEX(PkPartyA,32),CalcAmt)+SUMIF(CalcCredit2,INDEX(PkPartyA,32),CalcAmt2)+SUMIF(CalcCredit3,INDEX(PkPartyA,32),CalcAmt3))) | G56: =IF($B56="","",ROUND($E56-$F56,0)) | H56: =IF($B56="","",IF(ROUND($G56,0)>0,"بدهکار",IF(ROUND($G56,0)<0,"بستانکار","تسویه")))
A57: =IF($B57="","",48) | B57: =IF(33>NPartyA,"",IFERROR(IF(VLOOKUP(INDEX(PkPartyA,33),AcctTblA,4,0)="","(بدون نام)",VLOOKUP(INDEX(PkPartyA,33),AcctTblA,4,0)),"—")) | C57: =IF($B57="","",IF(33>NPartyA,"",INDEX(PkPartyA,33))) | D57: =IF($B57="","","p") | E57: =IF($B57="","",IF(33>NPartyA,0,SUMIF(CalcDebit,INDEX(PkPartyA,33),CalcAmt)+SUMIF(CalcDebit2,INDEX(PkPartyA,33),CalcAmt2)+SUMIF(CalcDebit3,INDEX(PkPartyA,33),CalcAmt3))) | F57: =IF($B57="","",IF(33>NPartyA,0,SUMIF(CalcCredit,INDEX(PkPartyA,33),CalcAmt)+SUMIF(CalcCredit2,INDEX(PkPartyA,33),CalcAmt2)+SUMIF(CalcCredit3,INDEX(PkPartyA,33),CalcAmt3))) | G57: =IF($B57="","",ROUND($E57-$F57,0)) | H57: =IF($B57="","",IF(ROUND($G57,0)>0,"بدهکار",IF(ROUND($G57,0)<0,"بستانکار","تسویه")))
A58: =IF($B58="","",49) | B58: =IF(34>NPartyA,"",IFERROR(IF(VLOOKUP(INDEX(PkPartyA,34),AcctTblA,4,0)="","(بدون نام)",VLOOKUP(INDEX(PkPartyA,34),AcctTblA,4,0)),"—")) | C58: =IF($B58="","",IF(34>NPartyA,"",INDEX(PkPartyA,34))) | D58: =IF($B58="","","p") | E58: =IF($B58="","",IF(34>NPartyA,0,SUMIF(CalcDebit,INDEX(PkPartyA,34),CalcAmt)+SUMIF(CalcDebit2,INDEX(PkPartyA,34),CalcAmt2)+SUMIF(CalcDebit3,INDEX(PkPartyA,34),CalcAmt3))) | F58: =IF($B58="","",IF(34>NPartyA,0,SUMIF(CalcCredit,INDEX(PkPartyA,34),CalcAmt)+SUMIF(CalcCredit2,INDEX(PkPartyA,34),CalcAmt2)+SUMIF(CalcCredit3,INDEX(PkPartyA,34),CalcAmt3))) | G58: =IF($B58="","",ROUND($E58-$F58,0)) | H58: =IF($B58="","",IF(ROUND($G58,0)>0,"بدهکار",IF(ROUND($G58,0)<0,"بستانکار","تسویه")))
A59: =IF($B59="","",50) | B59: =IF(35>NPartyA,"",IFERROR(IF(VLOOKUP(INDEX(PkPartyA,35),AcctTblA,4,0)="","(بدون نام)",VLOOKUP(INDEX(PkPartyA,35),AcctTblA,4,0)),"—")) | C59: =IF($B59="","",IF(35>NPartyA,"",INDEX(PkPartyA,35))) | D59: =IF($B59="","","p") | E59: =IF($B59="","",IF(35>NPartyA,0,SUMIF(CalcDebit,INDEX(PkPartyA,35),CalcAmt)+SUMIF(CalcDebit2,INDEX(PkPartyA,35),CalcAmt2)+SUMIF(CalcDebit3,INDEX(PkPartyA,35),CalcAmt3))) | F59: =IF($B59="","",IF(35>NPartyA,0,SUMIF(CalcCredit,INDEX(PkPartyA,35),CalcAmt)+SUMIF(CalcCredit2,INDEX(PkPartyA,35),CalcAmt2)+SUMIF(CalcCredit3,INDEX(PkPartyA,35),CalcAmt3))) | G59: =IF($B59="","",ROUND($E59-$F59,0)) | H59: =IF($B59="","",IF(ROUND($G59,0)>0,"بدهکار",IF(ROUND($G59,0)<0,"بستانکار","تسویه")))
A60: =IF($B60="","",51) | B60: =IF(36>NPartyA,"",IFERROR(IF(VLOOKUP(INDEX(PkPartyA,36),AcctTblA,4,0)="","(بدون نام)",VLOOKUP(INDEX(PkPartyA,36),AcctTblA,4,0)),"—")) | C60: =IF($B60="","",IF(36>NPartyA,"",INDEX(PkPartyA,36))) | D60: =IF($B60="","","p") | E60: =IF($B60="","",IF(36>NPartyA,0,SUMIF(CalcDebit,INDEX(PkPartyA,36),CalcAmt)+SUMIF(CalcDebit2,INDEX(PkPartyA,36),CalcAmt2)+SUMIF(CalcDebit3,INDEX(PkPartyA,36),CalcAmt3))) | F60: =IF($B60="","",IF(36>NPartyA,0,SUMIF(CalcCredit,INDEX(PkPartyA,36),CalcAmt)+SUMIF(CalcCredit2,INDEX(PkPartyA,36),CalcAmt2)+SUMIF(CalcCredit3,INDEX(PkPartyA,36),CalcAmt3))) | G60: =IF($B60="","",ROUND($E60-$F60,0)) | H60: =IF($B60="","",IF(ROUND($G60,0)>0,"بدهکار",IF(ROUND($G60,0)<0,"بستانکار","تسویه")))
A61: =IF($B61="","",52) | B61: =IF(37>NPartyA,"",IFERROR(IF(VLOOKUP(INDEX(PkPartyA,37),AcctTblA,4,0)="","(بدون نام)",VLOOKUP(INDEX(PkPartyA,37),AcctTblA,4,0)),"—")) | C61: =IF($B61="","",IF(37>NPartyA,"",INDEX(PkPartyA,37))) | D61: =IF($B61="","","p") | E61: =IF($B61="","",IF(37>NPartyA,0,SUMIF(CalcDebit,INDEX(PkPartyA,37),CalcAmt)+SUMIF(CalcDebit2,INDEX(PkPartyA,37),CalcAmt2)+SUMIF(CalcDebit3,INDEX(PkPartyA,37),CalcAmt3))) | F61: =IF($B61="","",IF(37>NPartyA,0,SUMIF(CalcCredit,INDEX(PkPartyA,37),CalcAmt)+SUMIF(CalcCredit2,INDEX(PkPartyA,37),CalcAmt2)+SUMIF(CalcCredit3,INDEX(PkPartyA,37),CalcAmt3))) | G61: =IF($B61="","",ROUND($E61-$F61,0)) | H61: =IF($B61="","",IF(ROUND($G61,0)>0,"بدهکار",IF(ROUND($G61,0)<0,"بستانکار","تسویه")))
A62: =IF($B62="","",53) | B62: =IF(38>NPartyA,"",IFERROR(IF(VLOOKUP(INDEX(PkPartyA,38),AcctTblA,4,0)="","(بدون نام)",VLOOKUP(INDEX(PkPartyA,38),AcctTblA,4,0)),"—")) | C62: =IF($B62="","",IF(38>NPartyA,"",INDEX(PkPartyA,38))) | D62: =IF($B62="","","p") | E62: =IF($B62="","",IF(38>NPartyA,0,SUMIF(CalcDebit,INDEX(PkPartyA,38),CalcAmt)+SUMIF(CalcDebit2,INDEX(PkPartyA,38),CalcAmt2)+SUMIF(CalcDebit3,INDEX(PkPartyA,38),CalcAmt3))) | F62: =IF($B62="","",IF(38>NPartyA,0,SUMIF(CalcCredit,INDEX(PkPartyA,38),CalcAmt)+SUMIF(CalcCredit2,INDEX(PkPartyA,38),CalcAmt2)+SUMIF(CalcCredit3,INDEX(PkPartyA,38),CalcAmt3))) | G62: =IF($B62="","",ROUND($E62-$F62,0)) | H62: =IF($B62="","",IF(ROUND($G62,0)>0,"بدهکار",IF(ROUND($G62,0)<0,"بستانکار","تسویه")))
A63: =IF($B63="","",54) | B63: =IF(39>NPartyA,"",IFERROR(IF(VLOOKUP(INDEX(PkPartyA,39),AcctTblA,4,0)="","(بدون نام)",VLOOKUP(INDEX(PkPartyA,39),AcctTblA,4,0)),"—")) | C63: =IF($B63="","",IF(39>NPartyA,"",INDEX(PkPartyA,39))) | D63: =IF($B63="","","p") | E63: =IF($B63="","",IF(39>NPartyA,0,SUMIF(CalcDebit,INDEX(PkPartyA,39),CalcAmt)+SUMIF(CalcDebit2,INDEX(PkPartyA,39),CalcAmt2)+SUMIF(CalcDebit3,INDEX(PkPartyA,39),CalcAmt3))) | F63: =IF($B63="","",IF(39>NPartyA,0,SUMIF(CalcCredit,INDEX(PkPartyA,39),CalcAmt)+SUMIF(CalcCredit2,INDEX(PkPartyA,39),CalcAmt2)+SUMIF(CalcCredit3,INDEX(PkPartyA,39),CalcAmt3))) | G63: =IF($B63="","",ROUND($E63-$F63,0)) | H63: =IF($B63="","",IF(ROUND($G63,0)>0,"بدهکار",IF(ROUND($G63,0)<0,"بستانکار","تسویه")))
A64: =IF($B64="","",55) | B64: =IF(40>NPartyA,"",IFERROR(IF(VLOOKUP(INDEX(PkPartyA,40),AcctTblA,4,0)="","(بدون نام)",VLOOKUP(INDEX(PkPartyA,40),AcctTblA,4,0)),"—")) | C64: =IF($B64="","",IF(40>NPartyA,"",INDEX(PkPartyA,40))) | D64: =IF($B64="","","p") | E64: =IF($B64="","",IF(40>NPartyA,0,SUMIF(CalcDebit,INDEX(PkPartyA,40),CalcAmt)+SUMIF(CalcDebit2,INDEX(PkPartyA,40),CalcAmt2)+SUMIF(CalcDebit3,INDEX(PkPartyA,40),CalcAmt3))) | F64: =IF($B64="","",IF(40>NPartyA,0,SUMIF(CalcCredit,INDEX(PkPartyA,40),CalcAmt)+SUMIF(CalcCredit2,INDEX(PkPartyA,40),CalcAmt2)+SUMIF(CalcCredit3,INDEX(PkPartyA,40),CalcAmt3))) | G64: =IF($B64="","",ROUND($E64-$F64,0)) | H64: =IF($B64="","",IF(ROUND($G64,0)>0,"بدهکار",IF(ROUND($G64,0)<0,"بستانکار","تسویه")))
A65: =IF($B65="","",56) | B65: =IF(41>NPartyA,"",IFERROR(IF(VLOOKUP(INDEX(PkPartyA,41),AcctTblA,4,0)="","(بدون نام)",VLOOKUP(INDEX(PkPartyA,41),AcctTblA,4,0)),"—")) | C65: =IF($B65="","",IF(41>NPartyA,"",INDEX(PkPartyA,41))) | D65: =IF($B65="","","p") | E65: =IF($B65="","",IF(41>NPartyA,0,SUMIF(CalcDebit,INDEX(PkPartyA,41),CalcAmt)+SUMIF(CalcDebit2,INDEX(PkPartyA,41),CalcAmt2)+SUMIF(CalcDebit3,INDEX(PkPartyA,41),CalcAmt3))) | F65: =IF($B65="","",IF(41>NPartyA,0,SUMIF(CalcCredit,INDEX(PkPartyA,41),CalcAmt)+SUMIF(CalcCredit2,INDEX(PkPartyA,41),CalcAmt2)+SUMIF(CalcCredit3,INDEX(PkPartyA,41),CalcAmt3))) | G65: =IF($B65="","",ROUND($E65-$F65,0)) | H65: =IF($B65="","",IF(ROUND($G65,0)>0,"بدهکار",IF(ROUND($G65,0)<0,"بستانکار","تسویه")))
A66: =IF($B66="","",57) | B66: =IF(42>NPartyA,"",IFERROR(IF(VLOOKUP(INDEX(PkPartyA,42),AcctTblA,4,0)="","(بدون نام)",VLOOKUP(INDEX(PkPartyA,42),AcctTblA,4,0)),"—")) | C66: =IF($B66="","",IF(42>NPartyA,"",INDEX(PkPartyA,42))) | D66: =IF($B66="","","p") | E66: =IF($B66="","",IF(42>NPartyA,0,SUMIF(CalcDebit,INDEX(PkPartyA,42),CalcAmt)+SUMIF(CalcDebit2,INDEX(PkPartyA,42),CalcAmt2)+SUMIF(CalcDebit3,INDEX(PkPartyA,42),CalcAmt3))) | F66: =IF($B66="","",IF(42>NPartyA,0,SUMIF(CalcCredit,INDEX(PkPartyA,42),CalcAmt)+SUMIF(CalcCredit2,INDEX(PkPartyA,42),CalcAmt2)+SUMIF(CalcCredit3,INDEX(PkPartyA,42),CalcAmt3))) | G66: =IF($B66="","",ROUND($E66-$F66,0)) | H66: =IF($B66="","",IF(ROUND($G66,0)>0,"بدهکار",IF(ROUND($G66,0)<0,"بستانکار","تسویه")))
A67: =IF($B67="","",58) | B67: =IF(43>NPartyA,"",IFERROR(IF(VLOOKUP(INDEX(PkPartyA,43),AcctTblA,4,0)="","(بدون نام)",VLOOKUP(INDEX(PkPartyA,43),AcctTblA,4,0)),"—")) | C67: =IF($B67="","",IF(43>NPartyA,"",INDEX(PkPartyA,43))) | D67: =IF($B67="","","p") | E67: =IF($B67="","",IF(43>NPartyA,0,SUMIF(CalcDebit,INDEX(PkPartyA,43),CalcAmt)+SUMIF(CalcDebit2,INDEX(PkPartyA,43),CalcAmt2)+SUMIF(CalcDebit3,INDEX(PkPartyA,43),CalcAmt3))) | F67: =IF($B67="","",IF(43>NPartyA,0,SUMIF(CalcCredit,INDEX(PkPartyA,43),CalcAmt)+SUMIF(CalcCredit2,INDEX(PkPartyA,43),CalcAmt2)+SUMIF(CalcCredit3,INDEX(PkPartyA,43),CalcAmt3))) | G67: =IF($B67="","",ROUND($E67-$F67,0)) | H67: =IF($B67="","",IF(ROUND($G67,0)>0,"بدهکار",IF(ROUND($G67,0)<0,"بستانکار","تسویه")))
A68: =IF($B68="","",59) | B68: =IF(44>NPartyA,"",IFERROR(IF(VLOOKUP(INDEX(PkPartyA,44),AcctTblA,4,0)="","(بدون نام)",VLOOKUP(INDEX(PkPartyA,44),AcctTblA,4,0)),"—")) | C68: =IF($B68="","",IF(44>NPartyA,"",INDEX(PkPartyA,44))) | D68: =IF($B68="","","p") | E68: =IF($B68="","",IF(44>NPartyA,0,SUMIF(CalcDebit,INDEX(PkPartyA,44),CalcAmt)+SUMIF(CalcDebit2,INDEX(PkPartyA,44),CalcAmt2)+SUMIF(CalcDebit3,INDEX(PkPartyA,44),CalcAmt3))) | F68: =IF($B68="","",IF(44>NPartyA,0,SUMIF(CalcCredit,INDEX(PkPartyA,44),CalcAmt)+SUMIF(CalcCredit2,INDEX(PkPartyA,44),CalcAmt2)+SUMIF(CalcCredit3,INDEX(PkPartyA,44),CalcAmt3))) | G68: =IF($B68="","",ROUND($E68-$F68,0)) | H68: =IF($B68="","",IF(ROUND($G68,0)>0,"بدهکار",IF(ROUND($G68,0)<0,"بستانکار","تسویه")))
A69: =IF($B69="","",60) | B69: =IF(45>NPartyA,"",IFERROR(IF(VLOOKUP(INDEX(PkPartyA,45),AcctTblA,4,0)="","(بدون نام)",VLOOKUP(INDEX(PkPartyA,45),AcctTblA,4,0)),"—")) | C69: =IF($B69="","",IF(45>NPartyA,"",INDEX(PkPartyA,45))) | D69: =IF($B69="","","p") | E69: =IF($B69="","",IF(45>NPartyA,0,SUMIF(CalcDebit,INDEX(PkPartyA,45),CalcAmt)+SUMIF(CalcDebit2,INDEX(PkPartyA,45),CalcAmt2)+SUMIF(CalcDebit3,INDEX(PkPartyA,45),CalcAmt3))) | F69: =IF($B69="","",IF(45>NPartyA,0,SUMIF(CalcCredit,INDEX(PkPartyA,45),CalcAmt)+SUMIF(CalcCredit2,INDEX(PkPartyA,45),CalcAmt2)+SUMIF(CalcCredit3,INDEX(PkPartyA,45),CalcAmt3))) | G69: =IF($B69="","",ROUND($E69-$F69,0)) | H69: =IF($B69="","",IF(ROUND($G69,0)>0,"بدهکار",IF(ROUND($G69,0)<0,"بستانکار","تسویه")))
A70: =IF($B70="","",61) | B70: =IF(46>NPartyA,"",IFERROR(IF(VLOOKUP(INDEX(PkPartyA,46),AcctTblA,4,0)="","(بدون نام)",VLOOKUP(INDEX(PkPartyA,46),AcctTblA,4,0)),"—")) | C70: =IF($B70="","",IF(46>NPartyA,"",INDEX(PkPartyA,46))) | D70: =IF($B70="","","p") | E70: =IF($B70="","",IF(46>NPartyA,0,SUMIF(CalcDebit,INDEX(PkPartyA,46),CalcAmt)+SUMIF(CalcDebit2,INDEX(PkPartyA,46),CalcAmt2)+SUMIF(CalcDebit3,INDEX(PkPartyA,46),CalcAmt3))) | F70: =IF($B70="","",IF(46>NPartyA,0,SUMIF(CalcCredit,INDEX(PkPartyA,46),CalcAmt)+SUMIF(CalcCredit2,INDEX(PkPartyA,46),CalcAmt2)+SUMIF(CalcCredit3,INDEX(PkPartyA,46),CalcAmt3))) | G70: =IF($B70="","",ROUND($E70-$F70,0)) | H70: =IF($B70="","",IF(ROUND($G70,0)>0,"بدهکار",IF(ROUND($G70,0)<0,"بستانکار","تسویه")))
A71: =IF($B71="","",62) | B71: =IF(47>NPartyA,"",IFERROR(IF(VLOOKUP(INDEX(PkPartyA,47),AcctTblA,4,0)="","(بدون نام)",VLOOKUP(INDEX(PkPartyA,47),AcctTblA,4,0)),"—")) | C71: =IF($B71="","",IF(47>NPartyA,"",INDEX(PkPartyA,47))) | D71: =IF($B71="","","p") | E71: =IF($B71="","",IF(47>NPartyA,0,SUMIF(CalcDebit,INDEX(PkPartyA,47),CalcAmt)+SUMIF(CalcDebit2,INDEX(PkPartyA,47),CalcAmt2)+SUMIF(CalcDebit3,INDEX(PkPartyA,47),CalcAmt3))) | F71: =IF($B71="","",IF(47>NPartyA,0,SUMIF(CalcCredit,INDEX(PkPartyA,47),CalcAmt)+SUMIF(CalcCredit2,INDEX(PkPartyA,47),CalcAmt2)+SUMIF(CalcCredit3,INDEX(PkPartyA,47),CalcAmt3))) | G71: =IF($B71="","",ROUND($E71-$F71,0)) | H71: =IF($B71="","",IF(ROUND($G71,0)>0,"بدهکار",IF(ROUND($G71,0)<0,"بستانکار","تسویه")))
A72: =IF($B72="","",63) | B72: =IF(48>NPartyA,"",IFERROR(IF(VLOOKUP(INDEX(PkPartyA,48),AcctTblA,4,0)="","(بدون نام)",VLOOKUP(INDEX(PkPartyA,48),AcctTblA,4,0)),"—")) | C72: =IF($B72="","",IF(48>NPartyA,"",INDEX(PkPartyA,48))) | D72: =IF($B72="","","p") | E72: =IF($B72="","",IF(48>NPartyA,0,SUMIF(CalcDebit,INDEX(PkPartyA,48),CalcAmt)+SUMIF(CalcDebit2,INDEX(PkPartyA,48),CalcAmt2)+SUMIF(CalcDebit3,INDEX(PkPartyA,48),CalcAmt3))) | F72: =IF($B72="","",IF(48>NPartyA,0,SUMIF(CalcCredit,INDEX(PkPartyA,48),CalcAmt)+SUMIF(CalcCredit2,INDEX(PkPartyA,48),CalcAmt2)+SUMIF(CalcCredit3,INDEX(PkPartyA,48),CalcAmt3))) | G72: =IF($B72="","",ROUND($E72-$F72,0)) | H72: =IF($B72="","",IF(ROUND($G72,0)>0,"بدهکار",IF(ROUND($G72,0)<0,"بستانکار","تسویه")))
A73: =IF($B73="","",64) | B73: =IF(49>NPartyA,"",IFERROR(IF(VLOOKUP(INDEX(PkPartyA,49),AcctTblA,4,0)="","(بدون نام)",VLOOKUP(INDEX(PkPartyA,49),AcctTblA,4,0)),"—")) | C73: =IF($B73="","",IF(49>NPartyA,"",INDEX(PkPartyA,49))) | D73: =IF($B73="","","p") | E73: =IF($B73="","",IF(49>NPartyA,0,SUMIF(CalcDebit,INDEX(PkPartyA,49),CalcAmt)+SUMIF(CalcDebit2,INDEX(PkPartyA,49),CalcAmt2)+SUMIF(CalcDebit3,INDEX(PkPartyA,49),CalcAmt3))) | F73: =IF($B73="","",IF(49>NPartyA,0,SUMIF(CalcCredit,INDEX(PkPartyA,49),CalcAmt)+SUMIF(CalcCredit2,INDEX(PkPartyA,49),CalcAmt2)+SUMIF(CalcCredit3,INDEX(PkPartyA,49),CalcAmt3))) | G73: =IF($B73="","",ROUND($E73-$F73,0)) | H73: =IF($B73="","",IF(ROUND($G73,0)>0,"بدهکار",IF(ROUND($G73,0)<0,"بستانکار","تسویه")))
A74: =IF($B74="","",65) | B74: =IF(50>NPartyA,"",IFERROR(IF(VLOOKUP(INDEX(PkPartyA,50),AcctTblA,4,0)="","(بدون نام)",VLOOKUP(INDEX(PkPartyA,50),AcctTblA,4,0)),"—")) | C74: =IF($B74="","",IF(50>NPartyA,"",INDEX(PkPartyA,50))) | D74: =IF($B74="","","p") | E74: =IF($B74="","",IF(50>NPartyA,0,SUMIF(CalcDebit,INDEX(PkPartyA,50),CalcAmt)+SUMIF(CalcDebit2,INDEX(PkPartyA,50),CalcAmt2)+SUMIF(CalcDebit3,INDEX(PkPartyA,50),CalcAmt3))) | F74: =IF($B74="","",IF(50>NPartyA,0,SUMIF(CalcCredit,INDEX(PkPartyA,50),CalcAmt)+SUMIF(CalcCredit2,INDEX(PkPartyA,50),CalcAmt2)+SUMIF(CalcCredit3,INDEX(PkPartyA,50),CalcAmt3))) | G74: =IF($B74="","",ROUND($E74-$F74,0)) | H74: =IF($B74="","",IF(ROUND($G74,0)>0,"بدهکار",IF(ROUND($G74,0)<0,"بستانکار","تسویه")))
A75: =IF($B75="","",66) | B75: =IF(51>NPartyA,"",IFERROR(IF(VLOOKUP(INDEX(PkPartyA,51),AcctTblA,4,0)="","(بدون نام)",VLOOKUP(INDEX(PkPartyA,51),AcctTblA,4,0)),"—")) | C75: =IF($B75="","",IF(51>NPartyA,"",INDEX(PkPartyA,51))) | D75: =IF($B75="","","p") | E75: =IF($B75="","",IF(51>NPartyA,0,SUMIF(CalcDebit,INDEX(PkPartyA,51),CalcAmt)+SUMIF(CalcDebit2,INDEX(PkPartyA,51),CalcAmt2)+SUMIF(CalcDebit3,INDEX(PkPartyA,51),CalcAmt3))) | F75: =IF($B75="","",IF(51>NPartyA,0,SUMIF(CalcCredit,INDEX(PkPartyA,51),CalcAmt)+SUMIF(CalcCredit2,INDEX(PkPartyA,51),CalcAmt2)+SUMIF(CalcCredit3,INDEX(PkPartyA,51),CalcAmt3))) | G75: =IF($B75="","",ROUND($E75-$F75,0)) | H75: =IF($B75="","",IF(ROUND($G75,0)>0,"بدهکار",IF(ROUND($G75,0)<0,"بستانکار","تسویه")))
A76: =IF($B76="","",67) | B76: =IF(52>NPartyA,"",IFERROR(IF(VLOOKUP(INDEX(PkPartyA,52),AcctTblA,4,0)="","(بدون نام)",VLOOKUP(INDEX(PkPartyA,52),AcctTblA,4,0)),"—")) | C76: =IF($B76="","",IF(52>NPartyA,"",INDEX(PkPartyA,52))) | D76: =IF($B76="","","p") | E76: =IF($B76="","",IF(52>NPartyA,0,SUMIF(CalcDebit,INDEX(PkPartyA,52),CalcAmt)+SUMIF(CalcDebit2,INDEX(PkPartyA,52),CalcAmt2)+SUMIF(CalcDebit3,INDEX(PkPartyA,52),CalcAmt3))) | F76: =IF($B76="","",IF(52>NPartyA,0,SUMIF(CalcCredit,INDEX(PkPartyA,52),CalcAmt)+SUMIF(CalcCredit2,INDEX(PkPartyA,52),CalcAmt2)+SUMIF(CalcCredit3,INDEX(PkPartyA,52),CalcAmt3))) | G76: =IF($B76="","",ROUND($E76-$F76,0)) | H76: =IF($B76="","",IF(ROUND($G76,0)>0,"بدهکار",IF(ROUND($G76,0)<0,"بستانکار","تسویه")))
A77: =IF($B77="","",68) | B77: =IF(53>NPartyA,"",IFERROR(IF(VLOOKUP(INDEX(PkPartyA,53),AcctTblA,4,0)="","(بدون نام)",VLOOKUP(INDEX(PkPartyA,53),AcctTblA,4,0)),"—")) | C77: =IF($B77="","",IF(53>NPartyA,"",INDEX(PkPartyA,53))) | D77: =IF($B77="","","p") | E77: =IF($B77="","",IF(53>NPartyA,0,SUMIF(CalcDebit,INDEX(PkPartyA,53),CalcAmt)+SUMIF(CalcDebit2,INDEX(PkPartyA,53),CalcAmt2)+SUMIF(CalcDebit3,INDEX(PkPartyA,53),CalcAmt3))) | F77: =IF($B77="","",IF(53>NPartyA,0,SUMIF(CalcCredit,INDEX(PkPartyA,53),CalcAmt)+SUMIF(CalcCredit2,INDEX(PkPartyA,53),CalcAmt2)+SUMIF(CalcCredit3,INDEX(PkPartyA,53),CalcAmt3))) | G77: =IF($B77="","",ROUND($E77-$F77,0)) | H77: =IF($B77="","",IF(ROUND($G77,0)>0,"بدهکار",IF(ROUND($G77,0)<0,"بستانکار","تسویه")))
A78: =IF($B78="","",69) | B78: =IF(54>NPartyA,"",IFERROR(IF(VLOOKUP(INDEX(PkPartyA,54),AcctTblA,4,0)="","(بدون نام)",VLOOKUP(INDEX(PkPartyA,54),AcctTblA,4,0)),"—")) | C78: =IF($B78="","",IF(54>NPartyA,"",INDEX(PkPartyA,54))) | D78: =IF($B78="","","p") | E78: =IF($B78="","",IF(54>NPartyA,0,SUMIF(CalcDebit,INDEX(PkPartyA,54),CalcAmt)+SUMIF(CalcDebit2,INDEX(PkPartyA,54),CalcAmt2)+SUMIF(CalcDebit3,INDEX(PkPartyA,54),CalcAmt3))) | F78: =IF($B78="","",IF(54>NPartyA,0,SUMIF(CalcCredit,INDEX(PkPartyA,54),CalcAmt)+SUMIF(CalcCredit2,INDEX(PkPartyA,54),CalcAmt2)+SUMIF(CalcCredit3,INDEX(PkPartyA,54),CalcAmt3))) | G78: =IF($B78="","",ROUND($E78-$F78,0)) | H78: =IF($B78="","",IF(ROUND($G78,0)>0,"بدهکار",IF(ROUND($G78,0)<0,"بستانکار","تسویه")))
A79: =IF($B79="","",70) | B79: =IF(55>NPartyA,"",IFERROR(IF(VLOOKUP(INDEX(PkPartyA,55),AcctTblA,4,0)="","(بدون نام)",VLOOKUP(INDEX(PkPartyA,55),AcctTblA,4,0)),"—")) | C79: =IF($B79="","",IF(55>NPartyA,"",INDEX(PkPartyA,55))) | D79: =IF($B79="","","p") | E79: =IF($B79="","",IF(55>NPartyA,0,SUMIF(CalcDebit,INDEX(PkPartyA,55),CalcAmt)+SUMIF(CalcDebit2,INDEX(PkPartyA,55),CalcAmt2)+SUMIF(CalcDebit3,INDEX(PkPartyA,55),CalcAmt3))) | F79: =IF($B79="","",IF(55>NPartyA,0,SUMIF(CalcCredit,INDEX(PkPartyA,55),CalcAmt)+SUMIF(CalcCredit2,INDEX(PkPartyA,55),CalcAmt2)+SUMIF(CalcCredit3,INDEX(PkPartyA,55),CalcAmt3))) | G79: =IF($B79="","",ROUND($E79-$F79,0)) | H79: =IF($B79="","",IF(ROUND($G79,0)>0,"بدهکار",IF(ROUND($G79,0)<0,"بستانکار","تسویه")))
A80: =IF($B80="","",71) | B80: =IF(56>NPartyA,"",IFERROR(IF(VLOOKUP(INDEX(PkPartyA,56),AcctTblA,4,0)="","(بدون نام)",VLOOKUP(INDEX(PkPartyA,56),AcctTblA,4,0)),"—")) | C80: =IF($B80="","",IF(56>NPartyA,"",INDEX(PkPartyA,56))) | D80: =IF($B80="","","p") | E80: =IF($B80="","",IF(56>NPartyA,0,SUMIF(CalcDebit,INDEX(PkPartyA,56),CalcAmt)+SUMIF(CalcDebit2,INDEX(PkPartyA,56),CalcAmt2)+SUMIF(CalcDebit3,INDEX(PkPartyA,56),CalcAmt3))) | F80: =IF($B80="","",IF(56>NPartyA,0,SUMIF(CalcCredit,INDEX(PkPartyA,56),CalcAmt)+SUMIF(CalcCredit2,INDEX(PkPartyA,56),CalcAmt2)+SUMIF(CalcCredit3,INDEX(PkPartyA,56),CalcAmt3))) | G80: =IF($B80="","",ROUND($E80-$F80,0)) | H80: =IF($B80="","",IF(ROUND($G80,0)>0,"بدهکار",IF(ROUND($G80,0)<0,"بستانکار","تسویه")))
A81: =IF($B81="","",72) | B81: =IF(57>NPartyA,"",IFERROR(IF(VLOOKUP(INDEX(PkPartyA,57),AcctTblA,4,0)="","(بدون نام)",VLOOKUP(INDEX(PkPartyA,57),AcctTblA,4,0)),"—")) | C81: =IF($B81="","",IF(57>NPartyA,"",INDEX(PkPartyA,57))) | D81: =IF($B81="","","p") | E81: =IF($B81="","",IF(57>NPartyA,0,SUMIF(CalcDebit,INDEX(PkPartyA,57),CalcAmt)+SUMIF(CalcDebit2,INDEX(PkPartyA,57),CalcAmt2)+SUMIF(CalcDebit3,INDEX(PkPartyA,57),CalcAmt3))) | F81: =IF($B81="","",IF(57>NPartyA,0,SUMIF(CalcCredit,INDEX(PkPartyA,57),CalcAmt)+SUMIF(CalcCredit2,INDEX(PkPartyA,57),CalcAmt2)+SUMIF(CalcCredit3,INDEX(PkPartyA,57),CalcAmt3))) | G81: =IF($B81="","",ROUND($E81-$F81,0)) | H81: =IF($B81="","",IF(ROUND($G81,0)>0,"بدهکار",IF(ROUND($G81,0)<0,"بستانکار","تسویه")))
A82: =IF($B82="","",73) | B82: =IF(58>NPartyA,"",IFERROR(IF(VLOOKUP(INDEX(PkPartyA,58),AcctTblA,4,0)="","(بدون نام)",VLOOKUP(INDEX(PkPartyA,58),AcctTblA,4,0)),"—")) | C82: =IF($B82="","",IF(58>NPartyA,"",INDEX(PkPartyA,58))) | D82: =IF($B82="","","p") | E82: =IF($B82="","",IF(58>NPartyA,0,SUMIF(CalcDebit,INDEX(PkPartyA,58),CalcAmt)+SUMIF(CalcDebit2,INDEX(PkPartyA,58),CalcAmt2)+SUMIF(CalcDebit3,INDEX(PkPartyA,58),CalcAmt3))) | F82: =IF($B82="","",IF(58>NPartyA,0,SUMIF(CalcCredit,INDEX(PkPartyA,58),CalcAmt)+SUMIF(CalcCredit2,INDEX(PkPartyA,58),CalcAmt2)+SUMIF(CalcCredit3,INDEX(PkPartyA,58),CalcAmt3))) | G82: =IF($B82="","",ROUND($E82-$F82,0)) | H82: =IF($B82="","",IF(ROUND($G82,0)>0,"بدهکار",IF(ROUND($G82,0)<0,"بستانکار","تسویه")))
A83: =IF($B83="","",74) | B83: =IF(59>NPartyA,"",IFERROR(IF(VLOOKUP(INDEX(PkPartyA,59),AcctTblA,4,0)="","(بدون نام)",VLOOKUP(INDEX(PkPartyA,59),AcctTblA,4,0)),"—")) | C83: =IF($B83="","",IF(59>NPartyA,"",INDEX(PkPartyA,59))) | D83: =IF($B83="","","p") | E83: =IF($B83="","",IF(59>NPartyA,0,SUMIF(CalcDebit,INDEX(PkPartyA,59),CalcAmt)+SUMIF(CalcDebit2,INDEX(PkPartyA,59),CalcAmt2)+SUMIF(CalcDebit3,INDEX(PkPartyA,59),CalcAmt3))) | F83: =IF($B83="","",IF(59>NPartyA,0,SUMIF(CalcCredit,INDEX(PkPartyA,59),CalcAmt)+SUMIF(CalcCredit2,INDEX(PkPartyA,59),CalcAmt2)+SUMIF(CalcCredit3,INDEX(PkPartyA,59),CalcAmt3))) | G83: =IF($B83="","",ROUND($E83-$F83,0)) | H83: =IF($B83="","",IF(ROUND($G83,0)>0,"بدهکار",IF(ROUND($G83,0)<0,"بستانکار","تسویه")))
A84: =IF($B84="","",75) | B84: =IF(60>NPartyA,"",IFERROR(IF(VLOOKUP(INDEX(PkPartyA,60),AcctTblA,4,0)="","(بدون نام)",VLOOKUP(INDEX(PkPartyA,60),AcctTblA,4,0)),"—")) | C84: =IF($B84="","",IF(60>NPartyA,"",INDEX(PkPartyA,60))) | D84: =IF($B84="","","p") | E84: =IF($B84="","",IF(60>NPartyA,0,SUMIF(CalcDebit,INDEX(PkPartyA,60),CalcAmt)+SUMIF(CalcDebit2,INDEX(PkPartyA,60),CalcAmt2)+SUMIF(CalcDebit3,INDEX(PkPartyA,60),CalcAmt3))) | F84: =IF($B84="","",IF(60>NPartyA,0,SUMIF(CalcCredit,INDEX(PkPartyA,60),CalcAmt)+SUMIF(CalcCredit2,INDEX(PkPartyA,60),CalcAmt2)+SUMIF(CalcCredit3,INDEX(PkPartyA,60),CalcAmt3))) | G84: =IF($B84="","",ROUND($E84-$F84,0)) | H84: =IF($B84="","",IF(ROUND($G84,0)>0,"بدهکار",IF(ROUND($G84,0)<0,"بستانکار","تسویه")))
A85: =IF($B85="","",76) | B85: =IF(61>NPartyA,"",IFERROR(IF(VLOOKUP(INDEX(PkPartyA,61),AcctTblA,4,0)="","(بدون نام)",VLOOKUP(INDEX(PkPartyA,61),AcctTblA,4,0)),"—")) | C85: =IF($B85="","",IF(61>NPartyA,"",INDEX(PkPartyA,61))) | D85: =IF($B85="","","p") | E85: =IF($B85="","",IF(61>NPartyA,0,SUMIF(CalcDebit,INDEX(PkPartyA,61),CalcAmt)+SUMIF(CalcDebit2,INDEX(PkPartyA,61),CalcAmt2)+SUMIF(CalcDebit3,INDEX(PkPartyA,61),CalcAmt3))) | F85: =IF($B85="","",IF(61>NPartyA,0,SUMIF(CalcCredit,INDEX(PkPartyA,61),CalcAmt)+SUMIF(CalcCredit2,INDEX(PkPartyA,61),CalcAmt2)+SUMIF(CalcCredit3,INDEX(PkPartyA,61),CalcAmt3))) | G85: =IF($B85="","",ROUND($E85-$F85,0)) | H85: =IF($B85="","",IF(ROUND($G85,0)>0,"بدهکار",IF(ROUND($G85,0)<0,"بستانکار","تسویه")))
A86: =IF($B86="","",77) | B86: =IF(62>NPartyA,"",IFERROR(IF(VLOOKUP(INDEX(PkPartyA,62),AcctTblA,4,0)="","(بدون نام)",VLOOKUP(INDEX(PkPartyA,62),AcctTblA,4,0)),"—")) | C86: =IF($B86="","",IF(62>NPartyA,"",INDEX(PkPartyA,62))) | D86: =IF($B86="","","p") | E86: =IF($B86="","",IF(62>NPartyA,0,SUMIF(CalcDebit,INDEX(PkPartyA,62),CalcAmt)+SUMIF(CalcDebit2,INDEX(PkPartyA,62),CalcAmt2)+SUMIF(CalcDebit3,INDEX(PkPartyA,62),CalcAmt3))) | F86: =IF($B86="","",IF(62>NPartyA,0,SUMIF(CalcCredit,INDEX(PkPartyA,62),CalcAmt)+SUMIF(CalcCredit2,INDEX(PkPartyA,62),CalcAmt2)+SUMIF(CalcCredit3,INDEX(PkPartyA,62),CalcAmt3))) | G86: =IF($B86="","",ROUND($E86-$F86,0)) | H86: =IF($B86="","",IF(ROUND($G86,0)>0,"بدهکار",IF(ROUND($G86,0)<0,"بستانکار","تسویه")))
A87: =IF($B87="","",78) | B87: =IF(63>NPartyA,"",IFERROR(IF(VLOOKUP(INDEX(PkPartyA,63),AcctTblA,4,0)="","(بدون نام)",VLOOKUP(INDEX(PkPartyA,63),AcctTblA,4,0)),"—")) | C87: =IF($B87="","",IF(63>NPartyA,"",INDEX(PkPartyA,63))) | D87: =IF($B87="","","p") | E87: =IF($B87="","",IF(63>NPartyA,0,SUMIF(CalcDebit,INDEX(PkPartyA,63),CalcAmt)+SUMIF(CalcDebit2,INDEX(PkPartyA,63),CalcAmt2)+SUMIF(CalcDebit3,INDEX(PkPartyA,63),CalcAmt3))) | F87: =IF($B87="","",IF(63>NPartyA,0,SUMIF(CalcCredit,INDEX(PkPartyA,63),CalcAmt)+SUMIF(CalcCredit2,INDEX(PkPartyA,63),CalcAmt2)+SUMIF(CalcCredit3,INDEX(PkPartyA,63),CalcAmt3))) | G87: =IF($B87="","",ROUND($E87-$F87,0)) | H87: =IF($B87="","",IF(ROUND($G87,0)>0,"بدهکار",IF(ROUND($G87,0)<0,"بستانکار","تسویه")))
A88: =IF($B88="","",79) | B88: =IF(64>NPartyA,"",IFERROR(IF(VLOOKUP(INDEX(PkPartyA,64),AcctTblA,4,0)="","(بدون نام)",VLOOKUP(INDEX(PkPartyA,64),AcctTblA,4,0)),"—")) | C88: =IF($B88="","",IF(64>NPartyA,"",INDEX(PkPartyA,64))) | D88: =IF($B88="","","p") | E88: =IF($B88="","",IF(64>NPartyA,0,SUMIF(CalcDebit,INDEX(PkPartyA,64),CalcAmt)+SUMIF(CalcDebit2,INDEX(PkPartyA,64),CalcAmt2)+SUMIF(CalcDebit3,INDEX(PkPartyA,64),CalcAmt3))) | F88: =IF($B88="","",IF(64>NPartyA,0,SUMIF(CalcCredit,INDEX(PkPartyA,64),CalcAmt)+SUMIF(CalcCredit2,INDEX(PkPartyA,64),CalcAmt2)+SUMIF(CalcCredit3,INDEX(PkPartyA,64),CalcAmt3))) | G88: =IF($B88="","",ROUND($E88-$F88,0)) | H88: =IF($B88="","",IF(ROUND($G88,0)>0,"بدهکار",IF(ROUND($G88,0)<0,"بستانکار","تسویه")))
A89: =IF($B89="","",80) | B89: =IF(65>NPartyA,"",IFERROR(IF(VLOOKUP(INDEX(PkPartyA,65),AcctTblA,4,0)="","(بدون نام)",VLOOKUP(INDEX(PkPartyA,65),AcctTblA,4,0)),"—")) | C89: =IF($B89="","",IF(65>NPartyA,"",INDEX(PkPartyA,65))) | D89: =IF($B89="","","p") | E89: =IF($B89="","",IF(65>NPartyA,0,SUMIF(CalcDebit,INDEX(PkPartyA,65),CalcAmt)+SUMIF(CalcDebit2,INDEX(PkPartyA,65),CalcAmt2)+SUMIF(CalcDebit3,INDEX(PkPartyA,65),CalcAmt3))) | F89: =IF($B89="","",IF(65>NPartyA,0,SUMIF(CalcCredit,INDEX(PkPartyA,65),CalcAmt)+SUMIF(CalcCredit2,INDEX(PkPartyA,65),CalcAmt2)+SUMIF(CalcCredit3,INDEX(PkPartyA,65),CalcAmt3))) | G89: =IF($B89="","",ROUND($E89-$F89,0)) | H89: =IF($B89="","",IF(ROUND($G89,0)>0,"بدهکار",IF(ROUND($G89,0)<0,"بستانکار","تسویه")))
A90: =IF($B90="","",81) | B90: =IF(66>NPartyA,"",IFERROR(IF(VLOOKUP(INDEX(PkPartyA,66),AcctTblA,4,0)="","(بدون نام)",VLOOKUP(INDEX(PkPartyA,66),AcctTblA,4,0)),"—")) | C90: =IF($B90="","",IF(66>NPartyA,"",INDEX(PkPartyA,66))) | D90: =IF($B90="","","p") | E90: =IF($B90="","",IF(66>NPartyA,0,SUMIF(CalcDebit,INDEX(PkPartyA,66),CalcAmt)+SUMIF(CalcDebit2,INDEX(PkPartyA,66),CalcAmt2)+SUMIF(CalcDebit3,INDEX(PkPartyA,66),CalcAmt3))) | F90: =IF($B90="","",IF(66>NPartyA,0,SUMIF(CalcCredit,INDEX(PkPartyA,66),CalcAmt)+SUMIF(CalcCredit2,INDEX(PkPartyA,66),CalcAmt2)+SUMIF(CalcCredit3,INDEX(PkPartyA,66),CalcAmt3))) | G90: =IF($B90="","",ROUND($E90-$F90,0)) | H90: =IF($B90="","",IF(ROUND($G90,0)>0,"بدهکار",IF(ROUND($G90,0)<0,"بستانکار","تسویه")))
A91: =IF($B91="","",82) | B91: =IF(67>NPartyA,"",IFERROR(IF(VLOOKUP(INDEX(PkPartyA,67),AcctTblA,4,0)="","(بدون نام)",VLOOKUP(INDEX(PkPartyA,67),AcctTblA,4,0)),"—")) | C91: =IF($B91="","",IF(67>NPartyA,"",INDEX(PkPartyA,67))) | D91: =IF($B91="","","p") | E91: =IF($B91="","",IF(67>NPartyA,0,SUMIF(CalcDebit,INDEX(PkPartyA,67),CalcAmt)+SUMIF(CalcDebit2,INDEX(PkPartyA,67),CalcAmt2)+SUMIF(CalcDebit3,INDEX(PkPartyA,67),CalcAmt3))) | F91: =IF($B91="","",IF(67>NPartyA,0,SUMIF(CalcCredit,INDEX(PkPartyA,67),CalcAmt)+SUMIF(CalcCredit2,INDEX(PkPartyA,67),CalcAmt2)+SUMIF(CalcCredit3,INDEX(PkPartyA,67),CalcAmt3))) | G91: =IF($B91="","",ROUND($E91-$F91,0)) | H91: =IF($B91="","",IF(ROUND($G91,0)>0,"بدهکار",IF(ROUND($G91,0)<0,"بستانکار","تسویه")))
A92: =IF($B92="","",83) | B92: =IF(68>NPartyA,"",IFERROR(IF(VLOOKUP(INDEX(PkPartyA,68),AcctTblA,4,0)="","(بدون نام)",VLOOKUP(INDEX(PkPartyA,68),AcctTblA,4,0)),"—")) | C92: =IF($B92="","",IF(68>NPartyA,"",INDEX(PkPartyA,68))) | D92: =IF($B92="","","p") | E92: =IF($B92="","",IF(68>NPartyA,0,SUMIF(CalcDebit,INDEX(PkPartyA,68),CalcAmt)+SUMIF(CalcDebit2,INDEX(PkPartyA,68),CalcAmt2)+SUMIF(CalcDebit3,INDEX(PkPartyA,68),CalcAmt3))) | F92: =IF($B92="","",IF(68>NPartyA,0,SUMIF(CalcCredit,INDEX(PkPartyA,68),CalcAmt)+SUMIF(CalcCredit2,INDEX(PkPartyA,68),CalcAmt2)+SUMIF(CalcCredit3,INDEX(PkPartyA,68),CalcAmt3))) | G92: =IF($B92="","",ROUND($E92-$F92,0)) | H92: =IF($B92="","",IF(ROUND($G92,0)>0,"بدهکار",IF(ROUND($G92,0)<0,"بستانکار","تسویه")))
A93: =IF($B93="","",84) | B93: =IF(69>NPartyA,"",IFERROR(IF(VLOOKUP(INDEX(PkPartyA,69),AcctTblA,4,0)="","(بدون نام)",VLOOKUP(INDEX(PkPartyA,69),AcctTblA,4,0)),"—")) | C93: =IF($B93="","",IF(69>NPartyA,"",INDEX(PkPartyA,69))) | D93: =IF($B93="","","p") | E93: =IF($B93="","",IF(69>NPartyA,0,SUMIF(CalcDebit,INDEX(PkPartyA,69),CalcAmt)+SUMIF(CalcDebit2,INDEX(PkPartyA,69),CalcAmt2)+SUMIF(CalcDebit3,INDEX(PkPartyA,69),CalcAmt3))) | F93: =IF($B93="","",IF(69>NPartyA,0,SUMIF(CalcCredit,INDEX(PkPartyA,69),CalcAmt)+SUMIF(CalcCredit2,INDEX(PkPartyA,69),CalcAmt2)+SUMIF(CalcCredit3,INDEX(PkPartyA,69),CalcAmt3))) | G93: =IF($B93="","",ROUND($E93-$F93,0)) | H93: =IF($B93="","",IF(ROUND($G93,0)>0,"بدهکار",IF(ROUND($G93,0)<0,"بستانکار","تسویه")))
A94: =IF($B94="","",85) | B94: =IF(70>NPartyA,"",IFERROR(IF(VLOOKUP(INDEX(PkPartyA,70),AcctTblA,4,0)="","(بدون نام)",VLOOKUP(INDEX(PkPartyA,70),AcctTblA,4,0)),"—")) | C94: =IF($B94="","",IF(70>NPartyA,"",INDEX(PkPartyA,70))) | D94: =IF($B94="","","p") | E94: =IF($B94="","",IF(70>NPartyA,0,SUMIF(CalcDebit,INDEX(PkPartyA,70),CalcAmt)+SUMIF(CalcDebit2,INDEX(PkPartyA,70),CalcAmt2)+SUMIF(CalcDebit3,INDEX(PkPartyA,70),CalcAmt3))) | F94: =IF($B94="","",IF(70>NPartyA,0,SUMIF(CalcCredit,INDEX(PkPartyA,70),CalcAmt)+SUMIF(CalcCredit2,INDEX(PkPartyA,70),CalcAmt2)+SUMIF(CalcCredit3,INDEX(PkPartyA,70),CalcAmt3))) | G94: =IF($B94="","",ROUND($E94-$F94,0)) | H94: =IF($B94="","",IF(ROUND($G94,0)>0,"بدهکار",IF(ROUND($G94,0)<0,"بستانکار","تسویه")))
A95: =IF($B95="","",86) | B95: =IF(71>NPartyA,"",IFERROR(IF(VLOOKUP(INDEX(PkPartyA,71),AcctTblA,4,0)="","(بدون نام)",VLOOKUP(INDEX(PkPartyA,71),AcctTblA,4,0)),"—")) | C95: =IF($B95="","",IF(71>NPartyA,"",INDEX(PkPartyA,71))) | D95: =IF($B95="","","p") | E95: =IF($B95="","",IF(71>NPartyA,0,SUMIF(CalcDebit,INDEX(PkPartyA,71),CalcAmt)+SUMIF(CalcDebit2,INDEX(PkPartyA,71),CalcAmt2)+SUMIF(CalcDebit3,INDEX(PkPartyA,71),CalcAmt3))) | F95: =IF($B95="","",IF(71>NPartyA,0,SUMIF(CalcCredit,INDEX(PkPartyA,71),CalcAmt)+SUMIF(CalcCredit2,INDEX(PkPartyA,71),CalcAmt2)+SUMIF(CalcCredit3,INDEX(PkPartyA,71),CalcAmt3))) | G95: =IF($B95="","",ROUND($E95-$F95,0)) | H95: =IF($B95="","",IF(ROUND($G95,0)>0,"بدهکار",IF(ROUND($G95,0)<0,"بستانکار","تسویه")))
A96: =IF($B96="","",87) | B96: =IF(72>NPartyA,"",IFERROR(IF(VLOOKUP(INDEX(PkPartyA,72),AcctTblA,4,0)="","(بدون نام)",VLOOKUP(INDEX(PkPartyA,72),AcctTblA,4,0)),"—")) | C96: =IF($B96="","",IF(72>NPartyA,"",INDEX(PkPartyA,72))) | D96: =IF($B96="","","p") | E96: =IF($B96="","",IF(72>NPartyA,0,SUMIF(CalcDebit,INDEX(PkPartyA,72),CalcAmt)+SUMIF(CalcDebit2,INDEX(PkPartyA,72),CalcAmt2)+SUMIF(CalcDebit3,INDEX(PkPartyA,72),CalcAmt3))) | F96: =IF($B96="","",IF(72>NPartyA,0,SUMIF(CalcCredit,INDEX(PkPartyA,72),CalcAmt)+SUMIF(CalcCredit2,INDEX(PkPartyA,72),CalcAmt2)+SUMIF(CalcCredit3,INDEX(PkPartyA,72),CalcAmt3))) | G96: =IF($B96="","",ROUND($E96-$F96,0)) | H96: =IF($B96="","",IF(ROUND($G96,0)>0,"بدهکار",IF(ROUND($G96,0)<0,"بستانکار","تسویه")))
A97: =IF($B97="","",88) | B97: =IF(73>NPartyA,"",IFERROR(IF(VLOOKUP(INDEX(PkPartyA,73),AcctTblA,4,0)="","(بدون نام)",VLOOKUP(INDEX(PkPartyA,73),AcctTblA,4,0)),"—")) | C97: =IF($B97="","",IF(73>NPartyA,"",INDEX(PkPartyA,73))) | D97: =IF($B97="","","p") | E97: =IF($B97="","",IF(73>NPartyA,0,SUMIF(CalcDebit,INDEX(PkPartyA,73),CalcAmt)+SUMIF(CalcDebit2,INDEX(PkPartyA,73),CalcAmt2)+SUMIF(CalcDebit3,INDEX(PkPartyA,73),CalcAmt3))) | F97: =IF($B97="","",IF(73>NPartyA,0,SUMIF(CalcCredit,INDEX(PkPartyA,73),CalcAmt)+SUMIF(CalcCredit2,INDEX(PkPartyA,73),CalcAmt2)+SUMIF(CalcCredit3,INDEX(PkPartyA,73),CalcAmt3))) | G97: =IF($B97="","",ROUND($E97-$F97,0)) | H97: =IF($B97="","",IF(ROUND($G97,0)>0,"بدهکار",IF(ROUND($G97,0)<0,"بستانکار","تسویه")))
A98: =IF($B98="","",89) | B98: =IF(74>NPartyA,"",IFERROR(IF(VLOOKUP(INDEX(PkPartyA,74),AcctTblA,4,0)="","(بدون نام)",VLOOKUP(INDEX(PkPartyA,74),AcctTblA,4,0)),"—")) | C98: =IF($B98="","",IF(74>NPartyA,"",INDEX(PkPartyA,74))) | D98: =IF($B98="","","p") | E98: =IF($B98="","",IF(74>NPartyA,0,SUMIF(CalcDebit,INDEX(PkPartyA,74),CalcAmt)+SUMIF(CalcDebit2,INDEX(PkPartyA,74),CalcAmt2)+SUMIF(CalcDebit3,INDEX(PkPartyA,74),CalcAmt3))) | F98: =IF($B98="","",IF(74>NPartyA,0,SUMIF(CalcCredit,INDEX(PkPartyA,74),CalcAmt)+SUMIF(CalcCredit2,INDEX(PkPartyA,74),CalcAmt2)+SUMIF(CalcCredit3,INDEX(PkPartyA,74),CalcAmt3))) | G98: =IF($B98="","",ROUND($E98-$F98,0)) | H98: =IF($B98="","",IF(ROUND($G98,0)>0,"بدهکار",IF(ROUND($G98,0)<0,"بستانکار","تسویه")))
A99: =IF($B99="","",90) | B99: =IF(75>NPartyA,"",IFERROR(IF(VLOOKUP(INDEX(PkPartyA,75),AcctTblA,4,0)="","(بدون نام)",VLOOKUP(INDEX(PkPartyA,75),AcctTblA,4,0)),"—")) | C99: =IF($B99="","",IF(75>NPartyA,"",INDEX(PkPartyA,75))) | D99: =IF($B99="","","p") | E99: =IF($B99="","",IF(75>NPartyA,0,SUMIF(CalcDebit,INDEX(PkPartyA,75),CalcAmt)+SUMIF(CalcDebit2,INDEX(PkPartyA,75),CalcAmt2)+SUMIF(CalcDebit3,INDEX(PkPartyA,75),CalcAmt3))) | F99: =IF($B99="","",IF(75>NPartyA,0,SUMIF(CalcCredit,INDEX(PkPartyA,75),CalcAmt)+SUMIF(CalcCredit2,INDEX(PkPartyA,75),CalcAmt2)+SUMIF(CalcCredit3,INDEX(PkPartyA,75),CalcAmt3))) | G99: =IF($B99="","",ROUND($E99-$F99,0)) | H99: =IF($B99="","",IF(ROUND($G99,0)>0,"بدهکار",IF(ROUND($G99,0)<0,"بستانکار","تسویه")))
A100: =IF($B100="","",91) | B100: =IF(76>NPartyA,"",IFERROR(IF(VLOOKUP(INDEX(PkPartyA,76),AcctTblA,4,0)="","(بدون نام)",VLOOKUP(INDEX(PkPartyA,76),AcctTblA,4,0)),"—")) | C100: =IF($B100="","",IF(76>NPartyA,"",INDEX(PkPartyA,76))) | D100: =IF($B100="","","p") | E100: =IF($B100="","",IF(76>NPartyA,0,SUMIF(CalcDebit,INDEX(PkPartyA,76),CalcAmt)+SUMIF(CalcDebit2,INDEX(PkPartyA,76),CalcAmt2)+SUMIF(CalcDebit3,INDEX(PkPartyA,76),CalcAmt3))) | F100: =IF($B100="","",IF(76>NPartyA,0,SUMIF(CalcCredit,INDEX(PkPartyA,76),CalcAmt)+SUMIF(CalcCredit2,INDEX(PkPartyA,76),CalcAmt2)+SUMIF(CalcCredit3,INDEX(PkPartyA,76),CalcAmt3))) | G100: =IF($B100="","",ROUND($E100-$F100,0)) | H100: =IF($B100="","",IF(ROUND($G100,0)>0,"بدهکار",IF(ROUND($G100,0)<0,"بستانکار","تسویه")))
A101: =IF($B101="","",92) | B101: =IF(77>NPartyA,"",IFERROR(IF(VLOOKUP(INDEX(PkPartyA,77),AcctTblA,4,0)="","(بدون نام)",VLOOKUP(INDEX(PkPartyA,77),AcctTblA,4,0)),"—")) | C101: =IF($B101="","",IF(77>NPartyA,"",INDEX(PkPartyA,77))) | D101: =IF($B101="","","p") | E101: =IF($B101="","",IF(77>NPartyA,0,SUMIF(CalcDebit,INDEX(PkPartyA,77),CalcAmt)+SUMIF(CalcDebit2,INDEX(PkPartyA,77),CalcAmt2)+SUMIF(CalcDebit3,INDEX(PkPartyA,77),CalcAmt3))) | F101: =IF($B101="","",IF(77>NPartyA,0,SUMIF(CalcCredit,INDEX(PkPartyA,77),CalcAmt)+SUMIF(CalcCredit2,INDEX(PkPartyA,77),CalcAmt2)+SUMIF(CalcCredit3,INDEX(PkPartyA,77),CalcAmt3))) | G101: =IF($B101="","",ROUND($E101-$F101,0)) | H101: =IF($B101="","",IF(ROUND($G101,0)>0,"بدهکار",IF(ROUND($G101,0)<0,"بستانکار","تسویه")))
...

Sheet Balance
A1: =IF(Sync!$P$6="","مازندشت",Sync!$P$6)&" — "&IF(Sync!$P$9="","سورتینگ و بسته‌بندی مرکبات",Sync!$P$9)
A2: =IF(Sync!$P$7="","باغدشت، بخش مرکزی، شهرستان قائم‌شهر، استان مازندران، ایران",Sync!$P$7)&" | MAZANDASHT · CITRUS SORTING & PACKING"
A3: ترازنامه گزارشی — از تراکنش‌ها و چک‌های پرداختی (خودکار)
A4: دارایی = نقد بانک‌ها + طلب اشخاص + سبد و ظروف + دارایی‌های ثابت (F…) · بدهی = دیون اشخاص + چک‌های پاس‌نشده + وام‌ها (L…) + متفرقه · حقوق صاحبان = افتتاحیه + سرمایه و آورده (CAP…) − هزینه‌های دوره − تراکنش‌های شخصی. ستون «درصد از جمع» سهم هر ردیف از جمع همان بخش است؛ ستون «دوره قبل» اختیاری و دستی است (برای ترازنامه تطبیقی، ارقام پایان دوره قبل را بنویسید) تا ستون «اختلاف» خودکار محاسبه شود. ارقام جاری از شیت Trial (تراز آزمایشی) جمع می‌شوند — پس از تغییر تراکنش‌ها: Data ← Edit Links ← Update Values.
A5: جمع دارایی‌ها (ریال) | C5: جمع بدهی‌ها (ریال) | E5: حقوق صاحبان (ریال) | G5: کنترل ترازنامه | I5: نسبت جاری (پوشش بدهی کوتاه‌مدت)
A6: =E15 | C6: =E21 | E6: =E27 | G6: =IF(ROUND(E15-(E21+E27),0)=0,"√ تراز است","▲ مغایرت") | I6: =IFERROR(ROUND((E11+E12)/(E17+E18+E20),2),"—")
A8: واریزهای فروش (ریال) | C8: برداشت‌های خرید (ریال) | E8: هزینه‌های دوره (ریال) | G8: چک‌های پاس‌نشده (ریال) | I8: سود نقدی دوره (تقریبی)
A9: =SUMIF(CalcGroup,"فروش",CalcDep) | C9: =SUMIF(CalcGroup,"خرید",CalcWit) | E9: =SUMIF(CalcGroup,"هزینه",CalcWit)-SUMIF(CalcGroup,"هزینه",CalcDep) | G9: =-SUMIFS(TrialBal,TrialType,"q") | I9: =SUMIF(CalcGroup,"فروش",CalcDep)-SUMIF(CalcGroup,"خرید",CalcWit)-(SUMIF(CalcGroup,"هزینه",CalcWit)-SUMIF(CalcGroup,"هزینه",CalcDep))
A10: بخش | B10: شرح | D10: کد طبقه | E10: مبلغ (ریال) | F10: ٪ از جمع | G10: دوره قبل (دستی) | H10: اختلاف با دوره قبل
A11: دارایی | B11: موجودی نقدی بانک‌ها | D11: b | E11: =SUMIFS(TrialBal,TrialType,"b") | F11: =IFERROR(E11/E$15,"") | H11: =IF($G11="","",E11-$G11)
A12: دارایی | B12: طلب از اشخاص (مانده بدهکار / پیش‌پرداخت) | D12: p+ | E12: =SUMIFS(TrialBal,TrialType,"p",TrialBal,">0") | F12: =IFERROR(E12/E$15,"") | H12: =IF($G12="","",E12-$G12)
A13: دارایی | B13: سبد و ظروف (دفتر Baskets) | D13: s | E13: =SUMIFS(TrialBal,TrialType,"s") | F13: =IFERROR(E13/E$15,"") | H13: =IF($G13="","",E13-$G13)
A14: دارایی | B14: دارایی‌های ثابت — زمین، خودرو، تجهیزات (F…) | D14: f | E14: =SUMIFS(TrialBal,TrialType,"f") | F14: =IFERROR(E14/E$15,"") | H14: =IF($G14="","",E14-$G14)
A15: جمع دارایی‌ها | E15: =SUM(E11:E14) | F15: =IFERROR(E15/E$15,"") | G15: =SUM(G11:G14) | H15: =IF(COUNT(G11:G14)=0,"",E15-G15)
A17: بدهی | B17: دیون اشخاص (مانده بستانکار) | D17: p- | E17: =-SUMIFS(TrialBal,TrialType,"p",TrialBal,"<0") | F17: =IFERROR(E17/E$21,"") | H17: =IF($G17="","",E17-$G17)
A18: بدهی | B18: اسناد چک پرداختی — پاس‌نشده | D18: q | E18: =-SUMIFS(TrialBal,TrialType,"q") | F18: =IFERROR(E18/E$21,"") | H18: =IF($G18="","",E18-$G18)
A19: بدهی | B19: وام‌ها و تسهیلات (L…) | D19: l | E19: =-SUMIFS(TrialBal,TrialType,"l") | F19: =IFERROR(E19/E$21,"") | H19: =IF($G19="","",E19-$G19)
A20: بدهی | B20: متفرقه / در انتظار تعریف (شیت Control) | D20: m | E20: =-SUMIFS(TrialBal,TrialType,"m") | F20: =IFERROR(E20/E$21,"") | H20: =IF($G20="","",E20-$G20)
A21: جمع بدهی‌ها | E21: =SUM(E17:E20) | F21: =IFERROR(E21/E$21,"") | G21: =SUM(G17:G20) | H21: =IF(COUNT(G17:G20)=0,"",E21-G21)
A23: حقوق صاحبان | B23: افتتاحیه (مانده اولیه بانک‌ها) | D23: o | E23: =SUMIFS(TrialBal,TrialType,"o")*-1 | F23: =IFERROR(E23/E$27,"") | H23: =IF($G23="","",E23-$G23)
A24: حقوق صاحبان | B24: سرمایه و آورده صاحبان (CAP…) | D24: c | E24: =SUMIFS(TrialBal,TrialType,"c")*-1 | F24: =IFERROR(E24/E$27,"") | H24: =IF($G24="","",E24-$G24)
A25: حقوق صاحبان | B25: هزینه‌های دوره (کسر — مبنای نقدی) | D25: e | E25: =SUMIFS(TrialBal,TrialType,"e")*-1 | F25: =IFERROR(E25/E$27,"") | H25: =IF($G25="","",E25-$G25)
A26: حقوق صاحبان | B26: تراکنش‌های شخصی قاسم (خارج از شرکت، کسر) | D26: x | E26: =SUMIFS(TrialBal,TrialType,"x")*-1 | F26: =IFERROR(E26/E$27,"") | H26: =IF($G26="","",E26-$G26)
A27: جمع حقوق صاحبان (مبنای نقدی) | E27: =SUM(E23:E26) | F27: =IFERROR(E27/E$27,"") | G27: =SUM(G23:G26) | H27: =IF(COUNT(G23:G26)=0,"",E27-G27)
A29: ⚠️ مبنای این ترازنامه نقدی است: درآمد فروش تا تطبیق با فاکتورها در «دیون اشخاص» (پیش‌دریافت) می‌نشیند و هنوز سود شناسایی‌شده نیست؛ سود واقعی دوره = درآمد فاکتورشده (فایل Sales) − بهای تمام‌شده (Purchases) − هزینه‌ها (Expenses). «متفرقه» حساب معلق است و تا تعریف شدن (شیت Control) در بدهی‌ها می‌ماند.

Sheet BalanceClassic
A1: =IF(Sync!$P$6="","مازندشت",Sync!$P$6)&" — "&IF(Sync!$P$9="","سورتینگ و بسته‌بندی مرکبات",Sync!$P$9)
A2: =IF(Sync!$P$7="","باغدشت، بخش مرکزی، شهرستان قائم‌شهر، استان مازندران، ایران",Sync!$P$7)&" | MAZANDASHT · CITRUS SORTING & PACKING"
A3: ترازنامه کلاسیک دوستونه — سبک سنتی (خودکار)
A4: چیدمان سنتی: دارایی‌ها یک سمت، بدهی‌ها و حقوق صاحبان سمت دیگر — ارقام هر دو سمت از شیت Trial جمع می‌شوند و باید برابر باشند (معادله حسابداری). «متفرقه» تا تعریف شدن در شیت Control، در بدهی‌های کوتاه‌مدت می‌ماند.
A10: دارایی‌ها | D10: مبلغ (ریال) | E10: بدهی‌ها و حقوق صاحبان | H10: مبلغ (ریال)
A11: موجودی نقدی بانک‌ها | D11: =SUMIFS(TrialBal,TrialType,"b") | E11: دیون اشخاص (بستانکار) | H11: =-SUMIFS(TrialBal,TrialType,"p",TrialBal,"<0")
A12: طلب از اشخاص (بدهکار) | D12: =SUMIFS(TrialBal,TrialType,"p",TrialBal,">0") | E12: اسناد چک پرداختی — پاس‌نشده | H12: =-SUMIFS(TrialBal,TrialType,"q")
A13: دارایی‌های ثابت (F…) | D13: =SUMIFS(TrialBal,TrialType,"f") | E13: وام‌ها و تسهیلات (L…) | H13: =-SUMIFS(TrialBal,TrialType,"l")
A14: سبد و ظروف (دفتر Baskets) | D14: =SUMIFS(TrialBal,TrialType,"s") | E14: متفرقه — در انتظار تعریف | H14: =-SUMIFS(TrialBal,TrialType,"m")
E15: جمع بدهی‌ها | H15: =SUM(H11:H14)
E17: سرمایه و آورده صاحبان (CAP…) | H17: =-SUMIFS(TrialBal,TrialType,"c")
E18: افتتاحیه (آورده اولیه) | H18: =-SUMIFS(TrialBal,TrialType,"o")
E19: تغییرات نقدی دوره (− هزینه‌ها − شخصی) | H19: =-SUMIFS(TrialBal,TrialType,"e")-SUMIFS(TrialBal,TrialType,"x")
A20: جمع دارایی‌ها | D20: =SUM(D11:D14) | E20: جمع حقوق صاحبان | H20: =SUM(H17:H19)
A21: جمع کل دارایی‌ها | D21: =D20 | E21: جمع کل بدهی‌ها + حقوق صاحبان | H21: =H15+H20
A23: =IF(ROUND(D21-H21,0)=0,"√ تراز است — دارایی‌ها = بدهی‌ها + حقوق صاحبان","▲ مغایرت: دارایی‌ها ≠ بدهی‌ها + حقوق صاحبان")
A25: مبنای نقدی: واریزهای فروش تا تطبیق با فاکتور در «دیون اشخاص» است و سود واقعی دوره از فاکتورهای فروش/خرید محاسبه می‌شود (فایل‌های Sales و Purchases و Expenses).

Sheet Control
A1: =IF(Sync!$P$6="","مازندشت",Sync!$P$6)&" — "&IF(Sync!$P$9="","سورتینگ و بسته‌بندی مرکبات",Sync!$P$9)
A2: =IF(Sync!$P$7="","باغدشت، بخش مرکزی، شهرستان قائم‌شهر، استان مازندران، ایران",Sync!$P$7)&" | MAZANDASHT · CITRUS SORTING & PACKING"
A3: کنترل و اعتبارسنجی — موارد تعریف‌نشده یا نیازمند تعریف
A4: این شیت خودکار است: هر تراکنش یا چکی که به حساب/زیرگروه/شماره‌ی تعریف‌نشده اشاره کند اینجا فهرست می‌شود تا در INFO (یا Transactions / Cheques) تعریف و اصلاحش کنید. موارد ناشناس تا تعریف نشوند، در «متفرقه» تراز می‌مانند. پس از اصلاح: Data ← Edit Links ← Update Values.
A5: موارد نیازمند اقدام | C5: جمع مبلغ تراکنش‌های مشکل‌دار (ریال) | E5: هزینه بدون زیرگروه (ریال) | G5: مانده متفرقه — در انتظار تعریف (ریال)
A6: =COUNTIF(CalcRank1,">0")+COUNTIF(CalcRank2,">0") | C6: =SUMIF(CalcRank1,">0",CalcAmt) | E6: =SUMIF(CalcProb1,"هزینه بدون زیرگروه",CalcAmt) | G6: =-SUMIFS(TrialBal,TrialType,"m")
A7: =IF(COUNTIF(CalcRank1,">0")+COUNTIF(CalcRank2,">0")=0,"✓ همه‌چیز تعریف‌شده — موردی برای اقدام نیست","▲ "&COUNTIF(CalcRank1,">0")+COUNTIF(CalcRank2,">0")&" مورد نیازمند تعریف — فهرست زیر را اصلاح کنید")
A9: الف) تراکنش‌های نیازمند تعریف — از Transactions ← Entry
A10: ردیف | B10: نوع مشکل | C10: تاریخ | D10: بانک | E10: طرف | F10: نوع تراکنش | G10: مبلغ (ریال)
A11: No. | B11: Issue | C11: Date | D11: Bank | E11: Party | F11: Txn Type | G11: Amount
A12: =IF(IFERROR(MATCH(1,CalcRank1,0),0)=0,"",1) | B12: =IF(IFERROR(MATCH(1,CalcRank1,0),0)=0,"",INDEX(CalcProb1,IFERROR(MATCH(1,CalcRank1,0),0))) | C12: =IF(IFERROR(MATCH(1,CalcRank1,0),0)=0,"",INDEX(Sync!$AK$6:$AK$2005,IFERROR(MATCH(1,CalcRank1,0),0))) | D12: =IF(IFERROR(MATCH(1,CalcRank1,0),0)=0,"",INDEX(Calc!$A$6:$A$2005,IFERROR(MATCH(1,CalcRank1,0),0))) | E12: =IF(IFERROR(MATCH(1,CalcRank1,0),0)=0,"",INDEX(Calc!$B$6:$B$2005,IFERROR(MATCH(1,CalcRank1,0),0))) | F12: =IF(IFERROR(MATCH(1,CalcRank1,0),0)=0,"",INDEX(Calc!$C$6:$C$2005,IFERROR(MATCH(1,CalcRank1,0),0))) | G12: =IF(IFERROR(MATCH(1,CalcRank1,0),0)=0,"",INDEX(Calc!$H$6:$H$2005,IFERROR(MATCH(1,CalcRank1,0),0)))
A13: =IF(IFERROR(MATCH(2,CalcRank1,0),0)=0,"",2) | B13: =IF(IFERROR(MATCH(2,CalcRank1,0),0)=0,"",INDEX(CalcProb1,IFERROR(MATCH(2,CalcRank1,0),0))) | C13: =IF(IFERROR(MATCH(2,CalcRank1,0),0)=0,"",INDEX(Sync!$AK$6:$AK$2005,IFERROR(MATCH(2,CalcRank1,0),0))) | D13: =IF(IFERROR(MATCH(2,CalcRank1,0),0)=0,"",INDEX(Calc!$A$6:$A$2005,IFERROR(MATCH(2,CalcRank1,0),0))) | E13: =IF(IFERROR(MATCH(2,CalcRank1,0),0)=0,"",INDEX(Calc!$B$6:$B$2005,IFERROR(MATCH(2,CalcRank1,0),0))) | F13: =IF(IFERROR(MATCH(2,CalcRank1,0),0)=0,"",INDEX(Calc!$C$6:$C$2005,IFERROR(MATCH(2,CalcRank1,0),0))) | G13: =IF(IFERROR(MATCH(2,CalcRank1,0),0)=0,"",INDEX(Calc!$H$6:$H$2005,IFERROR(MATCH(2,CalcRank1,0),0)))
A14: =IF(IFERROR(MATCH(3,CalcRank1,0),0)=0,"",3) | B14: =IF(IFERROR(MATCH(3,CalcRank1,0),0)=0,"",INDEX(CalcProb1,IFERROR(MATCH(3,CalcRank1,0),0))) | C14: =IF(IFERROR(MATCH(3,CalcRank1,0),0)=0,"",INDEX(Sync!$AK$6:$AK$2005,IFERROR(MATCH(3,CalcRank1,0),0))) | D14: =IF(IFERROR(MATCH(3,CalcRank1,0),0)=0,"",INDEX(Calc!$A$6:$A$2005,IFERROR(MATCH(3,CalcRank1,0),0))) | E14: =IF(IFERROR(MATCH(3,CalcRank1,0),0)=0,"",INDEX(Calc!$B$6:$B$2005,IFERROR(MATCH(3,CalcRank1,0),0))) | F14: =IF(IFERROR(MATCH(3,CalcRank1,0),0)=0,"",INDEX(Calc!$C$6:$C$2005,IFERROR(MATCH(3,CalcRank1,0),0))) | G14: =IF(IFERROR(MATCH(3,CalcRank1,0),0)=0,"",INDEX(Calc!$H$6:$H$2005,IFERROR(MATCH(3,CalcRank1,0),0)))
A15: =IF(IFERROR(MATCH(4,CalcRank1,0),0)=0,"",4) | B15: =IF(IFERROR(MATCH(4,CalcRank1,0),0)=0,"",INDEX(CalcProb1,IFERROR(MATCH(4,CalcRank1,0),0))) | C15: =IF(IFERROR(MATCH(4,CalcRank1,0),0)=0,"",INDEX(Sync!$AK$6:$AK$2005,IFERROR(MATCH(4,CalcRank1,0),0))) | D15: =IF(IFERROR(MATCH(4,CalcRank1,0),0)=0,"",INDEX(Calc!$A$6:$A$2005,IFERROR(MATCH(4,CalcRank1,0),0))) | E15: =IF(IFERROR(MATCH(4,CalcRank1,0),0)=0,"",INDEX(Calc!$B$6:$B$2005,IFERROR(MATCH(4,CalcRank1,0),0))) | F15: =IF(IFERROR(MATCH(4,CalcRank1,0),0)=0,"",INDEX(Calc!$C$6:$C$2005,IFERROR(MATCH(4,CalcRank1,0),0))) | G15: =IF(IFERROR(MATCH(4,CalcRank1,0),0)=0,"",INDEX(Calc!$H$6:$H$2005,IFERROR(MATCH(4,CalcRank1,0),0)))
A16: =IF(IFERROR(MATCH(5,CalcRank1,0),0)=0,"",5) | B16: =IF(IFERROR(MATCH(5,CalcRank1,0),0)=0,"",INDEX(CalcProb1,IFERROR(MATCH(5,CalcRank1,0),0))) | C16: =IF(IFERROR(MATCH(5,CalcRank1,0),0)=0,"",INDEX(Sync!$AK$6:$AK$2005,IFERROR(MATCH(5,CalcRank1,0),0))) | D16: =IF(IFERROR(MATCH(5,CalcRank1,0),0)=0,"",INDEX(Calc!$A$6:$A$2005,IFERROR(MATCH(5,CalcRank1,0),0))) | E16: =IF(IFERROR(MATCH(5,CalcRank1,0),0)=0,"",INDEX(Calc!$B$6:$B$2005,IFERROR(MATCH(5,CalcRank1,0),0))) | F16: =IF(IFERROR(MATCH(5,CalcRank1,0),0)=0,"",INDEX(Calc!$C$6:$C$2005,IFERROR(MATCH(5,CalcRank1,0),0))) | G16: =IF(IFERROR(MATCH(5,CalcRank1,0),0)=0,"",INDEX(Calc!$H$6:$H$2005,IFERROR(MATCH(5,CalcRank1,0),0)))
A17: =IF(IFERROR(MATCH(6,CalcRank1,0),0)=0,"",6) | B17: =IF(IFERROR(MATCH(6,CalcRank1,0),0)=0,"",INDEX(CalcProb1,IFERROR(MATCH(6,CalcRank1,0),0))) | C17: =IF(IFERROR(MATCH(6,CalcRank1,0),0)=0,"",INDEX(Sync!$AK$6:$AK$2005,IFERROR(MATCH(6,CalcRank1,0),0))) | D17: =IF(IFERROR(MATCH(6,CalcRank1,0),0)=0,"",INDEX(Calc!$A$6:$A$2005,IFERROR(MATCH(6,CalcRank1,0),0))) | E17: =IF(IFERROR(MATCH(6,CalcRank1,0),0)=0,"",INDEX(Calc!$B$6:$B$2005,IFERROR(MATCH(6,CalcRank1,0),0))) | F17: =IF(IFERROR(MATCH(6,CalcRank1,0),0)=0,"",INDEX(Calc!$C$6:$C$2005,IFERROR(MATCH(6,CalcRank1,0),0))) | G17: =IF(IFERROR(MATCH(6,CalcRank1,0),0)=0,"",INDEX(Calc!$H$6:$H$2005,IFERROR(MATCH(6,CalcRank1,0),0)))
A18: =IF(IFERROR(MATCH(7,CalcRank1,0),0)=0,"",7) | B18: =IF(IFERROR(MATCH(7,CalcRank1,0),0)=0,"",INDEX(CalcProb1,IFERROR(MATCH(7,CalcRank1,0),0))) | C18: =IF(IFERROR(MATCH(7,CalcRank1,0),0)=0,"",INDEX(Sync!$AK$6:$AK$2005,IFERROR(MATCH(7,CalcRank1,0),0))) | D18: =IF(IFERROR(MATCH(7,CalcRank1,0),0)=0,"",INDEX(Calc!$A$6:$A$2005,IFERROR(MATCH(7,CalcRank1,0),0))) | E18: =IF(IFERROR(MATCH(7,CalcRank1,0),0)=0,"",INDEX(Calc!$B$6:$B$2005,IFERROR(MATCH(7,CalcRank1,0),0))) | F18: =IF(IFERROR(MATCH(7,CalcRank1,0),0)=0,"",INDEX(Calc!$C$6:$C$2005,IFERROR(MATCH(7,CalcRank1,0),0))) | G18: =IF(IFERROR(MATCH(7,CalcRank1,0),0)=0,"",INDEX(Calc!$H$6:$H$2005,IFERROR(MATCH(7,CalcRank1,0),0)))
A19: =IF(IFERROR(MATCH(8,CalcRank1,0),0)=0,"",8) | B19: =IF(IFERROR(MATCH(8,CalcRank1,0),0)=0,"",INDEX(CalcProb1,IFERROR(MATCH(8,CalcRank1,0),0))) | C19: =IF(IFERROR(MATCH(8,CalcRank1,0),0)=0,"",INDEX(Sync!$AK$6:$AK$2005,IFERROR(MATCH(8,CalcRank1,0),0))) | D19: =IF(IFERROR(MATCH(8,CalcRank1,0),0)=0,"",INDEX(Calc!$A$6:$A$2005,IFERROR(MATCH(8,CalcRank1,0),0))) | E19: =IF(IFERROR(MATCH(8,CalcRank1,0),0)=0,"",INDEX(Calc!$B$6:$B$2005,IFERROR(MATCH(8,CalcRank1,0),0))) | F19: =IF(IFERROR(MATCH(8,CalcRank1,0),0)=0,"",INDEX(Calc!$C$6:$C$2005,IFERROR(MATCH(8,CalcRank1,0),0))) | G19: =IF(IFERROR(MATCH(8,CalcRank1,0),0)=0,"",INDEX(Calc!$H$6:$H$2005,IFERROR(MATCH(8,CalcRank1,0),0)))
A20: =IF(IFERROR(MATCH(9,CalcRank1,0),0)=0,"",9) | B20: =IF(IFERROR(MATCH(9,CalcRank1,0),0)=0,"",INDEX(CalcProb1,IFERROR(MATCH(9,CalcRank1,0),0))) | C20: =IF(IFERROR(MATCH(9,CalcRank1,0),0)=0,"",INDEX(Sync!$AK$6:$AK$2005,IFERROR(MATCH(9,CalcRank1,0),0))) | D20: =IF(IFERROR(MATCH(9,CalcRank1,0),0)=0,"",INDEX(Calc!$A$6:$A$2005,IFERROR(MATCH(9,CalcRank1,0),0))) | E20: =IF(IFERROR(MATCH(9,CalcRank1,0),0)=0,"",INDEX(Calc!$B$6:$B$2005,IFERROR(MATCH(9,CalcRank1,0),0))) | F20: =IF(IFERROR(MATCH(9,CalcRank1,0),0)=0,"",INDEX(Calc!$C$6:$C$2005,IFERROR(MATCH(9,CalcRank1,0),0))) | G20: =IF(IFERROR(MATCH(9,CalcRank1,0),0)=0,"",INDEX(Calc!$H$6:$H$2005,IFERROR(MATCH(9,CalcRank1,0),0)))
A21: =IF(IFERROR(MATCH(10,CalcRank1,0),0)=0,"",10) | B21: =IF(IFERROR(MATCH(10,CalcRank1,0),0)=0,"",INDEX(CalcProb1,IFERROR(MATCH(10,CalcRank1,0),0))) | C21: =IF(IFERROR(MATCH(10,CalcRank1,0),0)=0,"",INDEX(Sync!$AK$6:$AK$2005,IFERROR(MATCH(10,CalcRank1,0),0))) | D21: =IF(IFERROR(MATCH(10,CalcRank1,0),0)=0,"",INDEX(Calc!$A$6:$A$2005,IFERROR(MATCH(10,CalcRank1,0),0))) | E21: =IF(IFERROR(MATCH(10,CalcRank1,0),0)=0,"",INDEX(Calc!$B$6:$B$2005,IFERROR(MATCH(10,CalcRank1,0),0))) | F21: =IF(IFERROR(MATCH(10,CalcRank1,0),0)=0,"",INDEX(Calc!$C$6:$C$2005,IFERROR(MATCH(10,CalcRank1,0),0))) | G21: =IF(IFERROR(MATCH(10,CalcRank1,0),0)=0,"",INDEX(Calc!$H$6:$H$2005,IFERROR(MATCH(10,CalcRank1,0),0)))
A22: =IF(IFERROR(MATCH(11,CalcRank1,0),0)=0,"",11) | B22: =IF(IFERROR(MATCH(11,CalcRank1,0),0)=0,"",INDEX(CalcProb1,IFERROR(MATCH(11,CalcRank1,0),0))) | C22: =IF(IFERROR(MATCH(11,CalcRank1,0),0)=0,"",INDEX(Sync!$AK$6:$AK$2005,IFERROR(MATCH(11,CalcRank1,0),0))) | D22: =IF(IFERROR(MATCH(11,CalcRank1,0),0)=0,"",INDEX(Calc!$A$6:$A$2005,IFERROR(MATCH(11,CalcRank1,0),0))) | E22: =IF(IFERROR(MATCH(11,CalcRank1,0),0)=0,"",INDEX(Calc!$B$6:$B$2005,IFERROR(MATCH(11,CalcRank1,0),0))) | F22: =IF(IFERROR(MATCH(11,CalcRank1,0),0)=0,"",INDEX(Calc!$C$6:$C$2005,IFERROR(MATCH(11,CalcRank1,0),0))) | G22: =IF(IFERROR(MATCH(11,CalcRank1,0),0)=0,"",INDEX(Calc!$H$6:$H$2005,IFERROR(MATCH(11,CalcRank1,0),0)))
A23: =IF(IFERROR(MATCH(12,CalcRank1,0),0)=0,"",12) | B23: =IF(IFERROR(MATCH(12,CalcRank1,0),0)=0,"",INDEX(CalcProb1,IFERROR(MATCH(12,CalcRank1,0),0))) | C23: =IF(IFERROR(MATCH(12,CalcRank1,0),0)=0,"",INDEX(Sync!$AK$6:$AK$2005,IFERROR(MATCH(12,CalcRank1,0),0))) | D23: =IF(IFERROR(MATCH(12,CalcRank1,0),0)=0,"",INDEX(Calc!$A$6:$A$2005,IFERROR(MATCH(12,CalcRank1,0),0))) | E23: =IF(IFERROR(MATCH(12,CalcRank1,0),0)=0,"",INDEX(Calc!$B$6:$B$2005,IFERROR(MATCH(12,CalcRank1,0),0))) | F23: =IF(IFERROR(MATCH(12,CalcRank1,0),0)=0,"",INDEX(Calc!$C$6:$C$2005,IFERROR(MATCH(12,CalcRank1,0),0))) | G23: =IF(IFERROR(MATCH(12,CalcRank1,0),0)=0,"",INDEX(Calc!$H$6:$H$2005,IFERROR(MATCH(12,CalcRank1,0),0)))
A24: =IF(IFERROR(MATCH(13,CalcRank1,0),0)=0,"",13) | B24: =IF(IFERROR(MATCH(13,CalcRank1,0),0)=0,"",INDEX(CalcProb1,IFERROR(MATCH(13,CalcRank1,0),0))) | C24: =IF(IFERROR(MATCH(13,CalcRank1,0),0)=0,"",INDEX(Sync!$AK$6:$AK$2005,IFERROR(MATCH(13,CalcRank1,0),0))) | D24: =IF(IFERROR(MATCH(13,CalcRank1,0),0)=0,"",INDEX(Calc!$A$6:$A$2005,IFERROR(MATCH(13,CalcRank1,0),0))) | E24: =IF(IFERROR(MATCH(13,CalcRank1,0),0)=0,"",INDEX(Calc!$B$6:$B$2005,IFERROR(MATCH(13,CalcRank1,0),0))) | F24: =IF(IFERROR(MATCH(13,CalcRank1,0),0)=0,"",INDEX(Calc!$C$6:$C$2005,IFERROR(MATCH(13,CalcRank1,0),0))) | G24: =IF(IFERROR(MATCH(13,CalcRank1,0),0)=0,"",INDEX(Calc!$H$6:$H$2005,IFERROR(MATCH(13,CalcRank1,0),0)))
A25: =IF(IFERROR(MATCH(14,CalcRank1,0),0)=0,"",14) | B25: =IF(IFERROR(MATCH(14,CalcRank1,0),0)=0,"",INDEX(CalcProb1,IFERROR(MATCH(14,CalcRank1,0),0))) | C25: =IF(IFERROR(MATCH(14,CalcRank1,0),0)=0,"",INDEX(Sync!$AK$6:$AK$2005,IFERROR(MATCH(14,CalcRank1,0),0))) | D25: =IF(IFERROR(MATCH(14,CalcRank1,0),0)=0,"",INDEX(Calc!$A$6:$A$2005,IFERROR(MATCH(14,CalcRank1,0),0))) | E25: =IF(IFERROR(MATCH(14,CalcRank1,0),0)=0,"",INDEX(Calc!$B$6:$B$2005,IFERROR(MATCH(14,CalcRank1,0),0))) | F25: =IF(IFERROR(MATCH(14,CalcRank1,0),0)=0,"",INDEX(Calc!$C$6:$C$2005,IFERROR(MATCH(14,CalcRank1,0),0))) | G25: =IF(IFERROR(MATCH(14,CalcRank1,0),0)=0,"",INDEX(Calc!$H$6:$H$2005,IFERROR(MATCH(14,CalcRank1,0),0)))
A26: =IF(IFERROR(MATCH(15,CalcRank1,0),0)=0,"",15) | B26: =IF(IFERROR(MATCH(15,CalcRank1,0),0)=0,"",INDEX(CalcProb1,IFERROR(MATCH(15,CalcRank1,0),0))) | C26: =IF(IFERROR(MATCH(15,CalcRank1,0),0)=0,"",INDEX(Sync!$AK$6:$AK$2005,IFERROR(MATCH(15,CalcRank1,0),0))) | D26: =IF(IFERROR(MATCH(15,CalcRank1,0),0)=0,"",INDEX(Calc!$A$6:$A$2005,IFERROR(MATCH(15,CalcRank1,0),0))) | E26: =IF(IFERROR(MATCH(15,CalcRank1,0),0)=0,"",INDEX(Calc!$B$6:$B$2005,IFERROR(MATCH(15,CalcRank1,0),0))) | F26: =IF(IFERROR(MATCH(15,CalcRank1,0),0)=0,"",INDEX(Calc!$C$6:$C$2005,IFERROR(MATCH(15,CalcRank1,0),0))) | G26: =IF(IFERROR(MATCH(15,CalcRank1,0),0)=0,"",INDEX(Calc!$H$6:$H$2005,IFERROR(MATCH(15,CalcRank1,0),0)))
A28: ب) چک‌های صادره با ذی‌نفع تعریف‌نشده — از Cheques ← Issues
A29: ردیف | B29: شماره چک | C29: تاریخ چک | D29: مبلغ (ریال) | E29: ذی‌نفع | F29: نوع مشکل
A30: No. | B30: Cheque No. | C30: Date | D30: Amount | E30: Beneficiary | F30: Issue
A31: =IF(IFERROR(MATCH(1,CalcRank2,0),0)=0,"",1) | B31: =IF(IFERROR(MATCH(1,CalcRank2,0),0)=0,"",INDEX(Sync!$AG$6:$AG$505,IFERROR(MATCH(1,CalcRank2,0),0))) | C31: =IF(IFERROR(MATCH(1,CalcRank2,0),0)=0,"",INDEX(Sync!$AW$6:$AW$505,IFERROR(MATCH(1,CalcRank2,0),0))) | D31: =IF(IFERROR(MATCH(1,CalcRank2,0),0)=0,"",INDEX(Sync!$AH$6:$AH$505,IFERROR(MATCH(1,CalcRank2,0),0))) | E31: =IF(IFERROR(MATCH(1,CalcRank2,0),0)=0,"",INDEX(Sync!$AI$6:$AI$505,IFERROR(MATCH(1,CalcRank2,0),0))) | F31: =IF(IFERROR(MATCH(1,CalcRank2,0),0)=0,"",INDEX(CalcProb2,IFERROR(MATCH(1,CalcRank2,0),0)))
A32: =IF(IFERROR(MATCH(2,CalcRank2,0),0)=0,"",2) | B32: =IF(IFERROR(MATCH(2,CalcRank2,0),0)=0,"",INDEX(Sync!$AG$6:$AG$505,IFERROR(MATCH(2,CalcRank2,0),0))) | C32: =IF(IFERROR(MATCH(2,CalcRank2,0),0)=0,"",INDEX(Sync!$AW$6:$AW$505,IFERROR(MATCH(2,CalcRank2,0),0))) | D32: =IF(IFERROR(MATCH(2,CalcRank2,0),0)=0,"",INDEX(Sync!$AH$6:$AH$505,IFERROR(MATCH(2,CalcRank2,0),0))) | E32: =IF(IFERROR(MATCH(2,CalcRank2,0),0)=0,"",INDEX(Sync!$AI$6:$AI$505,IFERROR(MATCH(2,CalcRank2,0),0))) | F32: =IF(IFERROR(MATCH(2,CalcRank2,0),0)=0,"",INDEX(CalcProb2,IFERROR(MATCH(2,CalcRank2,0),0)))
A33: =IF(IFERROR(MATCH(3,CalcRank2,0),0)=0,"",3) | B33: =IF(IFERROR(MATCH(3,CalcRank2,0),0)=0,"",INDEX(Sync!$AG$6:$AG$505,IFERROR(MATCH(3,CalcRank2,0),0))) | C33: =IF(IFERROR(MATCH(3,CalcRank2,0),0)=0,"",INDEX(Sync!$AW$6:$AW$505,IFERROR(MATCH(3,CalcRank2,0),0))) | D33: =IF(IFERROR(MATCH(3,CalcRank2,0),0)=0,"",INDEX(Sync!$AH$6:$AH$505,IFERROR(MATCH(3,CalcRank2,0),0))) | E33: =IF(IFERROR(MATCH(3,CalcRank2,0),0)=0,"",INDEX(Sync!$AI$6:$AI$505,IFERROR(MATCH(3,CalcRank2,0),0))) | F33: =IF(IFERROR(MATCH(3,CalcRank2,0),0)=0,"",INDEX(CalcProb2,IFERROR(MATCH(3,CalcRank2,0),0)))
A34: =IF(IFERROR(MATCH(4,CalcRank2,0),0)=0,"",4) | B34: =IF(IFERROR(MATCH(4,CalcRank2,0),0)=0,"",INDEX(Sync!$AG$6:$AG$505,IFERROR(MATCH(4,CalcRank2,0),0))) | C34: =IF(IFERROR(MATCH(4,CalcRank2,0),0)=0,"",INDEX(Sync!$AW$6:$AW$505,IFERROR(MATCH(4,CalcRank2,0),0))) | D34: =IF(IFERROR(MATCH(4,CalcRank2,0),0)=0,"",INDEX(Sync!$AH$6:$AH$505,IFERROR(MATCH(4,CalcRank2,0),0))) | E34: =IF(IFERROR(MATCH(4,CalcRank2,0),0)=0,"",INDEX(Sync!$AI$6:$AI$505,IFERROR(MATCH(4,CalcRank2,0),0))) | F34: =IF(IFERROR(MATCH(4,CalcRank2,0),0)=0,"",INDEX(CalcProb2,IFERROR(MATCH(4,CalcRank2,0),0)))
A35: =IF(IFERROR(MATCH(5,CalcRank2,0),0)=0,"",5) | B35: =IF(IFERROR(MATCH(5,CalcRank2,0),0)=0,"",INDEX(Sync!$AG$6:$AG$505,IFERROR(MATCH(5,CalcRank2,0),0))) | C35: =IF(IFERROR(MATCH(5,CalcRank2,0),0)=0,"",INDEX(Sync!$AW$6:$AW$505,IFERROR(MATCH(5,CalcRank2,0),0))) | D35: =IF(IFERROR(MATCH(5,CalcRank2,0),0)=0,"",INDEX(Sync!$AH$6:$AH$505,IFERROR(MATCH(5,CalcRank2,0),0))) | E35: =IF(IFERROR(MATCH(5,CalcRank2,0),0)=0,"",INDEX(Sync!$AI$6:$AI$505,IFERROR(MATCH(5,CalcRank2,0),0))) | F35: =IF(IFERROR(MATCH(5,CalcRank2,0),0)=0,"",INDEX(CalcProb2,IFERROR(MATCH(5,CalcRank2,0),0)))
A36: =IF(IFERROR(MATCH(6,CalcRank2,0),0)=0,"",6) | B36: =IF(IFERROR(MATCH(6,CalcRank2,0),0)=0,"",INDEX(Sync!$AG$6:$AG$505,IFERROR(MATCH(6,CalcRank2,0),0))) | C36: =IF(IFERROR(MATCH(6,CalcRank2,0),0)=0,"",INDEX(Sync!$AW$6:$AW$505,IFERROR(MATCH(6,CalcRank2,0),0))) | D36: =IF(IFERROR(MATCH(6,CalcRank2,0),0)=0,"",INDEX(Sync!$AH$6:$AH$505,IFERROR(MATCH(6,CalcRank2,0),0))) | E36: =IF(IFERROR(MATCH(6,CalcRank2,0),0)=0,"",INDEX(Sync!$AI$6:$AI$505,IFERROR(MATCH(6,CalcRank2,0),0))) | F36: =IF(IFERROR(MATCH(6,CalcRank2,0),0)=0,"",INDEX(CalcProb2,IFERROR(MATCH(6,CalcRank2,0),0)))
A37: =IF(IFERROR(MATCH(7,CalcRank2,0),0)=0,"",7) | B37: =IF(IFERROR(MATCH(7,CalcRank2,0),0)=0,"",INDEX(Sync!$AG$6:$AG$505,IFERROR(MATCH(7,CalcRank2,0),0))) | C37: =IF(IFERROR(MATCH(7,CalcRank2,0),0)=0,"",INDEX(Sync!$AW$6:$AW$505,IFERROR(MATCH(7,CalcRank2,0),0))) | D37: =IF(IFERROR(MATCH(7,CalcRank2,0),0)=0,"",INDEX(Sync!$AH$6:$AH$505,IFERROR(MATCH(7,CalcRank2,0),0))) | E37: =IF(IFERROR(MATCH(7,CalcRank2,0),0)=0,"",INDEX(Sync!$AI$6:$AI$505,IFERROR(MATCH(7,CalcRank2,0),0))) | F37: =IF(IFERROR(MATCH(7,CalcRank2,0),0)=0,"",INDEX(CalcProb2,IFERROR(MATCH(7,CalcRank2,0),0)))
A38: =IF(IFERROR(MATCH(8,CalcRank2,0),0)=0,"",8) | B38: =IF(IFERROR(MATCH(8,CalcRank2,0),0)=0,"",INDEX(Sync!$AG$6:$AG$505,IFERROR(MATCH(8,CalcRank2,0),0))) | C38: =IF(IFERROR(MATCH(8,CalcRank2,0),0)=0,"",INDEX(Sync!$AW$6:$AW$505,IFERROR(MATCH(8,CalcRank2,0),0))) | D38: =IF(IFERROR(MATCH(8,CalcRank2,0),0)=0,"",INDEX(Sync!$AH$6:$AH$505,IFERROR(MATCH(8,CalcRank2,0),0))) | E38: =IF(IFERROR(MATCH(8,CalcRank2,0),0)=0,"",INDEX(Sync!$AI$6:$AI$505,IFERROR(MATCH(8,CalcRank2,0),0))) | F38: =IF(IFERROR(MATCH(8,CalcRank2,0),0)=0,"",INDEX(CalcProb2,IFERROR(MATCH(8,CalcRank2,0),0)))
A39: =IF(IFERROR(MATCH(9,CalcRank2,0),0)=0,"",9) | B39: =IF(IFERROR(MATCH(9,CalcRank2,0),0)=0,"",INDEX(Sync!$AG$6:$AG$505,IFERROR(MATCH(9,CalcRank2,0),0))) | C39: =IF(IFERROR(MATCH(9,CalcRank2,0),0)=0,"",INDEX(Sync!$AW$6:$AW$505,IFERROR(MATCH(9,CalcRank2,0),0))) | D39: =IF(IFERROR(MATCH(9,CalcRank2,0),0)=0,"",INDEX(Sync!$AH$6:$AH$505,IFERROR(MATCH(9,CalcRank2,0),0))) | E39: =IF(IFERROR(MATCH(9,CalcRank2,0),0)=0,"",INDEX(Sync!$AI$6:$AI$505,IFERROR(MATCH(9,CalcRank2,0),0))) | F39: =IF(IFERROR(MATCH(9,CalcRank2,0),0)=0,"",INDEX(CalcProb2,IFERROR(MATCH(9,CalcRank2,0),0)))
A40: =IF(IFERROR(MATCH(10,CalcRank2,0),0)=0,"",10) | B40: =IF(IFERROR(MATCH(10,CalcRank2,0),0)=0,"",INDEX(Sync!$AG$6:$AG$505,IFERROR(MATCH(10,CalcRank2,0),0))) | C40: =IF(IFERROR(MATCH(10,CalcRank2,0),0)=0,"",INDEX(Sync!$AW$6:$AW$505,IFERROR(MATCH(10,CalcRank2,0),0))) | D40: =IF(IFERROR(MATCH(10,CalcRank2,0),0)=0,"",INDEX(Sync!$AH$6:$AH$505,IFERROR(MATCH(10,CalcRank2,0),0))) | E40: =IF(IFERROR(MATCH(10,CalcRank2,0),0)=0,"",INDEX(Sync!$AI$6:$AI$505,IFERROR(MATCH(10,CalcRank2,0),0))) | F40: =IF(IFERROR(MATCH(10,CalcRank2,0),0)=0,"",INDEX(CalcProb2,IFERROR(MATCH(10,CalcRank2,0),0)))
A41: راه‌حل هر مورد: کد طرف/ذی‌نفع ناشناس ← در INFO ← شیت Accounts تعریف کنید (کد از پیش‌گذاشته) · هزینه بدون زیرگروه ← در Transactions ستون زیرگروه را انتخاب کنید · شماره چک نامعتبر ← شماره را اصلاح یا چک را در Cheques ← Issues صادر کنید.

Sheet Learn
A1: مازندشت — سورتینگ و بسته‌بندی مرکبات
A2: باغدشت، بخش مرکزی، شهرستان قائم‌شهر، استان مازندران، ایران | MAZANDASHT · CITRUS SORTING & PACKING
A3: آموزش حسابداری و کدگذاری — مفاهیم، سناریوهای ثبت و نقشه سامانه
A5: ۱) مفاهیم پایه (علم حسابداری)
A6: • معادله بنیادین حسابداری: دارایی = بدهی + حقوق صاحبان — ترازنامه همین معادله است و کنترل √ یعنی برقراری آن.
A7: • بدهکار (Dr) = سمت چپ ثبت؛ یعنی افزایش دارایی/هزینه یا کاهش بدهی/حقوق. بستانکار (Cr) = سمت راست ثبت؛ یعنی افزایش بدهی/حقوق/درآمد یا کاهش دارایی.
A8: • هر تراکنش دوطرفه ثبت می‌شود (مزدوج): یک حساب بدهکار و یک حساب بستانکار با مبلغ برابر — به همین دلیل جمع تراز آزمایشی همیشه برابر است.
A9: • دارایی جاری = نقد و طلب‌هایی که ظرف یک سال نقد می‌شوند (موجودی بانک، طلب اشخاص) · دارایی ثابت = زمین، خودرو، ماشین‌آلات (حساب‌های F…).
A10: • بدهی جاری = دیون کوتاه‌مدت (دیون اشخاص، چک‌های پاس‌نشده) · بدهی بلندمدت = وام‌ها و تسهیلات (L…) که قسط‌بندی می‌شوند.
A11: • حقوق صاحبان = آورده اولیه (افتتاحیه) + سرمایه و آورده (CAP…) + سود/زیان انباشته (− هزینه‌ها − تراکنش‌های شخصی).
A12: • حساب «متفرقه» (Suspense) محل موقت مبالغی است که طرفشان هنوز تعریف نشده — نباید مانده بماند؛ شیت Control آنها را فهرست می‌کند.
A14: ۲) سناریوهای ثبت — از رخداد تا ترازنامه
A15: رخداد | B15: ثبت کجا | C15: بدهکار (Dr) | D15: بستانکار (Cr) | E15: اثر در ترازنامه
A16: Event | B16: Where | C16: Debit | D16: Credit | E16: Effect
A17: فروش کالا (توزین فروش) | B17: Baskol | C17: — (فقط کالا) | D17: — (فقط کالا) | E17: تا تسویه، طلب مشتری از پرداخت‌ها ساخته می‌شود
A18: واریز پول مشتری | B18: Transactions ← واریز | C18: بانک | D18: مشتری (C…) | E18: دارایی نقد ↑ / طلب مشتری ↓
A19: خرید مرکبات (توزین خرید) | B19: Baskol | C19: — (فقط کالا) | D19: — (فقط کالا) | E19: تا تسویه، بدهی به تأمین‌کننده ساخته می‌شود
A20: پرداخت نقدی به تأمین‌کننده | B20: Transactions ← برداشت | C20: تأمین‌کننده (S…) | D20: بانک | E20: بدهی ↓ / نقد ↓
A21: ثبت هزینه عملیاتی | B21: Transactions ← برداشت + گروه هزینه | C21: هزینه: زیرگروه (SG…) | D21: بانک | E21: از حقوق (سود) کم می‌شود
A22: فروش دارایی شخصی و آورده به شرکت | B22: Transactions ← واریز + گروه سرمایه | C22: بانک | D22: سرمایه و آورده (CAP…) | E22: دارایی نقد ↑ / حقوق ↑
A23: برداشت سرمایه توسط صاحب | B23: Transactions ← برداشت + گروه سرمایه | C23: سرمایه و آورده (CAP…) | D23: بانک | E23: حقوق ↓ / نقد ↓
A24: دریافت وام بانکی | B24: Transactions ← واریز + گروه وام | C24: بانک | D24: وام (L…) | E24: نقد ↑ / بدهی بلندمدت ↑
A25: پرداخت قسط وام (اصل) | B25: Transactions ← برداشت + گروه وام | C25: وام (L…) | D25: بانک | E25: بدهی ↓ / نقد ↓
A26: پرداخت بهره/کارمزد وام | B26: Transactions ← برداشت + گروه هزینه + زیرگروه بهره | C26: هزینه: بهره و کارمزد وام | D26: بانک | E26: از حقوق کم می‌شود
... A30: پاس شدن چک صادره | B30: Transactions ← نوع پاس چک + شماره چک | C30: اسناد چک پرداختی | D30: بانک | E30: بدهی چک ↓ / نقد ↓
A32: ۳) کدگذاری سامانه (پیشوندها — هرگز تغییر ندهید)
A33: پیشوند | B33: چه چیزی | C33: تعریف در | D33: مثال
A34: Prefix | B34: What | C34: Defined in | D34: Example
A35: C… | B35: مشتری | C35: INFO ← Accounts | D35: C001
A36: SL… | B36: فروشنده | C36: INFO ← Accounts | D36: SL001
A37: S… | B37: تأمین‌کننده | C37: INFO ← Accounts | D37: S001
A38: E… | B38: کارمند | C38: INFO ← Accounts | D38: E002
A39: X… | B39: سایر حساب (اداری، مالیات، صندوق…) | C39: INFO ← Accounts | D39: X001
A40: F… | B40: دارایی ثابت (زمین، خودرو، تجهیزات) | C40: INFO ← Accounts | D40: F001
A41: L… | B41: وام و تسهیلات | C41: INFO ← Accounts | D41: L001
A42: CAP… | B42: سرمایه و آورده صاحبان | C42: INFO ← Accounts | D42: CAP001
A43: BANK… | B43: حساب بانکی | C43: INFO ← Banks | D43: BANK01
A44: G… | B44: گروه اصلی تراکنش (G01 خرید … G07 دارایی ثابت) | C44: INFO ← MainGroups | D44: G05
... A48: OP… / PB… / PS… / BK… / W… / P… | B48: عملیات باسکول / محصول خرید / محصول فروش / سبد / انبار / پارامتر | C48: INFO ← شیت مربوطه | D48: OP01 / PB01 / P01
A50: ۴) نقشه ارتباط فایل‌ها (لینک‌های خارجی — همیشه در یک پوشه)
A51: فایل | B51: نقش | C51: ورود داده | D51: از چه فایل‌هایی می‌خواند
A52: File | B52: Role | C52: Input | D52: Reads from
A53: INFO.xlsx | B53: مادر — همه تعریف‌ها + راهنما | C53: تعریف‌ها | D53: — (هیچ لینکی ندارد)
A54: Baskol.xlsx | B54: دفتر باسکول — تنها ورود کالا | C54: ✅ | D54: INFO
A55: Transactions.xlsx | B55: پول — واریز/برداشت + پاس چک | C55: ✅ | D55: INFO
A56: Sales.xlsx | B56: صورت‌حساب فروش کدمحور | C56: — | D56: INFO، Baskol، Transactions
A57: Purchases.xlsx | B57: گزارش خرید کدمحور | C57: — | D57: INFO، Baskol، Transactions
A58: Expenses.xlsx | B58: گزارش هزینه به تفکیک زیرگروه | C58: — | D58: INFO، Transactions
A59: Employees.xlsx | B59: دفتر دستمزد فردی/گروهی | C59: ✅ | D59: INFO، Transactions
A60: Baskets.xlsx | B60: دفتر سبد — خرید سبد از فروشنده + کارتکس | C60: ✅ خرید سبد | D60: INFO، Transactions
A61: Cheques.xlsx | B61: دفتر چک‌های پرداختی | C61: صدور چک | D61: INFO، Transactions
A62: Accounting.xlsx | B62: تراز آزمایشی، ترازنامه، کنترل، آموزش | C62: — | D62: INFO، Transactions، Cheques
A64: ۵) شیت‌های همین فایل (Accounting.xlsx)
A65: شیت | B65: نقش
A66: Sheet | B66: Role
A67: Trial | B67: تراز آزمایشی همه حساب‌ها (بانک، اشخاص، دارایی ثابت، وام، سرمایه، هزینه، چک، متفرقه) + کنترل √
A68: Balance | B68: ترازنامه گزارشی: مبلغ، درصد از جمع، دوره قبل (دستی) و اختلاف + نسبت جاری
A69: BalanceClassic | B69: ترازنامه کلاسیک دوستونه — دارایی‌ها روبروی بدهی‌ها و حقوق
A70: Control | B70: کنترل و اعتبارسنجی: موارد تعریف‌نشده یا نیازمند تعریف، با مبلغ و تاریخ
A71: Learn | B71: همین شیت آموزش — مفاهیم، سناریوها، کدگذاری و نقشه فایل‌ها
A72: Sync / Calc | B72: برگه‌های فنی (آینه لینک‌ها و موتور تشخیص بدهکار/بستانکار) — تغییر ندهید
A73: Help | B73: راهنمای کوتاه فایل
A75: ۶) طرز استفاده روزمره — گام‌به‌گام
A76: • گام ۱ (یک‌بار): در INFO همه تعریف‌ها را انجام دهید — حساب‌ها (Accounts)، بانک‌ها (Banks)، گروه‌ها (MainGroups/SubGroups)، انواع سبد (Baskets)، پارامترها.
A77: • گام ۲ (روزانه): هر توزین کالا را در Baskol.xlsx یک ردیف ثبت کنید (خرید/فروش/مرجوعی).
A78: • گام ۳ (روزانه): هر حرکت پول را در Transactions.xlsx ثبت کنید (واریز/برداشت + گروه اصلی + زیرگروه). خرید سبد در Baskets.xlsx و صدور چک در Cheques.xlsx.
A79: • گام ۴ (هر وقت خواستید گزارش): فایل گزارش مربوط را باز کنید، کد/بازه را وارد کنید، Data ← Edit Links ← Update Values.
A80: • گام ۵ (هر ماه): در Accounting.xlsx شیت Control را خالی کنید (همه موارد را تعریف/اصلاح کنید) و ترازنامه را چاپ/بایگانی کنید.
A81: • قاعده طلایی: تعریف فقط در INFO · کالا فقط در Baskol · پول فقط در Transactions · سبد در Baskets · چک در Cheques · دستمزد در Employees — گزارش‌ها هیچ‌وقت داده نمی‌گیرند.
A83: ۷) کدام گزارش برای کدام نیاز؟ (نقشه گزارش‌های کاربردی)
A84: من می‌خواهم بدانم… | B84: فایل / شیت | C84: ورودی
A85: Need | B85: Where | C85: Input
A86: صورت‌حساب کامل یک فروشنده مرکبات | B86: Sales.xlsx ← Report | C86: کد فروشنده (SL…)
A87: گزارش خرید و بدهی یک تأمین‌کننده مرکبات | B87: Purchases.xlsx ← Report | C87: کد حساب (S…)
A88: مجموع خرید از همه تأمین‌کنندگان + سهم‌ها | B88: Purchases.xlsx ← Summary | C88: —
A89: هزینه‌ها به تفکیک نوع + جزئیات هر نوع | B89: Expenses.xlsx ← Summary / Report | C89: کد زیرگروه (SG…)
A90: دستمزد و مانده هر نفر / هر گروه کاری | B90: Employees.xlsx ← Report / GroupReport | C90: کد E… / WG…
A91: خرید سبد از هر فروشنده + مانده‌اش | B91: Baskets.xlsx ← Report / Summary | C91: کد فروشنده سبد (S…)
A92: چک‌های پاس‌نشده و نزدیک‌ترین سررسید | B92: Cheques.xlsx ← Unpaid | C92: بازه از/تا
A93: گردش همه چک‌های یک بازه (ماهانه) | B93: Cheques.xlsx ← Month | C93: بازه از/تا
A94: موجودی و مغایرت هر بانک | B94: Transactions.xlsx ← Summary | C94: —
A95: بدهی/طلب یک شخص از شرکت (همه جریان‌ها) | B95: Accounting.xlsx ← Trial | C95: ردیف حساب
... A99: آموزش مفاهیم و کدگذاری | B99: Accounting.xlsx ← Learn | C99: —
A101: ۸) نکات طلایی
A102: • بعد از هر تغییر در منابع (INFO، Baskol، Transactions، Baskets، Cheques): در فایل‌های گزارش و Accounting، Data ← Edit Links ← Update Values.
A103: • کد طرفِ ناشناس = حساب متفرقه؛ فهرستش در شیت Control — بعد از تعریف در INFO ← Accounts خودکار درست می‌شود.
A104: • گزارش‌های کدمحور (Sales، Purchases، Baskets، گزارش‌های Cheques) را با کپی شیت + تغییر کد/بازه برای هر حساب/ماه جدا کنید.
A105: • روی سرستون‌ها نشانگر تولتیپ (💬) دارید — ماوس را روی هر ستون نگه دارید تا توضیحش باز شود.
A106: • ظرفیت هر ردیف با کپی فرمول ردیف آخر قابل افزایش است؛ کدها هرگز عوض نشوند.

Sheet Sync
A1: مازندشت — سورتینگ و بسته‌بندی مرکبات
A2: باغدشت، بخش مرکزی، شهرستان قائم‌شهر، استان مازندران، ایران | MAZANDASHT · CITRUS SORTING & PACKING
A3: برگه فنی — آینه‌ی فایل مادر (INFO)، تراکنش‌ها (Transactions)، چک‌ها (Cheques) و سبد (Baskets) برای تراز. فرمول‌ها را تغییر ندهید. اگر همه سلول‌ها خالی شدند یعنی لینک به‌روز نشده: Data ← Edit Links ← Update Values.
A5: Bank · Code | B5: · Title | C5: · Opening | D5: · Active | F5: Acct · Code | G5: · Nature | H5: · Sub | I5: · Name | K5: SG · Code | L5: · Group | M5: · Title | N5: · Desc | P5: Company | R5: flg | S5: cum·N | T5: packed·P | V5: flg | W5: cum·N | X5: packed·E | Z5: Entry · E | AA5: Entry · G | AB5: Entry · J | AC5: Entry · K | AD5: Entry · L | AE5: Entry · M | AF5: Entry · N | AG5: Issues · Cheque No. | AH5: Issues · Amount | AI5: Issues · Party | AJ5: Entry · S | AK5: Entry · C | AL5: Entry · D | AM5: flg | AN5: cum·N | AO5: packed·A | AP5: flg | AQ5: cum·N | AR5: packed·A | AS5: flg | AT5: cum·N | AU5: packed·A | AW5: Issues · Date | AX5: Bsk · Seller | AY5: Bsk · Qty | AZ5: Bsk · Price
A6: =IF([1]Banks!$B$7="","",[1]Banks!$A$7) | B6: =IF([1]Banks!$B$7="","",[1]Banks!$B$7) | C6: =IF([1]Banks!$B$7="","",[1]Banks!$C$7) | D6: =IF([1]Banks!$B$7="","",[1]Banks!$D$7) | F6: =IF([1]Accounts!$D$7="","",[1]Accounts!$A$7) | G6: =IF([1]Accounts!$D$7="","",[1]Accounts!$B$7) | H6: =IF([1]Accounts!$D$7="","",[1]Accounts!$C$7) | I6: =IF([1]Accounts!$D$7="","",[1]Accounts!$D$7) | K6: =IF([1]SubGroups!$C$7="","",[1]SubGroups!$A$7) | L6: =IF([1]SubGroups!$C$7="","",[1]SubGroups!$B$7) | M6: =IF([1]SubGroups!$C$7="","",[1]SubGroups!$C$7) | N6: =IF([1]SubGroups!$C$7="","",[1]SubGroups!$D$7) | P6: =IF([1]Company!$C$5="","",[1]Company!$C$5) | R6: =IF(AND($F6<>"",$I6<>""),IF(OR($G6="دارایی ثابت",$G6="وام و تسهیلات",$G6="سرمایه و آورده صاحبان"),0,1),0) | S6: =SUM($R$6:$R6) | T6: =IFERROR(INDEX($F$6:$F$565,MATCH(ROW()-5,$S$6:$S$565,0)),"") | V6: =IF(AND($K6<>"",$M6<>""),$L6="هزینه",0)*1 | W6: =SUM($V$6:$V6) | X6: =IFERROR(INDEX($M$6:$M$105,MATCH(ROW()-5,$W$6:$W$105,0)),"") | Z6: =IF([2]Entry!$E$9="","",[2]Entry!$E$9) | AA6: =IF([2]Entry!$G$9="","",[2]Entry!$G$9) | AB6: =IF([2]Entry!$J$9="","",[2]Entry!$J$9) | AC6: =IF([2]Entry!$K$9="","",[2]Entry!$K$9) | AD6: =IF([2]Entry!$L$9="","",[2]Entry!$L$9) | AE6: =IF([2]Entry!$M$9="","",[2]Entry!$M$9) | AF6: =IF([2]Entry!$N$9="","",[2]Entry!$N$9) | AG6: =IF([3]Issues!$B$9="","",[3]Issues!$B$9) | AH6: =IF([3]Issues!$D$9="","",[3]Issues!$D$9) | AI6: =IF([3]Issues!$E$9="","",[3]Issues!$E$9) | AJ6: =IF([2]Entry!$S$9="","",[2]Entry!$S$9) | AK6: =IF([2]Entry!$C$9="","",[2]Entry!$C$9) | AL6: =IF([2]Entry!$D$9="","",[2]Entry!$D$9) | AM6: =IF(AND($F6<>"",$I6<>""),IF($G6="دارایی ثابت",1,0),0) | AN6: =SUM($AM$6:$AM6) | AO6: =IFERROR(INDEX($F$6:$F$565,MATCH(ROW()-5,$AN$6:$AN$565,0)),"") | AP6: =IF(AND($F6<>"",$I6<>""),IF($G6="وام و تسهیلات",1,0),0) | AQ6: =SUM($AP$6:$AP6) | AR6: =IFERROR(INDEX($F$6:$F$565,MATCH(ROW()-5,$AQ$6:$AQ$565,0)),"") | AS6: =IF(AND($F6<>"",$I6<>""),IF($G6="سرمایه و آورده صاحبان",1,0),0) | AT6: =SUM($AS$6:$AS6) | AU6: =IFERROR(INDEX($F$6:$F$565,MATCH(ROW()-5,$AT$6:$AT$565,0)),"") | AW6: =IF([3]Issues!$C$9="","",[3]Issues!$C$9) | AX6: =IF([4]Entry!$E$9="","",[4]Entry!$E$9) | AY6: =IF([4]Entry!$H$9="","",[4]Entry!$H$9) | AZ6: =IF([4]Entry!$I$9="","",[4]Entry!$I$9)
A7: =IF([1]Banks!$B$8="","",[1]Banks!$A$8) | B7: =IF([1]Banks!$B$8="","",[1]Banks!$B$8) | C7: =IF([1]Banks!$B$8="","",[1]Banks!$C$8) | D7: =IF([1]Banks!$B$8="","",[1]Banks!$D$8) | F7: =IF([1]Accounts!$D$8="","",[1]Accounts!$A$8) | G7: =IF([1]Accounts!$D$8="","",[1]Accounts!$B$8) | H7: =IF([1]Accounts!$D$8="","",[1]Accounts!$C$8) | I7: =IF([1]Accounts!$D$8="","",[1]Accounts!$D$8) | K7: =IF([1]SubGroups!$C$8="","",[1]SubGroups!$A$8) | L7: =IF([1]SubGroups!$C$8="","",[1]SubGroups!$B$8) | M7: =IF([1]SubGroups!$C$8="","",[1]SubGroups!$C$8) | N7: =IF([1]SubGroups!$C$8="","",[1]SubGroups!$D$8) | P7: =IF([1]Company!$C$8="","",[1]Company!$C$8) | R7: =IF(AND($F7<>"",$I7<>""),IF(OR($G7="دارایی ثابت",$G7="وام و تسهیلات",$G7="سرمایه و آورده صاحبان"),0,1),0) | S7: =SUM($R$6:$R7) | T7: =IFERROR(INDEX($F$6:$F$565,MATCH(ROW()-5,$S$6:$S$565,0)),"") | V7: =IF(AND($K7<>"",$M7<>""),$L7="هزینه",0)*1 | W7: =SUM($V$6:$V7) | X7: =IFERROR(INDEX($M$6:$M$105,MATCH(ROW()-5,$W$6:$W$105,0)),"") | Z7: =IF([2]Entry!$E$10="","",[2]Entry!$E$10) | AA7: =IF([2]Entry!$G$10="","",[2]Entry!$G$10) | AB7: =IF([2]Entry!$J$10="","",[2]Entry!$J$10) | AC7: =IF([2]Entry!$K$10="","",[2]Entry!$K$10) | AD7: =IF([2]Entry!$L$10="","",[2]Entry!$L$10) | AE7: =IF([2]Entry!$M$10="","",[2]Entry!$M$10) | AF7: =IF([2]Entry!$N$10="","",[2]Entry!$N$10) | AG7: =IF([3]Issues!$B$10="","",[3]Issues!$B$10) | AH7: =IF([3]Issues!$D$10="","",[3]Issues!$D$10) | AI7: =IF([3]Issues!$E$10="","",[3]Issues!$E$10) | AJ7: =IF([2]Entry!$S$10="","",[2]Entry!$S$10) | AK7: =IF([2]Entry!$C$10="","",[2]Entry!$C$10) | AL7: =IF([2]Entry!$D$10="","",[2]Entry!$D$10) | AM7: =IF(AND($F7<>"",$I7<>""),IF($G7="دارایی ثابت",1,0),0) | AN7: =SUM($AM$6:$AM7) | AO7: =IFERROR(INDEX($F$6:$F$565,MATCH(ROW()-5,$AN$6:$AN$565,0)),"") | AP7: =IF(AND($F7<>"",$I7<>""),IF($G7="وام و تسهیلات",1,0),0) | AQ7: =SUM($AP$6:$AP7) | AR7: =IFERROR(INDEX($F$6:$F$565,MATCH(ROW()-5,$AQ$6:$AQ$565,0)),"") | AS7: =IF(AND($F7<>"",$I7<>""),IF($G7="سرمایه و آورده صاحبان",1,0),0) | AT7: =SUM($AS$6:$AS7) | AU7: =IFERROR(INDEX($F$6:$F$565,MATCH(ROW()-5,$AT$6:$AT$565,0)),"") | AW7: =IF([3]Issues!$C$10="","",[3]Issues!$C$10) | AX7: =IF([4]Entry!$E$10="","",[4]Entry!$E$10) | AY7: =IF([4]Entry!$H$10="","",[4]Entry!$H$10) | AZ7: =IF([4]Entry!$I$10="","",[4]Entry!$I$10)
A8: =IF([1]Banks!$B$9="","",[1]Banks!$A$9) | B8: =IF([1]Banks!$B$9="","",[1]Banks!$B$9) | C8: =IF([1]Banks!$B$9="","",[1]Banks!$C$9) | D8: =IF([1]Banks!$B$9="","",[1]Banks!$D$9) | F8: =IF([1]Accounts!$D$9="","",[1]Accounts!$A$9) | G8: =IF([1]Accounts!$D$9="","",[1]Accounts!$B$9) | H8: =IF([1]Accounts!$D$9="","",[1]Accounts!$C$9) | I8: =IF([1]Accounts!$D$9="","",[1]Accounts!$D$9) | K8: =IF([1]SubGroups!$C$9="","",[1]SubGroups!$A$9) | L8: =IF([1]SubGroups!$C$9="","",[1]SubGroups!$B$9) | M8: =IF([1]SubGroups!$C$9="","",[1]SubGroups!$C$9) | N8: =IF([1]SubGroups!$C$9="","",[1]SubGroups!$D$9) | P8: =IF([1]Company!$C$9="","",[1]Company!$C$9) | R8: =IF(AND($F8<>"",$I8<>""),IF(OR($G8="دارایی ثابت",$G8="وام و تسهیلات",$G8="سرمایه و آورده صاحبان"),0,1),0) | S8: =SUM($R$6:$R8) | T8: =IFERROR(INDEX($F$6:$F$565,MATCH(ROW()-5,$S$6:$S$565,0)),"") | V8: =IF(AND($K8<>"",$M8<>""),$L8="هزینه",0)*1 | W8: =SUM($V$6:$V8) | X8: =IFERROR(INDEX($M$6:$M$105,MATCH(ROW()-5,$W$6:$W$105,0)),"") | Z8: =IF([2]Entry!$E$11="","",[2]Entry!$E$11) | AA8: =IF([2]Entry!$G$11="","",[2]Entry!$G$11) | AB8: =IF([2]Entry!$J$11="","",[2]Entry!$J$11) | AC8: =IF([2]Entry!$K$11="","",[2]Entry!$K$11) | AD8: =IF([2]Entry!$L$11="","",[2]Entry!$L$11) | AE8: =IF([2]Entry!$M$11="","",[2]Entry!$M$11) | AF8: =IF([2]Entry!$N$11="","",[2]Entry!$N$11) | AG8: =IF([3]Issues!$B$11="","",[3]Issues!$B$11) | AH8: =IF([3]Issues!$D$11="","",[3]Issues!$D$11) | AI8: =IF([3]Issues!$E$11="","",[3]Issues!$E$11) | AJ8: =IF([2]Entry!$S$11="","",[2]Entry!$S$11) | AK8: =IF([2]Entry!$C$11="","",[2]Entry!$C$11) | AL8: =IF([2]Entry!$D$11="","",[2]Entry!$D$11) | AM8: =IF(AND($F8<>"",$I8<>""),IF($G8="دارایی ثابت",1,0),0) | AN8: =SUM($AM$6:$AM8) | AO8: =IFERROR(INDEX($F$6:$F$565,MATCH(ROW()-5,$AN$6:$AN$565,0)),"") | AP8: =IF(AND($F8<>"",$I8<>""),IF($G8="وام و تسهیلات",1,0),0) | AQ8: =SUM($AP$6:$AP8) | AR8: =IFERROR(INDEX($F$6:$F$565,MATCH(ROW()-5,$AQ$6:$AQ$565,0)),"") | AS8: =IF(AND($F8<>"",$I8<>""),IF($G8="سرمایه و آورده صاحبان",1,0),0) | AT8: =SUM($AS$6:$AS8) | AU8: =IFERROR(INDEX($F$6:$F$565,MATCH(ROW()-5,$AT$6:$AT$565,0)),"") | AW8: =IF([3]Issues!$C$11="","",[3]Issues!$C$11) | AX8: =IF([4]Entry!$E$11="","",[4]Entry!$E$11) | AY8: =IF([4]Entry!$H$11="","",[4]Entry!$H$11) | AZ8: =IF([4]Entry!$I$11="","",[4]Entry!$I$11)
A9: =IF([1]Banks!$B$10="","",[1]Banks!$A$10) | B9: =IF([1]Banks!$B$10="","",[1]Banks!$B$10) | C9: =IF([1]Banks!$B$10="","",[1]Banks!$C$10) | D9: =IF([1]Banks!$B$10="","",[1]Banks!$D$10) | F9: =IF([1]Accounts!$D$10="","",[1]Accounts!$A$10) | G9: =IF([1]Accounts!$D$10="","",[1]Accounts!$B$10) | H9: =IF([1]Accounts!$D$10="","",[1]Accounts!$C$10) | I9: =IF([1]Accounts!$D$10="","",[1]Accounts!$D$10) | K9: =IF([1]SubGroups!$C$10="","",[1]SubGroups!$A$10) | L9: =IF([1]SubGroups!$C$10="","",[1]SubGroups!$B$10) | M9: =IF([1]SubGroups!$C$10="","",[1]SubGroups!$C$10) | N9: =IF([1]SubGroups!$C$10="","",[1]SubGroups!$D$10) | P9: =IF([1]Company!$C$7="","",[1]Company!$C$7) | R9: =IF(AND($F9<>"",$I9<>""),IF(OR($G9="دارایی ثابت",$G9="وام و تسهیلات",$G9="سرمایه و آورده صاحبان"),0,1),0) | S9: =SUM($R$6:$R9) | T9: =IFERROR(INDEX($F$6:$F$565,MATCH(ROW()-5,$S$6:$S$565,0)),"") | V9: =IF(AND($K9<>"",$M9<>""),$L9="هزینه",0)*1 | W9: =SUM($V$6:$V9) | X9: =IFERROR(INDEX($M$6:$M$105,MATCH(ROW()-5,$W$6:$W$105,0)),"") | Z9: =IF([2]Entry!$E$12="","",[2]Entry!$E$12) | AA9: =IF([2]Entry!$G$12="","",[2]Entry!$G$12) | AB9: =IF([2]Entry!$J$12="","",[2]Entry!$J$12) | AC9: =IF([2]Entry!$K$12="","",[2]Entry!$K$12) | AD9: =IF([2]Entry!$L$12="","",[2]Entry!$L$12) | AE9: =IF([2]Entry!$M$12="","",[2]Entry!$M$12) | AF9: =IF([2]Entry!$N$12="","",[2]Entry!$N$12) | AG9: =IF([3]Issues!$B$12="","",[3]Issues!$B$12) | AH9: =IF([3]Issues!$D$12="","",[3]Issues!$D$12) | AI9: =IF([3]Issues!$E$12="","",[3]Issues!$E$12) | AJ9: =IF([2]Entry!$S$12="","",[2]Entry!$S$12) | AK9: =IF([2]Entry!$C$12="","",[2]Entry!$C$12) | AL9: =IF([2]Entry!$D$12="","",[2]Entry!$D$12) | AM9: =IF(AND($F9<>"",$I9<>""),IF($G9="دارایی ثابت",1,0),0) | AN9: =SUM($AM$6:$AM9) | AO9: =IFERROR(INDEX($F$6:$F$565,MATCH(ROW()-5,$AN$6:$AN$565,0)),"") | AP9: =IF(AND($F9<>"",$I9<>""),IF($G9="وام و تسهیلات",1,0),0) | AQ9: =SUM($AP$6:$AP9) | AR9: =IFERROR(INDEX($F$6:$F$565,MATCH(ROW()-5,$AQ$6:$AQ$565,0)),"") | AS9: =IF(AND($F9<>"",$I9<>""),IF($G9="سرمایه و آورده صاحبان",1,0),0) | AT9: =SUM($AS$6:$AS9) | AU9: =IFERROR(INDEX($F$6:$F$565,MATCH(ROW()-5,$AT$6:$AT$565,0)),"") | AW9: =IF([3]Issues!$C$12="","",[3]Issues!$C$12) | AX9: =IF([4]Entry!$E$12="","",[4]Entry!$E$12) | AY9: =IF([4]Entry!$H$12="","",[4]Entry!$H$12) | AZ9: =IF([4]Entry!$I$12="","",[4]Entry!$I$12)
A10: =IF([1]Banks!$B$11="","",[1]Banks!$A$11) | B10: =IF([1]Banks!$B$11="","",[1]Banks!$B$11) | C10: =IF([1]Banks!$B$11="","",[1]Banks!$C$11) | D10: =IF([1]Banks!$B$11="","",[1]Banks!$D$11) | F10: =IF([1]Accounts!$D$11="","",[1]Accounts!$A$11) | G10: =IF([1]Accounts!$D$11="","",[1]Accounts!$B$11) | H10: =IF([1]Accounts!$D$11="","",[1]Accounts!$C$11) | I10: =IF([1]Accounts!$D$11="","",[1]Accounts!$D$11) | K10: =IF([1]SubGroups!$C$11="","",[1]SubGroups!$A$11) | L10: =IF([1]SubGroups!$C$11="","",[1]SubGroups!$B$11) | M10: =IF([1]SubGroups!$C$11="","",[1]SubGroups!$C$11) | N10: =IF([1]SubGroups!$C$11="","",[1]SubGroups!$D$11) | R10: =IF(AND($F10<>"",$I10<>""),IF(OR($G10="دارایی ثابت",$G10="وام و تسهیلات",$G10="سرمایه و آورده صاحبان"),0,1),0) | S10: =SUM($R$6:$R10) | T10: =IFERROR(INDEX($F$6:$F$565,MATCH(ROW()-5,$S$6:$S$565,0)),"") | V10: =IF(AND($K10<>"",$M10<>""),$L10="هزینه",0)*1 | W10: =SUM($V$6:$V10) | X10: =IFERROR(INDEX($M$6:$M$105,MATCH(ROW()-5,$W$6:$W$105,0)),"") | Z10: =IF([2]Entry!$E$13="","",[2]Entry!$E$13) | AA10: =IF([2]Entry!$G$13="","",[2]Entry!$G$13) | AB10: =IF([2]Entry!$J$13="","",[2]Entry!$J$13) | AC10: =IF([2]Entry!$K$13="","",[2]Entry!$K$13) | AD10: =IF([2]Entry!$L$13="","",[2]Entry!$L$13) | AE10: =IF([2]Entry!$M$13="","",[2]Entry!$M$13) | AF10: =IF([2]Entry!$N$13="","",[2]Entry!$N$13) | AG10: =IF([3]Issues!$B$13="","",[3]Issues!$B$13) | AH10: =IF([3]Issues!$D$13="","",[3]Issues!$D$13) | AI10: =IF([3]Issues!$E$13="","",[3]Issues!$E$13) | AJ10: =IF([2]Entry!$S$13="","",[2]Entry!$S$13) | AK10: =IF([2]Entry!$C$13="","",[2]Entry!$C$13) | AL10: =IF([2]Entry!$D$13="","",[2]Entry!$D$13) | AM10: =IF(AND($F10<>"",$I10<>""),IF($G10="دارایی ثابت",1,0),0) | AN10: =SUM($AM$6:$AM10) | AO10: =IFERROR(INDEX($F$6:$F$565,MATCH(ROW()-5,$AN$6:$AN$565,0)),"") | AP10: =IF(AND($F10<>"",$I10<>""),IF($G10="وام و تسهیلات",1,0),0) | AQ10: =SUM($AP$6:$AP10) | AR10: =IFERROR(INDEX($F$6:$F$565,MATCH(ROW()-5,$AQ$6:$AQ$565,0)),"") | AS10: =IF(AND($F10<>"",$I10<>""),IF($G10="سرمایه و آورده صاحبان",1,0),0) | AT10: =SUM($AS$6:$AS10) | AU10: =IFERROR(INDEX($F$6:$F$565,MATCH(ROW()-5,$AT$6:$AT$565,0)),"") | AW10: =IF([3]Issues!$C$13="","",[3]Issues!$C$13) | AX10: =IF([4]Entry!$E$13="","",[4]Entry!$E$13) | AY10: =IF([4]Entry!$H$13="","",[4]Entry!$H$13) | AZ10: =IF([4]Entry!$I$13="","",[4]Entry!$I$13)
A11: =IF([1]Banks!$B$12="","",[1]Banks!$A$12) | B11: =IF([1]Banks!$B$12="","",[1]Banks!$B$12) | C11: =IF([1]Banks!$B$12="","",[1]Banks!$C$12) | D11: =IF([1]Banks!$B$12="","",[1]Banks!$D$12) | F11: =IF([1]Accounts!$D$12="","",[1]Accounts!$A$12) | G11: =IF([1]Accounts!$D$12="","",[1]Accounts!$B$12) | H11: =IF([1]Accounts!$D$12="","",[1]Accounts!$C$12) | I11: =IF([1]Accounts!$D$12="","",[1]Accounts!$D$12) | K11: =IF([1]SubGroups!$C$12="","",[1]SubGroups!$A$12) | L11: =IF([1]SubGroups!$C$12="","",[1]SubGroups!$B$12) | M11: =IF([1]SubGroups!$C$12="","",[1]SubGroups!$C$12) | N11: =IF([1]SubGroups!$C$12="","",[1]SubGroups!$D$12) | R11: =IF(AND($F11<>"",$I11<>""),IF(OR($G11="دارایی ثابت",$G11="وام و تسهیلات",$G11="سرمایه و آورده صاحبان"),0,1),0) | S11: =SUM($R$6:$R11) | T11: =IFERROR(INDEX($F$6:$F$565,MATCH(ROW()-5,$S$6:$S$565,0)),"") | V11: =IF(AND($K11<>"",$M11<>""),$L11="هزینه",0)*1 | W11: =SUM($V$6:$V11) | X11: =IFERROR(INDEX($M$6:$M$105,MATCH(ROW()-5,$W$6:$W$105,0)),"") | Z11: =IF([2]Entry!$E$14="","",[2]Entry!$E$14) | AA11: =IF([2]Entry!$G$14="","",[2]Entry!$G$14) | AB11: =IF([2]Entry!$J$14="","",[2]Entry!$J$14) | AC11: =IF([2]Entry!$K$14="","",[2]Entry!$K$14) | AD11: =IF([2]Entry!$L$14="","",[2]Entry!$L$14) | AE11: =IF([2]Entry!$M$14="","",[2]Entry!$M$14) | AF11: =IF([2]Entry!$N$14="","",[2]Entry!$N$14) | AG11: =IF([3]Issues!$B$14="","",[3]Issues!$B$14) | AH11: =IF([3]Issues!$D$14="","",[3]Issues!$D$14) | AI11: =IF([3]Issues!$E$14="","",[3]Issues!$E$14) | AJ11: =IF([2]Entry!$S$14="","",[2]Entry!$S$14) | AK11: =IF([2]Entry!$C$14="","",[2]Entry!$C$14) | AL11: =IF([2]Entry!$D$14="","",[2]Entry!$D$14) | AM11: =IF(AND($F11<>"",$I11<>""),IF($G11="دارایی ثابت",1,0),0) | AN11: =SUM($AM$6:$AM11) | AO11: =IFERROR(INDEX($F$6:$F$565,MATCH(ROW()-5,$AN$6:$AN$565,0)),"") | AP11: =IF(AND($F11<>"",$I11<>""),IF($G11="وام و تسهیلات",1,0),0) | AQ11: =SUM($AP$6:$AP11) | AR11: =IFERROR(INDEX($F$6:$F$565,MATCH(ROW()-5,$AQ$6:$AQ$565,0)),"") | AS11: =IF(AND($F11<>"",$I11<>""),IF($G11="سرمایه و آورده صاحبان",1,0),0) | AT11: =SUM($AS$6:$AS11) | AU11: =IFERROR(INDEX($F$6:$F$565,MATCH(ROW()-5,$AT$6:$AT$565,0)),"") | AW11: =IF([3]Issues!$C$14="","",[3]Issues!$C$14) | AX11: =IF([4]Entry!$E$14="","",[4]Entry!$E$14) | AY11: =IF([4]Entry!$H$14="","",[4]Entry!$H$14) | AZ11: =IF([4]Entry!$I$14="","",[4]Entry!$I$14)
A12: =IF([1]Banks!$B$13="","",[1]Banks!$A$13) | B12: =IF([1]Banks!$B$13="","",[1]Banks!$B$13) | C12: =IF([1]Banks!$B$13="","",[1]Banks!$C$13) | D12: =IF([1]Banks!$B$13="","",[1]Banks!$D$13) | F12: =IF([1]Accounts!$D$13="","",[1]Accounts!$A$13) | G12: =IF([1]Accounts!$D$13="","",[1]Accounts!$B$13) | H12: =IF([1]Accounts!$D$13="","",[1]Accounts!$C$13) | I12: =IF([1]Accounts!$D$13="","",[1]Accounts!$D$13) | K12: =IF([1]SubGroups!$C$13="","",[1]SubGroups!$A$13) | L12: =IF([1]SubGroups!$C$13="","",[1]SubGroups!$B$13) | M12: =IF([1]SubGroups!$C$13="","",[1]SubGroups!$C$13) | N12: =IF([1]SubGroups!$C$13="","",[1]SubGroups!$D$13) | R12: =IF(AND($F12<>"",$I12<>""),IF(OR($G12="دارایی ثابت",$G12="وام و تسهیلات",$G12="سرمایه و آورده صاحبان"),0,1),0) | S12: =SUM($R$6:$R12) | T12: =IFERROR(INDEX($F$6:$F$565,MATCH(ROW()-5,$S$6:$S$565,0)),"") | V12: =IF(AND($K12<>"",$M12<>""),$L12="هزینه",0)*1 | W12: =SUM($V$6:$V12) | X12: =IFERROR(INDEX($M$6:$M$105,MATCH(ROW()-5,$W$6:$W$105,0)),"") | Z12: =IF([2]Entry!$E$15="","",[2]Entry!$E$15) | AA12: =IF([2]Entry!$G$15="","",[2]Entry!$G$15) | AB12: =IF([2]Entry!$J$15="","",[2]Entry!$J$15) | AC12: =IF([2]Entry!$K$15="","",[2]Entry!$K$15) | AD12: =IF([2]Entry!$L$15="","",[2]Entry!$L$15) | AE12: =IF([2]Entry!$M$15="","",[2]Entry!$M$15) | AF12: =IF([2]Entry!$N$15="","",[2]Entry!$N$15) | AG12: =IF([3]Issues!$B$15="","",[3]Issues!$B$15) | AH12: =IF([3]Issues!$D$15="","",[3]Issues!$D$15) | AI12: =IF([3]Issues!$E$15="","",[3]Issues!$E$15) | AJ12: =IF([2]Entry!$S$15="","",[2]Entry!$S$15) | AK12: =IF([2]Entry!$C$15="","",[2]Entry!$C$15) | AL12: =IF([2]Entry!$D$15="","",[2]Entry!$D$15) | AM12: =IF(AND($F12<>"",$I12<>""),IF($G12="دارایی ثابت",1,0),0) | AN12: =SUM($AM$6:$AM12) | AO12: =IFERROR(INDEX($F$6:$F$565,MATCH(ROW()-5,$AN$6:$AN$565,0)),"") | AP12: =IF(AND($F12<>"",$I12<>""),IF($G12="وام و تسهیلات",1,0),0) | AQ12: =SUM($AP$6:$AP12) | AR12: =IFERROR(INDEX($F$6:$F$565,MATCH(ROW()-5,$AQ$6:$AQ$565,0)),"") | AS12: =IF(AND($F12<>"",$I12<>""),IF($G12="سرمایه و آورده صاحبان",1,0),0) | AT12: =SUM($AS$6:$AS12) | AU12: =IFERROR(INDEX($F$6:$F$565,MATCH(ROW()-5,$AT$6:$AT$565,0)),"") | AW12: =IF([3]Issues!$C$15="","",[3]Issues!$C$15) | AX12: =IF([4]Entry!$E$15="","",[4]Entry!$E$15) | AY12: =IF([4]Entry!$H$15="","",[4]Entry!$H$15) | AZ12: =IF([4]Entry!$I$15="","",[4]Entry!$I$15)
A13: =IF([1]Banks!$B$14="","",[1]Banks!$A$14) | B13: =IF([1]Banks!$B$14="","",[1]Banks!$B$14) | C13: =IF([1]Banks!$B$14="","",[1]Banks!$C$14) | D13: =IF([1]Banks!$B$14="","",[1]Banks!$D$14) | F13: =IF([1]Accounts!$D$14="","",[1]Accounts!$A$14) | G13: =IF([1]Accounts!$D$14="","",[1]Accounts!$B$14) | H13: =IF([1]Accounts!$D$14="","",[1]Accounts!$C$14) | I13: =IF([1]Accounts!$D$14="","",[1]Accounts!$D$14) | K13: =IF([1]SubGroups!$C$14="","",[1]SubGroups!$A$14) | L13: =IF([1]SubGroups!$C$14="","",[1]SubGroups!$B$14) | M13: =IF([1]SubGroups!$C$14="","",[1]SubGroups!$C$14) | N13: =IF([1]SubGroups!$C$14="","",[1]SubGroups!$D$14) | R13: =IF(AND($F13<>"",$I13<>""),IF(OR($G13="دارایی ثابت",$G13="وام و تسهیلات",$G13="سرمایه و آورده صاحبان"),0,1),0) | S13: =SUM($R$6:$R13) | T13: =IFERROR(INDEX($F$6:$F$565,MATCH(ROW()-5,$S$6:$S$565,0)),"") | V13: =IF(AND($K13<>"",$M13<>""),$L13="هزینه",0)*1 | W13: =SUM($V$6:$V13) | X13: =IFERROR(INDEX($M$6:$M$105,MATCH(ROW()-5,$W$6:$W$105,0)),"") | Z13: =IF([2]Entry!$E$16="","",[2]Entry!$E$16) | AA13: =IF([2]Entry!$G$16="","",[2]Entry!$G$16) | AB13: =IF([2]Entry!$J$16="","",[2]Entry!$J$16) | AC13: =IF([2]Entry!$K$16="","",[2]Entry!$K$16) | AD13: =IF([2]Entry!$L$16="","",[2]Entry!$L$16) | AE13: =IF([2]Entry!$M$16="","",[2]Entry!$M$16) | AF13: =IF([2]Entry!$N$16="","",[2]Entry!$N$16) | AG13: =IF([3]Issues!$B$16="","",[3]Issues!$B$16) | AH13: =IF([3]Issues!$D$16="","",[3]Issues!$D$16) | AI13: =IF([3]Issues!$E$16="","",[3]Issues!$E$16) | AJ13: =IF([2]Entry!$S$16="","",[2]Entry!$S$16) | AK13: =IF([2]Entry!$C$16="","",[2]Entry!$C$16) | AL13: =IF([2]Entry!$D$16="","",[2]Entry!$D$16) | AM13: =IF(AND($F13<>"",$I13<>""),IF($G13="دارایی ثابت",1,0),0) | AN13: =SUM($AM$6:$AM13) | AO13: =IFERROR(INDEX($F$6:$F$565,MATCH(ROW()-5,$AN$6:$AN$565,0)),"") | AP13: =IF(AND($F13<>"",$I13<>""),IF($G13="وام و تسهیلات",1,0),0) | AQ13: =SUM($AP$6:$AP13) | AR13: =IFERROR(INDEX($F$6:$F$565,MATCH(ROW()-5,$AQ$6:$AQ$565,0)),"") | AS13: =IF(AND($F13<>"",$I13<>""),IF($G13="سرمایه و آورده صاحبان",1,0),0) | AT13: =SUM($AS$6:$AS13) | AU13: =IFERROR(INDEX($F$6:$F$565,MATCH(ROW()-5,$AT$6:$AT$565,0)),"") | AW13: =IF([3]Issues!$C$16="","",[3]Issues!$C$16) | AX13: =IF([4]Entry!$E$16="","",[4]Entry!$E$16) | AY13: =IF([4]Entry!$H$16="","",[4]Entry!$H$16) | AZ13: =IF([4]Entry!$I$16="","",[4]Entry!$I$16)
A14: =IF([1]Banks!$B$15="","",[1]Banks!$A$15) | B14: =IF([1]Banks!$B$15="","",[1]Banks!$B$15) | C14: =IF([1]Banks!$B$15="","",[1]Banks!$C$15) | D14: =IF([1]Banks!$B$15="","",[1]Banks!$D$15) | F14: =IF([1]Accounts!$D$15="","",[1]Accounts!$A$15) | G14: =IF([1]Accounts!$D$15="","",[1]Accounts!$B$15) | H14: =IF([1]Accounts!$D$15="","",[1]Accounts!$C$15) | I14: =IF([1]Accounts!$D$15="","",[1]Accounts!$D$15) | K14: =IF([1]SubGroups!$C$15="","",[1]SubGroups!$A$15) | L14: =IF([1]SubGroups!$C$15="","",[1]SubGroups!$B$15) | M14: =IF([1]SubGroups!$C$15="","",[1]SubGroups!$C$15) | N14: =IF([1]SubGroups!$C$15="","",[1]SubGroups!$D$15) | R14: =IF(AND($F14<>"",$I14<>""),IF(OR($G14="دارایی ثابت",$G14="وام و تسهیلات",$G14="سرمایه و آورده صاحبان"),0,1),0) | S14: =SUM($R$6:$R14) | T14: =IFERROR(INDEX($F$6:$F$565,MATCH(ROW()-5,$S$6:$S$565,0)),"") | V14: =IF(AND($K14<>"",$M14<>""),$L14="هزینه",0)*1 | W14: =SUM($V$6:$V14) | X14: =IFERROR(INDEX($M$6:$M$105,MATCH(ROW()-5,$W$6:$W$105,0)),"") | Z14: =IF([2]Entry!$E$17="","",[2]Entry!$E$17) | AA14: =IF([2]Entry!$G$17="","",[2]Entry!$G$17) | AB14: =IF([2]Entry!$J$17="","",[2]Entry!$J$17) | AC14: =IF([2]Entry!$K$17="","",[2]Entry!$K$17) | AD14: =IF([2]Entry!$L$17="","",[2]Entry!$L$17) | AE14: =IF([2]Entry!$M$17="","",[2]Entry!$M$17) | AF14: =IF([2]Entry!$N$17="","",[2]Entry!$N$17) | AG14: =IF([3]Issues!$B$17="","",[3]Issues!$B$17) | AH14: =IF([3]Issues!$D$17="","",[3]Issues!$D$17) | AI14: =IF([3]Issues!$E$17="","",[3]Issues!$E$17) | AJ14: =IF([2]Entry!$S$17="","",[2]Entry!$S$17) | AK14: =IF([2]Entry!$C$17="","",[2]Entry!$C$17) | AL14: =IF([2]Entry!$D$17="","",[2]Entry!$D$17) | AM14: =IF(AND($F14<>"",$I14<>""),IF($G14="دارایی ثابت",1,0),0) | AN14: =SUM($AM$6:$AM14) | AO14: =IFERROR(INDEX($F$6:$F$565,MATCH(ROW()-5,$AN$6:$AN$565,0)),"") | AP14: =IF(AND($F14<>"",$I14<>""),IF($G14="وام و تسهیلات",1,0),0) | AQ14: =SUM($AP$6:$AP14) | AR14: =IFERROR(INDEX($F$6:$F$565,MATCH(ROW()-5,$AQ$6:$AQ$565,0)),"") | AS14: =IF(AND($F14<>"",$I14<>""),IF($G14="سرمایه و آورده صاحبان",1,0),0) | AT14: =SUM($AS$6:$AS14) | AU14: =IFERROR(INDEX($F$6:$F$565,MATCH(ROW()-5,$AT$6:$AT$565,0)),"") | AW14: =IF([3]Issues!$C$17="","",[3]Issues!$C$17) | AX14: =IF([4]Entry!$E$17="","",[4]Entry!$E$17) | AY14: =IF([4]Entry!$H$17="","",[4]Entry!$H$17) | AZ14: =IF([4]Entry!$I$17="","",[4]Entry!$I$17)
A15: =IF([1]Banks!$B$16="","",[1]Banks!$A$16) | B15: =IF([1]Banks!$B$16="","",[1]Banks!$B$16) | C15: =IF([1]Banks!$B$16="","",[1]Banks!$C$16) | D15: =IF([1]Banks!$B$16="","",[1]Banks!$D$16) | F15: =IF([1]Accounts!$D$16="","",[1]Accounts!$A$16) | G15: =IF([1]Accounts!$D$16="","",[1]Accounts!$B$16) | H15: =IF([1]Accounts!$D$16="","",[1]Accounts!$C$16) | I15: =IF([1]Accounts!$D$16="","",[1]Accounts!$D$16) | K15: =IF([1]SubGroups!$C$16="","",[1]SubGroups!$A$16) | L15: =IF([1]SubGroups!$C$16="","",[1]SubGroups!$B$16) | M15: =IF([1]SubGroups!$C$16="","",[1]SubGroups!$C$16) | N15: =IF([1]SubGroups!$C$16="","",[1]SubGroups!$D$16) | R15: =IF(AND($F15<>"",$I15<>""),IF(OR($G15="دارایی ثابت",$G15="وام و تسهیلات",$G15="سرمایه و آورده صاحبان"),0,1),0) | S15: =SUM($R$6:$R15) | T15: =IFERROR(INDEX($F$6:$F$565,MATCH(ROW()-5,$S$6:$S$565,0)),"") | V15: =IF(AND($K15<>"",$M15<>""),$L15="هزینه",0)*1 | W15: =SUM($V$6:$V15) | X15: =IFERROR(INDEX($M$6:$M$105,MATCH(ROW()-5,$W$6:$W$105,0)),"") | Z15: =IF([2]Entry!$E$18="","",[2]Entry!$E$18) | AA15: =IF([2]Entry!$G$18="","",[2]Entry!$G$18) | AB15: =IF([2]Entry!$J$18="","",[2]Entry!$J$18) | AC15: =IF([2]Entry!$K$18="","",[2]Entry!$K$18) | AD15: =IF([2]Entry!$L$18="","",[2]Entry!$L$18) | AE15: =IF([2]Entry!$M$18="","",[2]Entry!$M$18) | AF15: =IF([2]Entry!$N$18="","",[2]Entry!$N$18) | AG15: =IF([3]Issues!$B$18="","",[3]Issues!$B$18) | AH15: =IF([3]Issues!$D$18="","",[3]Issues!$D$18) | AI15: =IF([3]Issues!$E$18="","",[3]Issues!$E$18) | AJ15: =IF([2]Entry!$S$18="","",[2]Entry!$S$18) | AK15: =IF([2]Entry!$C$18="","",[2]Entry!$C$18) | AL15: =IF([2]Entry!$D$18="","",[2]Entry!$D$18) | AM15: =IF(AND($F15<>"",$I15<>""),IF($G15="دارایی ثابت",1,0),0) | AN15: =SUM($AM$6:$AM15) | AO15: =IFERROR(INDEX($F$6:$F$565,MATCH(ROW()-5,$AN$6:$AN$565,0)),"") | AP15: =IF(AND($F15<>"",$I15<>""),IF($G15="وام و تسهیلات",1,0),0) | AQ15: =SUM($AP$6:$AP15) | AR15: =IFERROR(INDEX($F$6:$F$565,MATCH(ROW()-5,$AQ$6:$AQ$565,0)),"") | AS15: =IF(AND($F15<>"",$I15<>""),IF($G15="سرمایه و آورده صاحبان",1,0),0) | AT15: =SUM($AS$6:$AS15) | AU15: =IFERROR(INDEX($F$6:$F$565,MATCH(ROW()-5,$AT$6:$AT$565,0)),"") | AW15: =IF([3]Issues!$C$18="","",[3]Issues!$C$18) | AX15: =IF([4]Entry!$E$18="","",[4]Entry!$E$18) | AY15: =IF([4]Entry!$H$18="","",[4]Entry!$H$18) | AZ15: =IF([4]Entry!$I$18="","",[4]Entry!$I$18)
F16: =IF([1]Accounts!$D$17="","",[1]Accounts!$A$17) | G16: =IF([1]Accounts!$D$17="","",[1]Accounts!$B$17) | H16: =IF([1]Accounts!$D$17="","",[1]Accounts!$C$17) | I16: =IF([1]Accounts!$D$17="","",[1]Accounts!$D$17) | K16: =IF([1]SubGroups!$C$17="","",[1]SubGroups!$A$17) | L16: =IF([1]SubGroups!$C$17="","",[1]SubGroups!$B$17) | M16: =IF([1]SubGroups!$C$17="","",[1]SubGroups!$C$17) | N16: =IF([1]SubGroups!$C$17="","",[1]SubGroups!$D$17) | R16: =IF(AND($F16<>"",$I16<>""),IF(OR($G16="دارایی ثابت",$G16="وام و تسهیلات",$G16="سرمایه و آورده صاحبان"),0,1),0) | S16: =SUM($R$6:$R16) | T16: =IFERROR(INDEX($F$6:$F$565,MATCH(ROW()-5,$S$6:$S$565,0)),"") | V16: =IF(AND($K16<>"",$M16<>""),$L16="هزینه",0)*1 | W16: =SUM($V$6:$V16) | X16: =IFERROR(INDEX($M$6:$M$105,MATCH(ROW()-5,$W$6:$W$105,0)),"") | Z16: =IF([2]Entry!$E$19="","",[2]Entry!$E$19) | AA16: =IF([2]Entry!$G$19="","",[2]Entry!$G$19) | AB16: =IF([2]Entry!$J$19="","",[2]Entry!$J$19) | AC16: =IF([2]Entry!$K$19="","",[2]Entry!$K$19) | AD16: =IF([2]Entry!$L$19="","",[2]Entry!$L$19) | AE16: =IF([2]Entry!$M$19="","",[2]Entry!$M$19) | AF16: =IF([2]Entry!$N$19="","",[2]Entry!$N$19) | AG16: =IF([3]Issues!$B$19="","",[3]Issues!$B$19) | AH16: =IF([3]Issues!$D$19="","",[3]Issues!$D$19) | AI16: =IF([3]Issues!$E$19="","",[3]Issues!$E$19) | AJ16: =IF([2]Entry!$S$19="","",[2]Entry!$S$19) | AK16: =IF([2]Entry!$C$19="","",[2]Entry!$C$19) | AL16: =IF([2]Entry!$D$19="","",[2]Entry!$D$19) | AM16: =IF(AND($F16<>"",$I16<>""),IF($G16="دارایی ثابت",1,0),0) | AN16: =SUM($AM$6:$AM16) | AO16: =IFERROR(INDEX($F$6:$F$565,MATCH(ROW()-5,$AN$6:$AN$565,0)),"") | AP16: =IF(AND($F16<>"",$I16<>""),IF($G16="وام و تسهیلات",1,0),0) | AQ16: =SUM($AP$6:$AP16) | AR16: =IFERROR(INDEX($F$6:$F$565,MATCH(ROW()-5,$AQ$6:$AQ$565,0)),"") | AS16: =IF(AND($F16<>"",$I16<>""),IF($G16="سرمایه و آورده صاحبان",1,0),0) | AT16: =SUM($AS$6:$AS16) | AU16: =IFERROR(INDEX($F$6:$F$565,MATCH(ROW()-5,$AT$6:$AT$565,0)),"") | AW16: =IF([3]Issues!$C$19="","",[3]Issues!$C$19) | AX16: =IF([4]Entry!$E$19="","",[4]Entry!$E$19) | AY16: =IF([4]Entry!$H$19="","",[4]Entry!$H$19) | AZ16: =IF([4]Entry!$I$19="","",[4]Entry!$I$19)
F17: =IF([1]Accounts!$D$18="","",[1]Accounts!$A$18) | G17: =IF([1]Accounts!$D$18="","",[1]Accounts!$B$18) | H17: =IF([1]Accounts!$D$18="","",[1]Accounts!$C$18) | I17: =IF([1]Accounts!$D$18="","",[1]Accounts!$D$18) | K17: =IF([1]SubGroups!$C$18="","",[1]SubGroups!$A$18) | L17: =IF([1]SubGroups!$C$18="","",[1]SubGroups!$B$18) | M17: =IF([1]SubGroups!$C$18="","",[1]SubGroups!$C$18) | N17: =IF([1]SubGroups!$C$18="","",[1]SubGroups!$D$18) | R17: =IF(AND($F17<>"",$I17<>""),IF(OR($G17="دارایی ثابت",$G17="وام و تسهیلات",$G17="سرمایه و آورده صاحبان"),0,1),0) | S17: =SUM($R$6:$R17) | T17: =IFERROR(INDEX($F$6:$F$565,MATCH(ROW()-5,$S$6:$S$565,0)),"") | V17: =IF(AND($K17<>"",$M17<>""),$L17="هزینه",0)*1 | W17: =SUM($V$6:$V17) | X17: =IFERROR(INDEX($M$6:$M$105,MATCH(ROW()-5,$W$6:$W$105,0)),"") | Z17: =IF([2]Entry!$E$20="","",[2]Entry!$E$20) | AA17: =IF([2]Entry!$G$20="","",[2]Entry!$G$20) | AB17: =IF([2]Entry!$J$20="","",[2]Entry!$J$20) | AC17: =IF([2]Entry!$K$20="","",[2]Entry!$K$20) | AD17: =IF([2]Entry!$L$20="","",[2]Entry!$L$20) | AE17: =IF([2]Entry!$M$20="","",[2]Entry!$M$20) | AF17: =IF([2]Entry!$N$20="","",[2]Entry!$N$20) | AG17: =IF([3]Issues!$B$20="","",[3]Issues!$B$20) | AH17: =IF([3]Issues!$D$20="","",[3]Issues!$D$20) | AI17: =IF([3]Issues!$E$20="","",[3]Issues!$E$20) | AJ17: =IF([2]Entry!$S$20="","",[2]Entry!$S$20) | AK17: =IF([2]Entry!$C$20="","",[2]Entry!$C$20) | AL17: =IF([2]Entry!$D$20="","",[2]Entry!$D$20) | AM17: =IF(AND($F17<>"",$I17<>""),IF($G17="دارایی ثابت",1,0),0) | AN17: =SUM($AM$6:$AM17) | AO17: =IFERROR(INDEX($F$6:$F$565,MATCH(ROW()-5,$AN$6:$AN$565,0)),"") | AP17: =IF(AND($F17<>"",$I17<>""),IF($G17="وام و تسهیلات",1,0),0) | AQ17: =SUM($AP$6:$AP17) | AR17: =IFERROR(INDEX($F$6:$F$565,MATCH(ROW()-5,$AQ$6:$AQ$565,0)),"") | AS17: =IF(AND($F17<>"",$I17<>""),IF($G17="سرمایه و آورده صاحبان",1,0),0) | AT17: =SUM($AS$6:$AS17) | AU17: =IFERROR(INDEX($F$6:$F$565,MATCH(ROW()-5,$AT$6:$AT$565,0)),"") | AW17: =IF([3]Issues!$C$20="","",[3]Issues!$C$20) | AX17: =IF([4]Entry!$E$20="","",[4]Entry!$E$20) | AY17: =IF([4]Entry!$H$20="","",[4]Entry!$H$20) | AZ17: =IF([4]Entry!$I$20="","",[4]Entry!$I$20)
F18: =IF([1]Accounts!$D$19="","",[1]Accounts!$A$19) | G18: =IF([1]Accounts!$D$19="","",[1]Accounts!$B$19) | H18: =IF([1]Accounts!$D$19="","",[1]Accounts!$C$19) | I18: =IF([1]Accounts!$D$19="","",[1]Accounts!$D$19) | K18: =IF([1]SubGroups!$C$19="","",[1]SubGroups!$A$19) | L18: =IF([1]SubGroups!$C$19="","",[1]SubGroups!$B$19) | M18: =IF([1]SubGroups!$C$19="","",[1]SubGroups!$C$19) | N18: =IF([1]SubGroups!$C$19="","",[1]SubGroups!$D$19) | R18: =IF(AND($F18<>"",$I18<>""),IF(OR($G18="دارایی ثابت",$G18="وام و تسهیلات",$G18="سرمایه و آورده صاحبان"),0,1),0) | S18: =SUM($R$6:$R18) | T18: =IFERROR(INDEX($F$6:$F$565,MATCH(ROW()-5,$S$6:$S$565,0)),"") | V18: =IF(AND($K18<>"",$M18<>""),$L18="هزینه",0)*1 | W18: =SUM($V$6:$V18) | X18: =IFERROR(INDEX($M$6:$M$105,MATCH(ROW()-5,$W$6:$W$105,0)),"") | Z18: =IF([2]Entry!$E$21="","",[2]Entry!$E$21) | AA18: =IF([2]Entry!$G$21="","",[2]Entry!$G$21) | AB18: =IF([2]Entry!$J$21="","",[2]Entry!$J$21) | AC18: =IF([2]Entry!$K$21="","",[2]Entry!$K$21) | AD18: =IF([2]Entry!$L$21="","",[2]Entry!$L$21) | AE18: =IF([2]Entry!$M$21="","",[2]Entry!$M$21) | AF18: =IF([2]Entry!$N$21="","",[2]Entry!$N$21) | AG18: =IF([3]Issues!$B$21="","",[3]Issues!$B$21) | AH18: =IF([3]Issues!$D$21="","",[3]Issues!$D$21) | AI18: =IF([3]Issues!$E$21="","",[3]Issues!$E$21) | AJ18: =IF([2]Entry!$S$21="","",[2]Entry!$S$21) | AK18: =IF([2]Entry!$C$21="","",[2]Entry!$C$21) | AL18: =IF([2]Entry!$D$21="","",[2]Entry!$D$21) | AM18: =IF(AND($F18<>"",$I18<>""),IF($G18="دارایی ثابت",1,0),0) | AN18: =SUM($AM$6:$AM18) | AO18: =IFERROR(INDEX($F$6:$F$565,MATCH(ROW()-5,$AN$6:$AN$565,0)),"") | AP18: =IF(AND($F18<>"",$I18<>""),IF($G18="وام و تسهیلات",1,0),0) | AQ18: =SUM($AP$6:$AP18) | AR18: =IFERROR(INDEX($F$6:$F$565,MATCH(ROW()-5,$AQ$6:$AQ$565,0)),"") | AS18: =IF(AND($F18<>"",$I18<>""),IF($G18="سرمایه و آورده صاحبان",1,0),0) | AT18: =SUM($AS$6:$AS18) | AU18: =IFERROR(INDEX($F$6:$F$565,MATCH(ROW()-5,$AT$6:$AT$565,0)),"") | AW18: =IF([3]Issues!$C$21="","",[3]Issues!$C$21) | AX18: =IF([4]Entry!$E$21="","",[4]Entry!$E$21) | AY18: =IF([4]Entry!$H$21="","",[4]Entry!$H$21) | AZ18: =IF([4]Entry!$I$21="","",[4]Entry!$I$21)
F19: =IF([1]Accounts!$D$20="","",[1]Accounts!$A$20) | G19: =IF([1]Accounts!$D$20="","",[1]Accounts!$B$20) | H19: =IF([1]Accounts!$D$20="","",[1]Accounts!$C$20) | I19: =IF([1]Accounts!$D$20="","",[1]Accounts!$D$20) | K19: =IF([1]SubGroups!$C$20="","",[1]SubGroups!$A$20) | L19: =IF([1]SubGroups!$C$20="","",[1]SubGroups!$B$20) | M19: =IF([1]SubGroups!$C$20="","",[1]SubGroups!$C$20) | N19: =IF([1]SubGroups!$C$20="","",[1]SubGroups!$D$20) | R19: =IF(AND($F19<>"",$I19<>""),IF(OR($G19="دارایی ثابت",$G19="وام و تسهیلات",$G19="سرمایه و آورده صاحبان"),0,1),0) | S19: =SUM($R$6:$R19) | T19: =IFERROR(INDEX($F$6:$F$565,MATCH(ROW()-5,$S$6:$S$565,0)),"") | V19: =IF(AND($K19<>"",$M19<>""),$L19="هزینه",0)*1 | W19: =SUM($V$6:$V19) | X19: =IFERROR(INDEX($M$6:$M$105,MATCH(ROW()-5,$W$6:$W$105,0)),"") | Z19: =IF([2]Entry!$E$22="","",[2]Entry!$E$22) | AA19: =IF([2]Entry!$G$22="","",[2]Entry!$G$22) | AB19: =IF([2]Entry!$J$22="","",[2]Entry!$J$22) | AC19: =IF([2]Entry!$K$22="","",[2]Entry!$K$22) | AD19: =IF([2]Entry!$L$22="","",[2]Entry!$L$22) | AE19: =IF([2]Entry!$M$22="","",[2]Entry!$M$22) | AF19: =IF([2]Entry!$N$22="","",[2]Entry!$N$22) | AG19: =IF([3]Issues!$B$22="","",[3]Issues!$B$22) | AH19: =IF([3]Issues!$D$22="","",[3]Issues!$D$22) | AI19: =IF([3]Issues!$E$22="","",[3]Issues!$E$22) | AJ19: =IF([2]Entry!$S$22="","",[2]Entry!$S$22) | AK19: =IF([2]Entry!$C$22="","",[2]Entry!$C$22) | AL19: =IF([2]Entry!$D$22="","",[2]Entry!$D$22) | AM19: =IF(AND($F19<>"",$I19<>""),IF($G19="دارایی ثابت",1,0),0) | AN19: =SUM($AM$6:$AM19) | AO19: =IFERROR(INDEX($F$6:$F$565,MATCH(ROW()-5,$AN$6:$AN$565,0)),"") | AP19: =IF(AND($F19<>"",$I19<>""),IF($G19="وام و تسهیلات",1,0),0) | AQ19: =SUM($AP$6:$AP19) | AR19: =IFERROR(INDEX($F$6:$F$565,MATCH(ROW()-5,$AQ$6:$AQ$565,0)),"") | AS19: =IF(AND($F19<>"",$I19<>""),IF($G19="سرمایه و آورده صاحبان",1,0),0) | AT19: =SUM($AS$6:$AS19) | AU19: =IFERROR(INDEX($F$6:$F$565,MATCH(ROW()-5,$AT$6:$AT$565,0)),"") | AW19: =IF([3]Issues!$C$22="","",[3]Issues!$C$22) | AX19: =IF([4]Entry!$E$22="","",[4]Entry!$E$22) | AY19: =IF([4]Entry!$H$22="","",[4]Entry!$H$22) | AZ19: =IF([4]Entry!$I$22="","",[4]Entry!$I$22)
F20: =IF([1]Accounts!$D$21="","",[1]Accounts!$A$21) | G20: =IF([1]Accounts!$D$21="","",[1]Accounts!$B$21) | H20: =IF([1]Accounts!$D$21="","",[1]Accounts!$C$21) | I20: =IF([1]Accounts!$D$21="","",[1]Accounts!$D$21) | K20: =IF([1]SubGroups!$C$21="","",[1]SubGroups!$A$21) | L20: =IF([1]SubGroups!$C$21="","",[1]SubGroups!$B$21) | M20: =IF([1]SubGroups!$C$21="","",[1]SubGroups!$C$21) | N20: =IF([1]SubGroups!$C$21="","",[1]SubGroups!$D$21) | R20: =IF(AND($F20<>"",$I20<>""),IF(OR($G20="دارایی ثابت",$G20="وام و تسهیلات",$G20="سرمایه و آورده صاحبان"),0,1),0) | S20: =SUM($R$6:$R20) | T20: =IFERROR(INDEX($F$6:$F$565,MATCH(ROW()-5,$S$6:$S$565,0)),"") | V20: =IF(AND($K20<>"",$M20<>""),$L20="هزینه",0)*1 | W20: =SUM($V$6:$V20) | X20: =IFERROR(INDEX($M$6:$M$105,MATCH(ROW()-5,$W$6:$W$105,0)),"") | Z20: =IF([2]Entry!$E$23="","",[2]Entry!$E$23) | AA20: =IF([2]Entry!$G$23="","",[2]Entry!$G$23) | AB20: =IF([2]Entry!$J$23="","",[2]Entry!$J$23) | AC20: =IF([2]Entry!$K$23="","",[2]Entry!$K$23) | AD20: =IF([2]Entry!$L$23="","",[2]Entry!$L$23) | AE20: =IF([2]Entry!$M$23="","",[2]Entry!$M$23) | AF20: =IF([2]Entry!$N$23="","",[2]Entry!$N$23) | AG20: =IF([3]Issues!$B$23="","",[3]Issues!$B$23) | AH20: =IF([3]Issues!$D$23="","",[3]Issues!$D$23) | AI20: =IF([3]Issues!$E$23="","",[3]Issues!$E$23) | AJ20: =IF([2]Entry!$S$23="","",[2]Entry!$S$23) | AK20: =IF([2]Entry!$C$23="","",[2]Entry!$C$23) | AL20: =IF([2]Entry!$D$23="","",[2]Entry!$D$23) | AM20: =IF(AND($F20<>"",$I20<>""),IF($G20="دارایی ثابت",1,0),0) | AN20: =SUM($AM$6:$AM20) | AO20: =IFERROR(INDEX($F$6:$F$565,MATCH(ROW()-5,$AN$6:$AN$565,0)),"") | AP20: =IF(AND($F20<>"",$I20<>""),IF($G20="وام و تسهیلات",1,0),0) | AQ20: =SUM($AP$6:$AP20) | AR20: =IFERROR(INDEX($F$6:$F$565,MATCH(ROW()-5,$AQ$6:$AQ$565,0)),"") | AS20: =IF(AND($F20<>"",$I20<>""),IF($G20="سرمایه و آورده صاحبان",1,0),0) | AT20: =SUM($AS$6:$AS20) | AU20: =IFERROR(INDEX($F$6:$F$565,MATCH(ROW()-5,$AT$6:$AT$565,0)),"") | AW20: =IF([3]Issues!$C$23="","",[3]Issues!$C$23) | AX20: =IF([4]Entry!$E$23="","",[4]Entry!$E$23) | AY20: =IF([4]Entry!$H$23="","",[4]Entry!$H$23) | AZ20: =IF([4]Entry!$I$23="","",[4]Entry!$I$23)
F21: =IF([1]Accounts!$D$22="","",[1]Accounts!$A$22) | G21: =IF([1]Accounts!$D$22="","",[1]Accounts!$B$22) | H21: =IF([1]Accounts!$D$22="","",[1]Accounts!$C$22) | I21: =IF([1]Accounts!$D$22="","",[1]Accounts!$D$22) | K21: =IF([1]SubGroups!$C$22="","",[1]SubGroups!$A$22) | L21: =IF([1]SubGroups!$C$22="","",[1]SubGroups!$B$22) | M21: =IF([1]SubGroups!$C$22="","",[1]SubGroups!$C$22) | N21: =IF([1]SubGroups!$C$22="","",[1]SubGroups!$D$22) | R21: =IF(AND($F21<>"",$I21<>""),IF(OR($G21="دارایی ثابت",$G21="وام و تسهیلات",$G21="سرمایه و آورده صاحبان"),0,1),0) | S21: =SUM($R$6:$R21) | T21: =IFERROR(INDEX($F$6:$F$565,MATCH(ROW()-5,$S$6:$S$565,0)),"") | V21: =IF(AND($K21<>"",$M21<>""),$L21="هزینه",0)*1 | W21: =SUM($V$6:$V21) | X21: =IFERROR(INDEX($M$6:$M$105,MATCH(ROW()-5,$W$6:$W$105,0)),"") | Z21: =IF([2]Entry!$E$24="","",[2]Entry!$E$24) | AA21: =IF([2]Entry!$G$24="","",[2]Entry!$G$24) | AB21: =IF([2]Entry!$J$24="","",[2]Entry!$J$24) | AC21: =IF([2]Entry!$K$24="","",[2]Entry!$K$24) | AD21: =IF([2]Entry!$L$24="","",[2]Entry!$L$24) | AE21: =IF([2]Entry!$M$24="","",[2]Entry!$M$24) | AF21: =IF([2]Entry!$N$24="","",[2]Entry!$N$24) | AG21: =IF([3]Issues!$B$24="","",[3]Issues!$B$24) | AH21: =IF([3]Issues!$D$24="","",[3]Issues!$D$24) | AI21: =IF([3]Issues!$E$24="","",[3]Issues!$E$24) | AJ21: =IF([2]Entry!$S$24="","",[2]Entry!$S$24) | AK21: =IF([2]Entry!$C$24="","",[2]Entry!$C$24) | AL21: =IF([2]Entry!$D$24="","",[2]Entry!$D$24) | AM21: =IF(AND($F21<>"",$I21<>""),IF($G21="دارایی ثابت",1,0),0) | AN21: =SUM($AM$6:$AM21) | AO21: =IFERROR(INDEX($F$6:$F$565,MATCH(ROW()-5,$AN$6:$AN$565,0)),"") | AP21: =IF(AND($F21<>"",$I21<>""),IF($G21="وام و تسهیلات",1,0),0) | AQ21: =SUM($AP$6:$AP21) | AR21: =IFERROR(INDEX($F$6:$F$565,MATCH(ROW()-5,$AQ$6:$AQ$565,0)),"") | AS21: =IF(AND($F21<>"",$I21<>""),IF($G21="سرمایه و آورده صاحبان",1,0),0) | AT21: =SUM($AS$6:$AS21) | AU21: =IFERROR(INDEX($F$6:$F$565,MATCH(ROW()-5,$AT$6:$AT$565,0)),"") | AW21: =IF([3]Issues!$C$24="","",[3]Issues!$C$24) | AX21: =IF([4]Entry!$E$24="","",[4]Entry!$E$24) | AY21: =IF([4]Entry!$H$24="","",[4]Entry!$H$24) | AZ21: =IF([4]Entry!$I$24="","",[4]Entry!$I$24)
F22: =IF([1]Accounts!$D$23="","",[1]Accounts!$A$23) | G22: =IF([1]Accounts!$D$23="","",[1]Accounts!$B$23) | H22: =IF([1]Accounts!$D$23="","",[1]Accounts!$C$23) | I22: =IF([1]Accounts!$D$23="","",[1]Accounts!$D$23) | K22: =IF([1]SubGroups!$C$23="","",[1]SubGroups!$A$23) | L22: =IF([1]SubGroups!$C$23="","",[1]SubGroups!$B$23) | M22: =IF([1]SubGroups!$C$23="","",[1]SubGroups!$C$23) | N22: =IF([1]SubGroups!$C$23="","",[1]SubGroups!$D$23) | R22: =IF(AND($F22<>"",$I22<>""),IF(OR($G22="دارایی ثابت",$G22="وام و تسهیلات",$G22="سرمایه و آورده صاحبان"),0,1),0) | S22: =SUM($R$6:$R22) | T22: =IFERROR(INDEX($F$6:$F$565,MATCH(ROW()-5,$S$6:$S$565,0)),"") | V22: =IF(AND($K22<>"",$M22<>""),$L22="هزینه",0)*1 | W22: =SUM($V$6:$V22) | X22: =IFERROR(INDEX($M$6:$M$105,MATCH(ROW()-5,$W$6:$W$105,0)),"") | Z22: =IF([2]Entry!$E$25="","",[2]Entry!$E$25) | AA22: =IF([2]Entry!$G$25="","",[2]Entry!$G$25) | AB22: =IF([2]Entry!$J$25="","",[2]Entry!$J$25) | AC22: =IF([2]Entry!$K$25="","",[2]Entry!$K$25) | AD22: =IF([2]Entry!$L$25="","",[2]Entry!$L$25) | AE22: =IF([2]Entry!$M$25="","",[2]Entry!$M$25) | AF22: =IF([2]Entry!$N$25="","",[2]Entry!$N$25) | AG22: =IF([3]Issues!$B$25="","",[3]Issues!$B$25) | AH22: =IF([3]Issues!$D$25="","",[3]Issues!$D$25) | AI22: =IF([3]Issues!$E$25="","",[3]Issues!$E$25) | AJ22: =IF([2]Entry!$S$25="","",[2]Entry!$S$25) | AK22: =IF([2]Entry!$C$25="","",[2]Entry!$C$25) | AL22: =IF([2]Entry!$D$25="","",[2]Entry!$D$25) | AM22: =IF(AND($F22<>"",$I22<>""),IF($G22="دارایی ثابت",1,0),0) | AN22: =SUM($AM$6:$AM22) | AO22: =IFERROR(INDEX($F$6:$F$565,MATCH(ROW()-5,$AN$6:$AN$565,0)),"") | AP22: =IF(AND($F22<>"",$I22<>""),IF($G22="وام و تسهیلات",1,0),0) | AQ22: =SUM($AP$6:$AP22) | AR22: =IFERROR(INDEX($F$6:$F$565,MATCH(ROW()-5,$AQ$6:$AQ$565,0)),"") | AS22: =IF(AND($F22<>"",$I22<>""),IF($G22="سرمایه و آورده صاحبان",1,0),0) | AT22: =SUM($AS$6:$AS22) | AU22: =IFERROR(INDEX($F$6:$F$565,MATCH(ROW()-5,$AT$6:$AT$565,0)),"") | AW22: =IF([3]Issues!$C$25="","",[3]Issues!$C$25) | AX22: =IF([4]Entry!$E$25="","",[4]Entry!$E$25) | AY22: =IF([4]Entry!$H$25="","",[4]Entry!$H$25) | AZ22: =IF([4]Entry!$I$25="","",[4]Entry!$I$25)
F23: =IF([1]Accounts!$D$24="","",[1]Accounts!$A$24) | G23: =IF([1]Accounts!$D$24="","",[1]Accounts!$B$24) | H23: =IF([1]Accounts!$D$24="","",[1]Accounts!$C$24) | I23: =IF([1]Accounts!$D$24="","",[1]Accounts!$D$24) | K23: =IF([1]SubGroups!$C$24="","",[1]SubGroups!$A$24) | L23: =IF([1]SubGroups!$C$24="","",[1]SubGroups!$B$24) | M23: =IF([1]SubGroups!$C$24="","",[1]SubGroups!$C$24) | N23: =IF([1]SubGroups!$C$24="","",[1]SubGroups!$D$24) | R23: =IF(AND($F23<>"",$I23<>""),IF(OR($G23="دارایی ثابت",$G23="وام و تسهیلات",$G23="سرمایه و آورده صاحبان"),0,1),0) | S23: =SUM($R$6:$R23) | T23: =IFERROR(INDEX($F$6:$F$565,MATCH(ROW()-5,$S$6:$S$565,0)),"") | V23: =IF(AND($K23<>"",$M23<>""),$L23="هزینه",0)*1 | W23: =SUM($V$6:$V23) | X23: =IFERROR(INDEX($M$6:$M$105,MATCH(ROW()-5,$W$6:$W$105,0)),"") | Z23: =IF([2]Entry!$E$26="","",[2]Entry!$E$26) | AA23: =IF([2]Entry!$G$26="","",[2]Entry!$G$26) | AB23: =IF([2]Entry!$J$26="","",[2]Entry!$J$26) | AC23: =IF([2]Entry!$K$26="","",[2]Entry!$K$26) | AD23: =IF([2]Entry!$L$26="","",[2]Entry!$L$26) | AE23: =IF([2]Entry!$M$26="","",[2]Entry!$M$26) | AF23: =IF([2]Entry!$N$26="","",[2]Entry!$N$26) | AG23: =IF([3]Issues!$B$26="","",[3]Issues!$B$26) | AH23: =IF([3]Issues!$D$26="","",[3]Issues!$D$26) | AI23: =IF([3]Issues!$E$26="","",[3]Issues!$E$26) | AJ23: =IF([2]Entry!$S$26="","",[2]Entry!$S$26) | AK23: =IF([2]Entry!$C$26="","",[2]Entry!$C$26) | AL23: =IF([2]Entry!$D$26="","",[2]Entry!$D$26) | AM23: =IF(AND($F23<>"",$I23<>""),IF($G23="دارایی ثابت",1,0),0) | AN23: =SUM($AM$6:$AM23) | AO23: =IFERROR(INDEX($F$6:$F$565,MATCH(ROW()-5,$AN$6:$AN$565,0)),"") | AP23: =IF(AND($F23<>"",$I23<>""),IF($G23="وام و تسهیلات",1,0),0) | AQ23: =SUM($AP$6:$AP23) | AR23: =IFERROR(INDEX($F$6:$F$565,MATCH(ROW()-5,$AQ$6:$AQ$565,0)),"") | AS23: =IF(AND($F23<>"",$I23<>""),IF($G23="سرمایه و آورده صاحبان",1,0),0) | AT23: =SUM($AS$6:$AS23) | AU23: =IFERROR(INDEX($F$6:$F$565,MATCH(ROW()-5,$AT$6:$AT$565,0)),"") | AW23: =IF([3]Issues!$C$26="","",[3]Issues!$C$26) | AX23: =IF([4]Entry!$E$26="","",[4]Entry!$E$26) | AY23: =IF([4]Entry!$H$26="","",[4]Entry!$H$26) | AZ23: =IF([4]Entry!$I$26="","",[4]Entry!$I$26)
F24: =IF([1]Accounts!$D$25="","",[1]Accounts!$A$25) | G24: =IF([1]Accounts!$D$25="","",[1]Accounts!$B$25) | H24: =IF([1]Accounts!$D$25="","",[1]Accounts!$C$25) | I24: =IF([1]Accounts!$D$25="","",[1]Accounts!$D$25) | K24: =IF([1]SubGroups!$C$25="","",[1]SubGroups!$A$25) | L24: =IF([1]SubGroups!$C$25="","",[1]SubGroups!$B$25) | M24: =IF([1]SubGroups!$C$25="","",[1]SubGroups!$C$25) | N24: =IF([1]SubGroups!$C$25="","",[1]SubGroups!$D$25) | R24: =IF(AND($F24<>"",$I24<>""),IF(OR($G24="دارایی ثابت",$G24="وام و تسهیلات",$G24="سرمایه و آورده صاحبان"),0,1),0) | S24: =SUM($R$6:$R24) | T24: =IFERROR(INDEX($F$6:$F$565,MATCH(ROW()-5,$S$6:$S$565,0)),"") | V24: =IF(AND($K24<>"",$M24<>""),$L24="هزینه",0)*1 | W24: =SUM($V$6:$V24) | X24: =IFERROR(INDEX($M$6:$M$105,MATCH(ROW()-5,$W$6:$W$105,0)),"") | Z24: =IF([2]Entry!$E$27="","",[2]Entry!$E$27) | AA24: =IF([2]Entry!$G$27="","",[2]Entry!$G$27) | AB24: =IF([2]Entry!$J$27="","",[2]Entry!$J$27) | AC24: =IF([2]Entry!$K$27="","",[2]Entry!$K$27) | AD24: =IF([2]Entry!$L$27="","",[2]Entry!$L$27) | AE24: =IF([2]Entry!$M$27="","",[2]Entry!$M$27) | AF24: =IF([2]Entry!$N$27="","",[2]Entry!$N$27) | AG24: =IF([3]Issues!$B$27="","",[3]Issues!$B$27) | AH24: =IF([3]Issues!$D$27="","",[3]Issues!$D$27) | AI24: =IF([3]Issues!$E$27="","",[3]Issues!$E$27) | AJ24: =IF([2]Entry!$S$27="","",[2]Entry!$S$27) | AK24: =IF([2]Entry!$C$27="","",[2]Entry!$C$27) | AL24: =IF([2]Entry!$D$27="","",[2]Entry!$D$27) | AM24: =IF(AND($F24<>"",$I24<>""),IF($G24="دارایی ثابت",1,0),0) | AN24: =SUM($AM$6:$AM24) | AO24: =IFERROR(INDEX($F$6:$F$565,MATCH(ROW()-5,$AN$6:$AN$565,0)),"") | AP24: =IF(AND($F24<>"",$I24<>""),IF($G24="وام و تسهیلات",1,0),0) | AQ24: =SUM($AP$6:$AP24) | AR24: =IFERROR(INDEX($F$6:$F$565,MATCH(ROW()-5,$AQ$6:$AQ$565,0)),"") | AS24: =IF(AND($F24<>"",$I24<>""),IF($G24="سرمایه و آورده صاحبان",1,0),0) | AT24: =SUM($AS$6:$AS24) | AU24: =IFERROR(INDEX($F$6:$F$565,MATCH(ROW()-5,$AT$6:$AT$565,0)),"") | AW24: =IF([3]Issues!$C$27="","",[3]Issues!$C$27) | AX24: =IF([4]Entry!$E$27="","",[4]Entry!$E$27) | AY24: =IF([4]Entry!$H$27="","",[4]Entry!$H$27) | AZ24: =IF([4]Entry!$I$27="","",[4]Entry!$I$27)
F25: =IF([1]Accounts!$D$26="","",[1]Accounts!$A$26) | G25: =IF([1]Accounts!$D$26="","",[1]Accounts!$B$26) | H25: =IF([1]Accounts!$D$26="","",[1]Accounts!$C$26) | I25: =IF([1]Accounts!$D$26="","",[1]Accounts!$D$26) | K25: =IF([1]SubGroups!$C$26="","",[1]SubGroups!$A$26) | L25: =IF([1]SubGroups!$C$26="","",[1]SubGroups!$B$26) | M25: =IF([1]SubGroups!$C$26="","",[1]SubGroups!$C$26) | N25: =IF([1]SubGroups!$C$26="","",[1]SubGroups!$D$26) | R25: =IF(AND($F25<>"",$I25<>""),IF(OR($G25="دارایی ثابت",$G25="وام و تسهیلات",$G25="سرمایه و آورده صاحبان"),0,1),0) | S25: =SUM($R$6:$R25) | T25: =IFERROR(INDEX($F$6:$F$565,MATCH(ROW()-5,$S$6:$S$565,0)),"") | V25: =IF(AND($K25<>"",$M25<>""),$L25="هزینه",0)*1 | W25: =SUM($V$6:$V25) | X25: =IFERROR(INDEX($M$6:$M$105,MATCH(ROW()-5,$W$6:$W$105,0)),"") | Z25: =IF([2]Entry!$E$28="","",[2]Entry!$E$28) | AA25: =IF([2]Entry!$G$28="","",[2]Entry!$G$28) | AB25: =IF([2]Entry!$J$28="","",[2]Entry!$J$28) | AC25: =IF([2]Entry!$K$28="","",[2]Entry!$K$28) | AD25: =IF([2]Entry!$L$28="","",[2]Entry!$L$28) | AE25: =IF([2]Entry!$M$28="","",[2]Entry!$M$28) | AF25: =IF([2]Entry!$N$28="","",[2]Entry!$N$28) | AG25: =IF([3]Issues!$B$28="","",[3]Issues!$B$28) | AH25: =IF([3]Issues!$D$28="","",[3]Issues!$D$28) | AI25: =IF([3]Issues!$E$28="","",[3]Issues!$E$28) | AJ25: =IF([2]Entry!$S$28="","",[2]Entry!$S$28) | AK25: =IF([2]Entry!$C$28="","",[2]Entry!$C$28) | AL25: =IF([2]Entry!$D$28="","",[2]Entry!$D$28) | AM25: =IF(AND($F25<>"",$I25<>""),IF($G25="دارایی ثابت",1,0),0) | AN25: =SUM($AM$6:$AM25) | AO25: =IFERROR(INDEX($F$6:$F$565,MATCH(ROW()-5,$AN$6:$AN$565,0)),"") | AP25: =IF(AND($F25<>"",$I25<>""),IF($G25="وام و تسهیلات",1,0),0) | AQ25: =SUM($AP$6:$AP25) | AR25: =IFERROR(INDEX($F$6:$F$565,MATCH(ROW()-5,$AQ$6:$AQ$565,0)),"") | AS25: =IF(AND($F25<>"",$I25<>""),IF($G25="سرمایه و آورده صاحبان",1,0),0) | AT25: =SUM($AS$6:$AS25) | AU25: =IFERROR(INDEX($F$6:$F$565,MATCH(ROW()-5,$AT$6:$AT$565,0)),"") | AW25: =IF([3]Issues!$C$28="","",[3]Issues!$C$28) | AX25: =IF([4]Entry!$E$28="","",[4]Entry!$E$28) | AY25: =IF([4]Entry!$H$28="","",[4]Entry!$H$28) | AZ25: =IF([4]Entry!$I$28="","",[4]Entry!$I$28)
F26: =IF([1]Accounts!$D$27="","",[1]Accounts!$A$27) | G26: =IF([1]Accounts!$D$27="","",[1]Accounts!$B$27) | H26: =IF([1]Accounts!$D$27="","",[1]Accounts!$C$27) | I26: =IF([1]Accounts!$D$27="","",[1]Accounts!$D$27) | K26: =IF([1]SubGroups!$C$27="","",[1]SubGroups!$A$27) | L26: =IF([1]SubGroups!$C$27="","",[1]SubGroups!$B$27) | M26: =IF([1]SubGroups!$C$27="","",[1]SubGroups!$C$27) | N26: =IF([1]SubGroups!$C$27="","",[1]SubGroups!$D$27) | R26: =IF(AND($F26<>"",$I26<>""),IF(OR($G26="دارایی ثابت",$G26="وام و تسهیلات",$G26="سرمایه و آورده صاحبان"),0,1),0) | S26: =SUM($R$6:$R26) | T26: =IFERROR(INDEX($F$6:$F$565,MATCH(ROW()-5,$S$6:$S$565,0)),"") | V26: =IF(AND($K26<>"",$M26<>""),$L26="هزینه",0)*1 | W26: =SUM($V$6:$V26) | X26: =IFERROR(INDEX($M$6:$M$105,MATCH(ROW()-5,$W$6:$W$105,0)),"") | Z26: =IF([2]Entry!$E$29="","",[2]Entry!$E$29) | AA26: =IF([2]Entry!$G$29="","",[2]Entry!$G$29) | AB26: =IF([2]Entry!$J$29="","",[2]Entry!$J$29) | AC26: =IF([2]Entry!$K$29="","",[2]Entry!$K$29) | AD26: =IF([2]Entry!$L$29="","",[2]Entry!$L$29) | AE26: =IF([2]Entry!$M$29="","",[2]Entry!$M$29) | AF26: =IF([2]Entry!$N$29="","",[2]Entry!$N$29) | AG26: =IF([3]Issues!$B$29="","",[3]Issues!$B$29) | AH26: =IF([3]Issues!$D$29="","",[3]Issues!$D$29) | AI26: =IF([3]Issues!$E$29="","",[3]Issues!$E$29) | AJ26: =IF([2]Entry!$S$29="","",[2]Entry!$S$29) | AK26: =IF([2]Entry!$C$29="","",[2]Entry!$C$29) | AL26: =IF([2]Entry!$D$29="","",[2]Entry!$D$29) | AM26: =IF(AND($F26<>"",$I26<>""),IF($G26="دارایی ثابت",1,0),0) | AN26: =SUM($AM$6:$AM26) | AO26: =IFERROR(INDEX($F$6:$F$565,MATCH(ROW()-5,$AN$6:$AN$565,0)),"") | AP26: =IF(AND($F26<>"",$I26<>""),IF($G26="وام و تسهیلات",1,0),0) | AQ26: =SUM($AP$6:$AP26) | AR26: =IFERROR(INDEX($F$6:$F$565,MATCH(ROW()-5,$AQ$6:$AQ$565,0)),"") | AS26: =IF(AND($F26<>"",$I26<>""),IF($G26="سرمایه و آورده صاحبان",1,0),0) | AT26: =SUM($AS$6:$AS26) | AU26: =IFERROR(INDEX($F$6:$F$565,MATCH(ROW()-5,$AT$6:$AT$565,0)),"") | AW26: =IF([3]Issues!$C$29="","",[3]Issues!$C$29) | AX26: =IF([4]Entry!$E$29="","",[4]Entry!$E$29) | AY26: =IF([4]Entry!$H$29="","",[4]Entry!$H$29) | AZ26: =IF([4]Entry!$I$29="","",[4]Entry!$I$29)
F27: =IF([1]Accounts!$D$28="","",[1]Accounts!$A$28) | G27: =IF([1]Accounts!$D$28="","",[1]Accounts!$B$28) | H27: =IF([1]Accounts!$D$28="","",[1]Accounts!$C$28) | I27: =IF([1]Accounts!$D$28="","",[1]Accounts!$D$28) | K27: =IF([1]SubGroups!$C$28="","",[1]SubGroups!$A$28) | L27: =IF([1]SubGroups!$C$28="","",[1]SubGroups!$B$28) | M27: =IF([1]SubGroups!$C$28="","",[1]SubGroups!$C$28) | N27: =IF([1]SubGroups!$C$28="","",[1]SubGroups!$D$28) | R27: =IF(AND($F27<>"",$I27<>""),IF(OR($G27="دارایی ثابت",$G27="وام و تسهیلات",$G27="سرمایه و آورده صاحبان"),0,1),0) | S27: =SUM($R$6:$R27) | T27: =IFERROR(INDEX($F$6:$F$565,MATCH(ROW()-5,$S$6:$S$565,0)),"") | V27: =IF(AND($K27<>"",$M27<>""),$L27="هزینه",0)*1 | W27: =SUM($V$6:$V27) | X27: =IFERROR(INDEX($M$6:$M$105,MATCH(ROW()-5,$W$6:$W$105,0)),"") | Z27: =IF([2]Entry!$E$30="","",[2]Entry!$E$30) | AA27: =IF([2]Entry!$G$30="","",[2]Entry!$G$30) | AB27: =IF([2]Entry!$J$30="","",[2]Entry!$J$30) | AC27: =IF([2]Entry!$K$30="","",[2]Entry!$K$30) | AD27: =IF([2]Entry!$L$30="","",[2]Entry!$L$30) | AE27: =IF([2]Entry!$M$30="","",[2]Entry!$M$30) | AF27: =IF([2]Entry!$N$30="","",[2]Entry!$N$30) | AG27: =IF([3]Issues!$B$30="","",[3]Issues!$B$30) | AH27: =IF([3]Issues!$D$30="","",[3]Issues!$D$30) | AI27: =IF([3]Issues!$E$30="","",[3]Issues!$E$30) | AJ27: =IF([2]Entry!$S$30="","",[2]Entry!$S$30) | AK27: =IF([2]Entry!$C$30="","",[2]Entry!$C$30) | AL27: =IF([2]Entry!$D$30="","",[2]Entry!$D$30) | AM27: =IF(AND($F27<>"",$I27<>""),IF($G27="دارایی ثابت",1,0),0) | AN27: =SUM($AM$6:$AM27) | AO27: =IFERROR(INDEX($F$6:$F$565,MATCH(ROW()-5,$AN$6:$AN$565,0)),"") | AP27: =IF(AND($F27<>"",$I27<>""),IF($G27="وام و تسهیلات",1,0),0) | AQ27: =SUM($AP$6:$AP27) | AR27: =IFERROR(INDEX($F$6:$F$565,MATCH(ROW()-5,$AQ$6:$AQ$565,0)),"") | AS27: =IF(AND($F27<>"",$I27<>""),IF($G27="سرمایه و آورده صاحبان",1,0),0) | AT27: =SUM($AS$6:$AS27) | AU27: =IFERROR(INDEX($F$6:$F$565,MATCH(ROW()-5,$AT$6:$AT$565,0)),"") | AW27: =IF([3]Issues!$C$30="","",[3]Issues!$C$30) | AX27: =IF([4]Entry!$E$30="","",[4]Entry!$E$30) | AY27: =IF([4]Entry!$H$30="","",[4]Entry!$H$30) | AZ27: =IF([4]Entry!$I$30="","",[4]Entry!$I$30)
F28: =IF([1]Accounts!$D$29="","",[1]Accounts!$A$29) | G28: =IF([1]Accounts!$D$29="","",[1]Accounts!$B$29) | H28: =IF([1]Accounts!$D$29="","",[1]Accounts!$C$29) | I28: =IF([1]Accounts!$D$29="","",[1]Accounts!$D$29) | K28: =IF([1]SubGroups!$C$29="","",[1]SubGroups!$A$29) | L28: =IF([1]SubGroups!$C$29="","",[1]SubGroups!$B$29) | M28: =IF([1]SubGroups!$C$29="","",[1]SubGroups!$C$29) | N28: =IF([1]SubGroups!$C$29="","",[1]SubGroups!$D$29) | R28: =IF(AND($F28<>"",$I28<>""),IF(OR($G28="دارایی ثابت",$G28="وام و تسهیلات",$G28="سرمایه و آورده صاحبان"),0,1),0) | S28: =SUM($R$6:$R28) | T28: =IFERROR(INDEX($F$6:$F$565,MATCH(ROW()-5,$S$6:$S$565,0)),"") | V28: =IF(AND($K28<>"",$M28<>""),$L28="هزینه",0)*1 | W28: =SUM($V$6:$V28) | X28: =IFERROR(INDEX($M$6:$M$105,MATCH(ROW()-5,$W$6:$W$105,0)),"") | Z28: =IF([2]Entry!$E$31="","",[2]Entry!$E$31) | AA28: =IF([2]Entry!$G$31="","",[2]Entry!$G$31) | AB28: =IF([2]Entry!$J$31="","",[2]Entry!$J$31) | AC28: =IF([2]Entry!$K$31="","",[2]Entry!$K$31) | AD28: =IF([2]Entry!$L$31="","",[2]Entry!$L$31) | AE28: =IF([2]Entry!$M$31="","",[2]Entry!$M$31) | AF28: =IF([2]Entry!$N$31="","",[2]Entry!$N$31) | AG28: =IF([3]Issues!$B$31="","",[3]Issues!$B$31) | AH28: =IF([3]Issues!$D$31="","",[3]Issues!$D$31) | AI28: =IF([3]Issues!$E$31="","",[3]Issues!$E$31) | AJ28: =IF([2]Entry!$S$31="","",[2]Entry!$S$31) | AK28: =IF([2]Entry!$C$31="","",[2]Entry!$C$31) | AL28: =IF([2]Entry!$D$31="","",[2]Entry!$D$31) | AM28: =IF(AND($F28<>"",$I28<>""),IF($G28="دارایی ثابت",1,0),0) | AN28: =SUM($AM$6:$AM28) | AO28: =IFERROR(INDEX($F$6:$F$565,MATCH(ROW()-5,$AN$6:$AN$565,0)),"") | AP28: =IF(AND($F28<>"",$I28<>""),IF($G28="وام و تسهیلات",1,0),0) | AQ28: =SUM($AP$6:$AP28) | AR28: =IFERROR(INDEX($F$6:$F$565,MATCH(ROW()-5,$AQ$6:$AQ$565,0)),"") | AS28: =IF(AND($F28<>"",$I28<>""),IF($G28="سرمایه و آورده صاحبان",1,0),0) | AT28: =SUM($AS$6:$AS28) | AU28: =IFERROR(INDEX($F$6:$F$565,MATCH(ROW()-5,$AT$6:$AT$565,0)),"") | AW28: =IF([3]Issues!$C$31="","",[3]Issues!$C$31) | AX28: =IF([4]Entry!$E$31="","",[4]Entry!$E$31) | AY28: =IF([4]Entry!$H$31="","",[4]Entry!$H$31) | AZ28: =IF([4]Entry!$I$31="","",[4]Entry!$I$31)
F29: =IF([1]Accounts!$D$30="","",[1]Accounts!$A$30) | G29: =IF([1]Accounts!$D$30="","",[1]Accounts!$B$30) | H29: =IF([1]Accounts!$D$30="","",[1]Accounts!$C$30) | I29: =IF([1]Accounts!$D$30="","",[1]Accounts!$D$30) | K29: =IF([1]SubGroups!$C$30="","",[1]SubGroups!$A$30) | L29: =IF([1]SubGroups!$C$30="","",[1]SubGroups!$B$30) | M29: =IF([1]SubGroups!$C$30="","",[1]SubGroups!$C$30) | N29: =IF([1]SubGroups!$C$30="","",[1]SubGroups!$D$30) | R29: =IF(AND($F29<>"",$I29<>""),IF(OR($G29="دارایی ثابت",$G29="وام و تسهیلات",$G29="سرمایه و آورده صاحبان"),0,1),0) | S29: =SUM($R$6:$R29) | T29: =IFERROR(INDEX($F$6:$F$565,MATCH(ROW()-5,$S$6:$S$565,0)),"") | V29: =IF(AND($K29<>"",$M29<>""),$L29="هزینه",0)*1 | W29: =SUM($V$6:$V29) | X29: =IFERROR(INDEX($M$6:$M$105,MATCH(ROW()-5,$W$6:$W$105,0)),"") | Z29: =IF([2]Entry!$E$32="","",[2]Entry!$E$32) | AA29: =IF([2]Entry!$G$32="","",[2]Entry!$G$32) | AB29: =IF([2]Entry!$J$32="","",[2]Entry!$J$32) | AC29: =IF([2]Entry!$K$32="","",[2]Entry!$K$32) | AD29: =IF([2]Entry!$L$32="","",[2]Entry!$L$32) | AE29: =IF([2]Entry!$M$32="","",[2]Entry!$M$32) | AF29: =IF([2]Entry!$N$32="","",[2]Entry!$N$32) | AG29: =IF([3]Issues!$B$32="","",[3]Issues!$B$32) | AH29: =IF([3]Issues!$D$32="","",[3]Issues!$D$32) | AI29: =IF([3]Issues!$E$32="","",[3]Issues!$E$32) | AJ29: =IF([2]Entry!$S$32="","",[2]Entry!$S$32) | AK29: =IF([2]Entry!$C$32="","",[2]Entry!$C$32) | AL29: =IF([2]Entry!$D$32="","",[2]Entry!$D$32) | AM29: =IF(AND($F29<>"",$I29<>""),IF($G29="دارایی ثابت",1,0),0) | AN29: =SUM($AM$6:$AM29) | AO29: =IFERROR(INDEX($F$6:$F$565,MATCH(ROW()-5,$AN$6:$AN$565,0)),"") | AP29: =IF(AND($F29<>"",$I29<>""),IF($G29="وام و تسهیلات",1,0),0) | AQ29: =SUM($AP$6:$AP29) | AR29: =IFERROR(INDEX($F$6:$F$565,MATCH(ROW()-5,$AQ$6:$AQ$565,0)),"") | AS29: =IF(AND($F29<>"",$I29<>""),IF($G29="سرمایه و آورده صاحبان",1,0),0) | AT29: =SUM($AS$6:$AS29) | AU29: =IFERROR(INDEX($F$6:$F$565,MATCH(ROW()-5,$AT$6:$AT$565,0)),"") | AW29: =IF([3]Issues!$C$32="","",[3]Issues!$C$32) | AX29: =IF([4]Entry!$E$32="","",[4]Entry!$E$32) | AY29: =IF([4]Entry!$H$32="","",[4]Entry!$H$32) | AZ29: =IF([4]Entry!$I$32="","",[4]Entry!$I$32)
F30: =IF([1]Accounts!$D$31="","",[1]Accounts!$A$31) | G30: =IF([1]Accounts!$D$31="","",[1]Accounts!$B$31) | H30: =IF([1]Accounts!$D$31="","",[1]Accounts!$C$31) | I30: =IF([1]Accounts!$D$31="","",[1]Accounts!$D$31) | K30: =IF([1]SubGroups!$C$31="","",[1]SubGroups!$A$31) | L30: =IF([1]SubGroups!$C$31="","",[1]SubGroups!$B$31) | M30: =IF([1]SubGroups!$C$31="","",[1]SubGroups!$C$31) | N30: =IF([1]SubGroups!$C$31="","",[1]SubGroups!$D$31) | R30: =IF(AND($F30<>"",$I30<>""),IF(OR($G30="دارایی ثابت",$G30="وام و تسهیلات",$G30="سرمایه و آورده صاحبان"),0,1),0) | S30: =SUM($R$6:$R30) | T30: =IFERROR(INDEX($F$6:$F$565,MATCH(ROW()-5,$S$6:$S$565,0)),"") | V30: =IF(AND($K30<>"",$M30<>""),$L30="هزینه",0)*1 | W30: =SUM($V$6:$V30) | X30: =IFERROR(INDEX($M$6:$M$105,MATCH(ROW()-5,$W$6:$W$105,0)),"") | Z30: =IF([2]Entry!$E$33="","",[2]Entry!$E$33) | AA30: =IF([2]Entry!$G$33="","",[2]Entry!$G$33) | AB30: =IF([2]Entry!$J$33="","",[2]Entry!$J$33) | AC30: =IF([2]Entry!$K$33="","",[2]Entry!$K$33) | AD30: =IF([2]Entry!$L$33="","",[2]Entry!$L$33) | AE30: =IF([2]Entry!$M$33="","",[2]Entry!$M$33) | AF30: =IF([2]Entry!$N$33="","",[2]Entry!$N$33) | AG30: =IF([3]Issues!$B$33="","",[3]Issues!$B$33) | AH30: =IF([3]Issues!$D$33="","",[3]Issues!$D$33) | AI30: =IF([3]Issues!$E$33="","",[3]Issues!$E$33) | AJ30: =IF([2]Entry!$S$33="","",[2]Entry!$S$33) | AK30: =IF([2]Entry!$C$33="","",[2]Entry!$C$33) | AL30: =IF([2]Entry!$D$33="","",[2]Entry!$D$33) | AM30: =IF(AND($F30<>"",$I30<>""),IF($G30="دارایی ثابت",1,0),0) | AN30: =SUM($AM$6:$AM30) | AO30: =IFERROR(INDEX($F$6:$F$565,MATCH(ROW()-5,$AN$6:$AN$565,0)),"") | AP30: =IF(AND($F30<>"",$I30<>""),IF($G30="وام و تسهیلات",1,0),0) | AQ30: =SUM($AP$6:$AP30) | AR30: =IFERROR(INDEX($F$6:$F$565,MATCH(ROW()-5,$AQ$6:$AQ$565,0)),"") | AS30: =IF(AND($F30<>"",$I30<>""),IF($G30="سرمایه و آورده صاحبان",1,0),0) | AT30: =SUM($AS$6:$AS30) | AU30: =IFERROR(INDEX($F$6:$F$565,MATCH(ROW()-5,$AT$6:$AT$565,0)),"") | AW30: =IF([3]Issues!$C$33="","",[3]Issues!$C$33) | AX30: =IF([4]Entry!$E$33="","",[4]Entry!$E$33) | AY30: =IF([4]Entry!$H$33="","",[4]Entry!$H$33) | AZ30: =IF([4]Entry!$I$33="","",[4]Entry!$I$33)
F31: =IF([1]Accounts!$D$32="","",[1]Accounts!$A$32) | G31: =IF([1]Accounts!$D$32="","",[1]Accounts!$B$32) | H31: =IF([1]Accounts!$D$32="","",[1]Accounts!$C$32) | I31: =IF([1]Accounts!$D$32="","",[1]Accounts!$D$32) | K31: =IF([1]SubGroups!$C$32="","",[1]SubGroups!$A$32) | L31: =IF([1]SubGroups!$C$32="","",[1]SubGroups!$B$32) | M31: =IF([1]SubGroups!$C$32="","",[1]SubGroups!$C$32) | N31: =IF([1]SubGroups!$C$32="","",[1]SubGroups!$D$32) | R31: =IF(AND($F31<>"",$I31<>""),IF(OR($G31="دارایی ثابت",$G31="وام و تسهیلات",$G31="سرمایه و آورده صاحبان"),0,1),0) | S31: =SUM($R$6:$R31) | T31: =IFERROR(INDEX($F$6:$F$565,MATCH(ROW()-5,$S$6:$S$565,0)),"") | V31: =IF(AND($K31<>"",$M31<>""),$L31="هزینه",0)*1 | W31: =SUM($V$6:$V31) | X31: =IFERROR(INDEX($M$6:$M$105,MATCH(ROW()-5,$W$6:$W$105,0)),"") | Z31: =IF([2]Entry!$E$34="","",[2]Entry!$E$34) | AA31: =IF([2]Entry!$G$34="","",[2]Entry!$G$34) | AB31: =IF([2]Entry!$J$34="","",[2]Entry!$J$34) | AC31: =IF([2]Entry!$K$34="","",[2]Entry!$K$34) | AD31: =IF([2]Entry!$L$34="","",[2]Entry!$L$34) | AE31: =IF([2]Entry!$M$34="","",[2]Entry!$M$34) | AF31: =IF([2]Entry!$N$34="","",[2]Entry!$N$34) | AG31: =IF([3]Issues!$B$34="","",[3]Issues!$B$34) | AH31: =IF([3]Issues!$D$34="","",[3]Issues!$D$34) | AI31: =IF([3]Issues!$E$34="","",[3]Issues!$E$34) | AJ31: =IF([2]Entry!$S$34="","",[2]Entry!$S$34) | AK31: =IF([2]Entry!$C$34="","",[2]Entry!$C$34) | AL31: =IF([2]Entry!$D$34="","",[2]Entry!$D$34) | AM31: =IF(AND($F31<>"",$I31<>""),IF($G31="دارایی ثابت",1,0),0) | AN31: =SUM($AM$6:$AM31) | AO31: =IFERROR(INDEX($F$6:$F$565,MATCH(ROW()-5,$AN$6:$AN$565,0)),"") | AP31: =IF(AND($F31<>"",$I31<>""),IF($G31="وام و تسهیلات",1,0),0) | AQ31: =SUM($AP$6:$AP31) | AR31: =IFERROR(INDEX($F$6:$F$565,MATCH(ROW()-5,$AQ$6:$AQ$565,0)),"") | AS31: =IF(AND($F31<>"",$I31<>""),IF($G31="سرمایه و آورده صاحبان",1,0),0) | AT31: =SUM($AS$6:$AS31) | AU31: =IFERROR(INDEX($F$6:$F$565,MATCH(ROW()-5,$AT$6:$AT$565,0)),"") | AW31: =IF([3]Issues!$C$34="","",[3]Issues!$C$34) | AX31: =IF([4]Entry!$E$34="","",[4]Entry!$E$34) | AY31: =IF([4]Entry!$H$34="","",[4]Entry!$H$34) | AZ31: =IF([4]Entry!$I$34="","",[4]Entry!$I$34)
F32: =IF([1]Accounts!$D$33="","",[1]Accounts!$A$33) | G32: =IF([1]Accounts!$D$33="","",[1]Accounts!$B$33) | H32: =IF([1]Accounts!$D$33="","",[1]Accounts!$C$33) | I32: =IF([1]Accounts!$D$33="","",[1]Accounts!$D$33) | K32: =IF([1]SubGroups!$C$33="","",[1]SubGroups!$A$33) | L32: =IF([1]SubGroups!$C$33="","",[1]SubGroups!$B$33) | M32: =IF([1]SubGroups!$C$33="","",[1]SubGroups!$C$33) | N32: =IF([1]SubGroups!$C$33="","",[1]SubGroups!$D$33) | R32: =IF(AND($F32<>"",$I32<>""),IF(OR($G32="دارایی ثابت",$G32="وام و تسهیلات",$G32="سرمایه و آورده صاحبان"),0,1),0) | S32: =SUM($R$6:$R32) | T32: =IFERROR(INDEX($F$6:$F$565,MATCH(ROW()-5,$S$6:$S$565,0)),"") | V32: =IF(AND($K32<>"",$M32<>""),$L32="هزینه",0)*1 | W32: =SUM($V$6:$V32) | X32: =IFERROR(INDEX($M$6:$M$105,MATCH(ROW()-5,$W$6:$W$105,0)),"") | Z32: =IF([2]Entry!$E$35="","",[2]Entry!$E$35) | AA32: =IF([2]Entry!$G$35="","",[2]Entry!$G$35) | AB32: =IF([2]Entry!$J$35="","",[2]Entry!$J$35) | AC32: =IF([2]Entry!$K$35="","",[2]Entry!$K$35) | AD32: =IF([2]Entry!$L$35="","",[2]Entry!$L$35) | AE32: =IF([2]Entry!$M$35="","",[2]Entry!$M$35) | AF32: =IF([2]Entry!$N$35="","",[2]Entry!$N$35) | AG32: =IF([3]Issues!$B$35="","",[3]Issues!$B$35) | AH32: =IF([3]Issues!$D$35="","",[3]Issues!$D$35) | AI32: =IF([3]Issues!$E$35="","",[3]Issues!$E$35) | AJ32: =IF([2]Entry!$S$35="","",[2]Entry!$S$35) | AK32: =IF([2]Entry!$C$35="","",[2]Entry!$C$35) | AL32: =IF([2]Entry!$D$35="","",[2]Entry!$D$35) | AM32: =IF(AND($F32<>"",$I32<>""),IF($G32="دارایی ثابت",1,0),0) | AN32: =SUM($AM$6:$AM32) | AO32: =IFERROR(INDEX($F$6:$F$565,MATCH(ROW()-5,$AN$6:$AN$565,0)),"") | AP32: =IF(AND($F32<>"",$I32<>""),IF($G32="وام و تسهیلات",1,0),0) | AQ32: =SUM($AP$6:$AP32) | AR32: =IFERROR(INDEX($F$6:$F$565,MATCH(ROW()-5,$AQ$6:$AQ$565,0)),"") | AS32: =IF(AND($F32<>"",$I32<>""),IF($G32="سرمایه و آورده صاحبان",1,0),0) | AT32: =SUM($AS$6:$AS32) | AU32: =IFERROR(INDEX($F$6:$F$565,MATCH(ROW()-5,$AT$6:$AT$565,0)),"") | AW32: =IF([3]Issues!$C$35="","",[3]Issues!$C$35) | AX32: =IF([4]Entry!$E$35="","",[4]Entry!$E$35) | AY32: =IF([4]Entry!$H$35="","",[4]Entry!$H$35) | AZ32: =IF([4]Entry!$I$35="","",[4]Entry!$I$35)
F33: =IF([1]Accounts!$D$34="","",[1]Accounts!$A$34) | G33: =IF([1]Accounts!$D$34="","",[1]Accounts!$B$34) | H33: =IF([1]Accounts!$D$34="","",[1]Accounts!$C$34) | I33: =IF([1]Accounts!$D$34="","",[1]Accounts!$D$34) | K33: =IF([1]SubGroups!$C$34="","",[1]SubGroups!$A$34) | L33: =IF([1]SubGroups!$C$34="","",[1]SubGroups!$B$34) | M33: =IF([1]SubGroups!$C$34="","",[1]SubGroups!$C$34) | N33: =IF([1]SubGroups!$C$34="","",[1]SubGroups!$D$34) | R33: =IF(AND($F33<>"",$I33<>""),IF(OR($G33="دارایی ثابت",$G33="وام و تسهیلات",$G33="سرمایه و آورده صاحبان"),0,1),0) | S33: =SUM($R$6:$R33) | T33: =IFERROR(INDEX($F$6:$F$565,MATCH(ROW()-5,$S$6:$S$565,0)),"") | V33: =IF(AND($K33<>"",$M33<>""),$L33="هزینه",0)*1 | W33: =SUM($V$6:$V33) | X33: =IFERROR(INDEX($M$6:$M$105,MATCH(ROW()-5,$W$6:$W$105,0)),"") | Z33: =IF([2]Entry!$E$36="","",[2]Entry!$E$36) | AA33: =IF([2]Entry!$G$36="","",[2]Entry!$G$36) | AB33: =IF([2]Entry!$J$36="","",[2]Entry!$J$36) | AC33: =IF([2]Entry!$K$36="","",[2]Entry!$K$36) | AD33: =IF([2]Entry!$L$36="","",[2]Entry!$L$36) | AE33: =IF([2]Entry!$M$36="","",[2]Entry!$M$36) | AF33: =IF([2]Entry!$N$36="","",[2]Entry!$N$36) | AG33: =IF([3]Issues!$B$36="","",[3]Issues!$B$36) | AH33: =IF([3]Issues!$D$36="","",[3]Issues!$D$36) | AI33: =IF([3]Issues!$E$36="","",[3]Issues!$E$36) | AJ33: =IF([2]Entry!$S$36="","",[2]Entry!$S$36) | AK33: =IF([2]Entry!$C$36="","",[2]Entry!$C$36) | AL33: =IF([2]Entry!$D$36="","",[2]Entry!$D$36) | AM33: =IF(AND($F33<>"",$I33<>""),IF($G33="دارایی ثابت",1,0),0) | AN33: =SUM($AM$6:$AM33) | AO33: =IFERROR(INDEX($F$6:$F$565,MATCH(ROW()-5,$AN$6:$AN$565,0)),"") | AP33: =IF(AND($F33<>"",$I33<>""),IF($G33="وام و تسهیلات",1,0),0) | AQ33: =SUM($AP$6:$AP33) | AR33: =IFERROR(INDEX($F$6:$F$565,MATCH(ROW()-5,$AQ$6:$AQ$565,0)),"") | AS33: =IF(AND($F33<>"",$I33<>""),IF($G33="سرمایه و آورده صاحبان",1,0),0) | AT33: =SUM($AS$6:$AS33) | AU33: =IFERROR(INDEX($F$6:$F$565,MATCH(ROW()-5,$AT$6:$AT$565,0)),"") | AW33: =IF([3]Issues!$C$36="","",[3]Issues!$C$36) | AX33: =IF([4]Entry!$E$36="","",[4]Entry!$E$36) | AY33: =IF([4]Entry!$H$36="","",[4]Entry!$H$36) | AZ33: =IF([4]Entry!$I$36="","",[4]Entry!$I$36)
F34: =IF([1]Accounts!$D$35="","",[1]Accounts!$A$35) | G34: =IF([1]Accounts!$D$35="","",[1]Accounts!$B$35) | H34: =IF([1]Accounts!$D$35="","",[1]Accounts!$C$35) | I34: =IF([1]Accounts!$D$35="","",[1]Accounts!$D$35) | K34: =IF([1]SubGroups!$C$35="","",[1]SubGroups!$A$35) | L34: =IF([1]SubGroups!$C$35="","",[1]SubGroups!$B$35) | M34: =IF([1]SubGroups!$C$35="","",[1]SubGroups!$C$35) | N34: =IF([1]SubGroups!$C$35="","",[1]SubGroups!$D$35) | R34: =IF(AND($F34<>"",$I34<>""),IF(OR($G34="دارایی ثابت",$G34="وام و تسهیلات",$G34="سرمایه و آورده صاحبان"),0,1),0) | S34: =SUM($R$6:$R34) | T34: =IFERROR(INDEX($F$6:$F$565,MATCH(ROW()-5,$S$6:$S$565,0)),"") | V34: =IF(AND($K34<>"",$M34<>""),$L34="هزینه",0)*1 | W34: =SUM($V$6:$V34) | X34: =IFERROR(INDEX($M$6:$M$105,MATCH(ROW()-5,$W$6:$W$105,0)),"") | Z34: =IF([2]Entry!$E$37="","",[2]Entry!$E$37) | AA34: =IF([2]Entry!$G$37="","",[2]Entry!$G$37) | AB34: =IF([2]Entry!$J$37="","",[2]Entry!$J$37) | AC34: =IF([2]Entry!$K$37="","",[2]Entry!$K$37) | AD34: =IF([2]Entry!$L$37="","",[2]Entry!$L$37) | AE34: =IF([2]Entry!$M$37="","",[2]Entry!$M$37) | AF34: =IF([2]Entry!$N$37="","",[2]Entry!$N$37) | AG34: =IF([3]Issues!$B$37="","",[3]Issues!$B$37) | AH34: =IF([3]Issues!$D$37="","",[3]Issues!$D$37) | AI34: =IF([3]Issues!$E$37="","",[3]Issues!$E$37) | AJ34: =IF([2]Entry!$S$37="","",[2]Entry!$S$37) | AK34: =IF([2]Entry!$C$37="","",[2]Entry!$C$37) | AL34: =IF([2]Entry!$D$37="","",[2]Entry!$D$37) | AM34: =IF(AND($F34<>"",$I34<>""),IF($G34="دارایی ثابت",1,0),0) | AN34: =SUM($AM$6:$AM34) | AO34: =IFERROR(INDEX($F$6:$F$565,MATCH(ROW()-5,$AN$6:$AN$565,0)),"") | AP34: =IF(AND($F34<>"",$I34<>""),IF($G34="وام و تسهیلات",1,0),0) | AQ34: =SUM($AP$6:$AP34) | AR34: =IFERROR(INDEX($F$6:$F$565,MATCH(ROW()-5,$AQ$6:$AQ$565,0)),"") | AS34: =IF(AND($F34<>"",$I34<>""),IF($G34="سرمایه و آورده صاحبان",1,0),0) | AT34: =SUM($AS$6:$AS34) | AU34: =IFERROR(INDEX($F$6:$F$565,MATCH(ROW()-5,$AT$6:$AT$565,0)),"") | AW34: =IF([3]Issues!$C$37="","",[3]Issues!$C$37) | AX34: =IF([4]Entry!$E$37="","",[4]Entry!$E$37) | AY34: =IF([4]Entry!$H$37="","",[4]Entry!$H$37) | AZ34: =IF([4]Entry!$I$37="","",[4]Entry!$I$37)
F35: =IF([1]Accounts!$D$36="","",[1]Accounts!$A$36) | G35: =IF([1]Accounts!$D$36="","",[1]Accounts!$B$36) | H35: =IF([1]Accounts!$D$36="","",[1]Accounts!$C$36) | I35: =IF([1]Accounts!$D$36="","",[1]Accounts!$D$36) | K35: =IF([1]SubGroups!$C$36="","",[1]SubGroups!$A$36) | L35: =IF([1]SubGroups!$C$36="","",[1]SubGroups!$B$36) | M35: =IF([1]SubGroups!$C$36="","",[1]SubGroups!$C$36) | N35: =IF([1]SubGroups!$C$36="","",[1]SubGroups!$D$36) | R35: =IF(AND($F35<>"",$I35<>""),IF(OR($G35="دارایی ثابت",$G35="وام و تسهیلات",$G35="سرمایه و آورده صاحبان"),0,1),0) | S35: =SUM($R$6:$R35) | T35: =IFERROR(INDEX($F$6:$F$565,MATCH(ROW()-5,$S$6:$S$565,0)),"") | V35: =IF(AND($K35<>"",$M35<>""),$L35="هزینه",0)*1 | W35: =SUM($V$6:$V35) | X35: =IFERROR(INDEX($M$6:$M$105,MATCH(ROW()-5,$W$6:$W$105,0)),"") | Z35: =IF([2]Entry!$E$38="","",[2]Entry!$E$38) | AA35: =IF([2]Entry!$G$38="","",[2]Entry!$G$38) | AB35: =IF([2]Entry!$J$38="","",[2]Entry!$J$38) | AC35: =IF([2]Entry!$K$38="","",[2]Entry!$K$38) | AD35: =IF([2]Entry!$L$38="","",[2]Entry!$L$38) | AE35: =IF([2]Entry!$M$38="","",[2]Entry!$M$38) | AF35: =IF([2]Entry!$N$38="","",[2]Entry!$N$38) | AG35: =IF([3]Issues!$B$38="","",[3]Issues!$B$38) | AH35: =IF([3]Issues!$D$38="","",[3]Issues!$D$38) | AI35: =IF([3]Issues!$E$38="","",[3]Issues!$E$38) | AJ35: =IF([2]Entry!$S$38="","",[2]Entry!$S$38) | AK35: =IF([2]Entry!$C$38="","",[2]Entry!$C$38) | AL35: =IF([2]Entry!$D$38="","",[2]Entry!$D$38) | AM35: =IF(AND($F35<>"",$I35<>""),IF($G35="دارایی ثابت",1,0),0) | AN35: =SUM($AM$6:$AM35) | AO35: =IFERROR(INDEX($F$6:$F$565,MATCH(ROW()-5,$AN$6:$AN$565,0)),"") | AP35: =IF(AND($F35<>"",$I35<>""),IF($G35="وام و تسهیلات",1,0),0) | AQ35: =SUM($AP$6:$AP35) | AR35: =IFERROR(INDEX($F$6:$F$565,MATCH(ROW()-5,$AQ$6:$AQ$565,0)),"") | AS35: =IF(AND($F35<>"",$I35<>""),IF($G35="سرمایه و آورده صاحبان",1,0),0) | AT35: =SUM($AS$6:$AS35) | AU35: =IFERROR(INDEX($F$6:$F$565,MATCH(ROW()-5,$AT$6:$AT$565,0)),"") | AW35: =IF([3]Issues!$C$38="","",[3]Issues!$C$38) | AX35: =IF([4]Entry!$E$38="","",[4]Entry!$E$38) | AY35: =IF([4]Entry!$H$38="","",[4]Entry!$H$38) | AZ35: =IF([4]Entry!$I$38="","",[4]Entry!$I$38)
F36: =IF([1]Accounts!$D$37="","",[1]Accounts!$A$37) | G36: =IF([1]Accounts!$D$37="","",[1]Accounts!$B$37) | H36: =IF([1]Accounts!$D$37="","",[1]Accounts!$C$37) | I36: =IF([1]Accounts!$D$37="","",[1]Accounts!$D$37) | K36: =IF([1]SubGroups!$C$37="","",[1]SubGroups!$A$37) | L36: =IF([1]SubGroups!$C$37="","",[1]SubGroups!$B$37) | M36: =IF([1]SubGroups!$C$37="","",[1]SubGroups!$C$37) | N36: =IF([1]SubGroups!$C$37="","",[1]SubGroups!$D$37) | R36: =IF(AND($F36<>"",$I36<>""),IF(OR($G36="دارایی ثابت",$G36="وام و تسهیلات",$G36="سرمایه و آورده صاحبان"),0,1),0) | S36: =SUM($R$6:$R36) | T36: =IFERROR(INDEX($F$6:$F$565,MATCH(ROW()-5,$S$6:$S$565,0)),"") | V36: =IF(AND($K36<>"",$M36<>""),$L36="هزینه",0)*1 | W36: =SUM($V$6:$V36) | X36: =IFERROR(INDEX($M$6:$M$105,MATCH(ROW()-5,$W$6:$W$105,0)),"") | Z36: =IF([2]Entry!$E$39="","",[2]Entry!$E$39) | AA36: =IF([2]Entry!$G$39="","",[2]Entry!$G$39) | AB36: =IF([2]Entry!$J$39="","",[2]Entry!$J$39) | AC36: =IF([2]Entry!$K$39="","",[2]Entry!$K$39) | AD36: =IF([2]Entry!$L$39="","",[2]Entry!$L$39) | AE36: =IF([2]Entry!$M$39="","",[2]Entry!$M$39) | AF36: =IF([2]Entry!$N$39="","",[2]Entry!$N$39) | AG36: =IF([3]Issues!$B$39="","",[3]Issues!$B$39) | AH36: =IF([3]Issues!$D$39="","",[3]Issues!$D$39) | AI36: =IF([3]Issues!$E$39="","",[3]Issues!$E$39) | AJ36: =IF([2]Entry!$S$39="","",[2]Entry!$S$39) | AK36: =IF([2]Entry!$C$39="","",[2]Entry!$C$39) | AL36: =IF([2]Entry!$D$39="","",[2]Entry!$D$39) | AM36: =IF(AND($F36<>"",$I36<>""),IF($G36="دارایی ثابت",1,0),0) | AN36: =SUM($AM$6:$AM36) | AO36: =IFERROR(INDEX($F$6:$F$565,MATCH(ROW()-5,$AN$6:$AN$565,0)),"") | AP36: =IF(AND($F36<>"",$I36<>""),IF($G36="وام و تسهیلات",1,0),0) | AQ36: =SUM($AP$6:$AP36) | AR36: =IFERROR(INDEX($F$6:$F$565,MATCH(ROW()-5,$AQ$6:$AQ$565,0)),"") | AS36: =IF(AND($F36<>"",$I36<>""),IF($G36="سرمایه و آورده صاحبان",1,0),0) | AT36: =SUM($AS$6:$AS36) | AU36: =IFERROR(INDEX($F$6:$F$565,MATCH(ROW()-5,$AT$6:$AT$565,0)),"") | AW36: =IF([3]Issues!$C$39="","",[3]Issues!$C$39) | AX36: =IF([4]Entry!$E$39="","",[4]Entry!$E$39) | AY36: =IF([4]Entry!$H$39="","",[4]Entry!$H$39) | AZ36: =IF([4]Entry!$I$39="","",[4]Entry!$I$39)
F37: =IF([1]Accounts!$D$38="","",[1]Accounts!$A$38) | G37: =IF([1]Accounts!$D$38="","",[1]Accounts!$B$38) | H37: =IF([1]Accounts!$D$38="","",[1]Accounts!$C$38) | I37: =IF([1]Accounts!$D$38="","",[1]Accounts!$D$38) | K37: =IF([1]SubGroups!$C$38="","",[1]SubGroups!$A$38) | L37: =IF([1]SubGroups!$C$38="","",[1]SubGroups!$B$38) | M37: =IF([1]SubGroups!$C$38="","",[1]SubGroups!$C$38) | N37: =IF([1]SubGroups!$C$38="","",[1]SubGroups!$D$38) | R37: =IF(AND($F37<>"",$I37<>""),IF(OR($G37="دارایی ثابت",$G37="وام و تسهیلات",$G37="سرمایه و آورده صاحبان"),0,1),0) | S37: =SUM($R$6:$R37) | T37: =IFERROR(INDEX($F$6:$F$565,MATCH(ROW()-5,$S$6:$S$565,0)),"") | V37: =IF(AND($K37<>"",$M37<>""),$L37="هزینه",0)*1 | W37: =SUM($V$6:$V37) | X37: =IFERROR(INDEX($M$6:$M$105,MATCH(ROW()-5,$W$6:$W$105,0)),"") | Z37: =IF([2]Entry!$E$40="","",[2]Entry!$E$40) | AA37: =IF([2]Entry!$G$40="","",[2]Entry!$G$40) | AB37: =IF([2]Entry!$J$40="","",[2]Entry!$J$40) | AC37: =IF([2]Entry!$K$40="","",[2]Entry!$K$40) | AD37: =IF([2]Entry!$L$40="","",[2]Entry!$L$40) | AE37: =IF([2]Entry!$M$40="","",[2]Entry!$M$40) | AF37: =IF([2]Entry!$N$40="","",[2]Entry!$N$40) | AG37: =IF([3]Issues!$B$40="","",[3]Issues!$B$40) | AH37: =IF([3]Issues!$D$40="","",[3]Issues!$D$40) | AI37: =IF([3]Issues!$E$40="","",[3]Issues!$E$40) | AJ37: =IF([2]Entry!$S$40="","",[2]Entry!$S$40) | AK37: =IF([2]Entry!$C$40="","",[2]Entry!$C$40) | AL37: =IF([2]Entry!$D$40="","",[2]Entry!$D$40) | AM37: =IF(AND($F37<>"",$I37<>""),IF($G37="دارایی ثابت",1,0),0) | AN37: =SUM($AM$6:$AM37) | AO37: =IFERROR(INDEX($F$6:$F$565,MATCH(ROW()-5,$AN$6:$AN$565,0)),"") | AP37: =IF(AND($F37<>"",$I37<>""),IF($G37="وام و تسهیلات",1,0),0) | AQ37: =SUM($AP$6:$AP37) | AR37: =IFERROR(INDEX($F$6:$F$565,MATCH(ROW()-5,$AQ$6:$AQ$565,0)),"") | AS37: =IF(AND($F37<>"",$I37<>""),IF($G37="سرمایه و آورده صاحبان",1,0),0) | AT37: =SUM($AS$6:$AS37) | AU37: =IFERROR(INDEX($F$6:$F$565,MATCH(ROW()-5,$AT$6:$AT$565,0)),"") | AW37: =IF([3]Issues!$C$40="","",[3]Issues!$C$40) | AX37: =IF([4]Entry!$E$40="","",[4]Entry!$E$40) | AY37: =IF([4]Entry!$H$40="","",[4]Entry!$H$40) | AZ37: =IF([4]Entry!$I$40="","",[4]Entry!$I$40)
F38: =IF([1]Accounts!$D$39="","",[1]Accounts!$A$39) | G38: =IF([1]Accounts!$D$39="","",[1]Accounts!$B$39) | H38: =IF([1]Accounts!$D$39="","",[1]Accounts!$C$39) | I38: =IF([1]Accounts!$D$39="","",[1]Accounts!$D$39) | K38: =IF([1]SubGroups!$C$39="","",[1]SubGroups!$A$39) | L38: =IF([1]SubGroups!$C$39="","",[1]SubGroups!$B$39) | M38: =IF([1]SubGroups!$C$39="","",[1]SubGroups!$C$39) | N38: =IF([1]SubGroups!$C$39="","",[1]SubGroups!$D$39) | R38: =IF(AND($F38<>"",$I38<>""),IF(OR($G38="دارایی ثابت",$G38="وام و تسهیلات",$G38="سرمایه و آورده صاحبان"),0,1),0) | S38: =SUM($R$6:$R38) | T38: =IFERROR(INDEX($F$6:$F$565,MATCH(ROW()-5,$S$6:$S$565,0)),"") | V38: =IF(AND($K38<>"",$M38<>""),$L38="هزینه",0)*1 | W38: =SUM($V$6:$V38) | X38: =IFERROR(INDEX($M$6:$M$105,MATCH(ROW()-5,$W$6:$W$105,0)),"") | Z38: =IF([2]Entry!$E$41="","",[2]Entry!$E$41) | AA38: =IF([2]Entry!$G$41="","",[2]Entry!$G$41) | AB38: =IF([2]Entry!$J$41="","",[2]Entry!$J$41) | AC38: =IF([2]Entry!$K$41="","",[2]Entry!$K$41) | AD38: =IF([2]Entry!$L$41="","",[2]Entry!$L$41) | AE38: =IF([2]Entry!$M$41="","",[2]Entry!$M$41) | AF38: =IF([2]Entry!$N$41="","",[2]Entry!$N$41) | AG38: =IF([3]Issues!$B$41="","",[3]Issues!$B$41) | AH38: =IF([3]Issues!$D$41="","",[3]Issues!$D$41) | AI38: =IF([3]Issues!$E$41="","",[3]Issues!$E$41) | AJ38: =IF([2]Entry!$S$41="","",[2]Entry!$S$41) | AK38: =IF([2]Entry!$C$41="","",[2]Entry!$C$41) | AL38: =IF([2]Entry!$D$41="","",[2]Entry!$D$41) | AM38: =IF(AND($F38<>"",$I38<>""),IF($G38="دارایی ثابت",1,0),0) | AN38: =SUM($AM$6:$AM38) | AO38: =IFERROR(INDEX($F$6:$F$565,MATCH(ROW()-5,$AN$6:$AN$565,0)),"") | AP38: =IF(AND($F38<>"",$I38<>""),IF($G38="وام و تسهیلات",1,0),0) | AQ38: =SUM($AP$6:$AP38) | AR38: =IFERROR(INDEX($F$6:$F$565,MATCH(ROW()-5,$AQ$6:$AQ$565,0)),"") | AS38: =IF(AND($F38<>"",$I38<>""),IF($G38="سرمایه و آورده صاحبان",1,0),0) | AT38: =SUM($AS$6:$AS38) | AU38: =IFERROR(INDEX($F$6:$F$565,MATCH(ROW()-5,$AT$6:$AT$565,0)),"") | AW38: =IF([3]Issues!$C$41="","",[3]Issues!$C$41) | AX38: =IF([4]Entry!$E$41="","",[4]Entry!$E$41) | AY38: =IF([4]Entry!$H$41="","",[4]Entry!$H$41) | AZ38: =IF([4]Entry!$I$41="","",[4]Entry!$I$41)
F39: =IF([1]Accounts!$D$40="","",[1]Accounts!$A$40) | G39: =IF([1]Accounts!$D$40="","",[1]Accounts!$B$40) | H39: =IF([1]Accounts!$D$40="","",[1]Accounts!$C$40) | I39: =IF([1]Accounts!$D$40="","",[1]Accounts!$D$40) | K39: =IF([1]SubGroups!$C$40="","",[1]SubGroups!$A$40) | L39: =IF([1]SubGroups!$C$40="","",[1]SubGroups!$B$40) | M39: =IF([1]SubGroups!$C$40="","",[1]SubGroups!$C$40) | N39: =IF([1]SubGroups!$C$40="","",[1]SubGroups!$D$40) | R39: =IF(AND($F39<>"",$I39<>""),IF(OR($G39="دارایی ثابت",$G39="وام و تسهیلات",$G39="سرمایه و آورده صاحبان"),0,1),0) | S39: =SUM($R$6:$R39) | T39: =IFERROR(INDEX($F$6:$F$565,MATCH(ROW()-5,$S$6:$S$565,0)),"") | V39: =IF(AND($K39<>"",$M39<>""),$L39="هزینه",0)*1 | W39: =SUM($V$6:$V39) | X39: =IFERROR(INDEX($M$6:$M$105,MATCH(ROW()-5,$W$6:$W$105,0)),"") | Z39: =IF([2]Entry!$E$42="","",[2]Entry!$E$42) | AA39: =IF([2]Entry!$G$42="","",[2]Entry!$G$42) | AB39: =IF([2]Entry!$J$42="","",[2]Entry!$J$42) | AC39: =IF([2]Entry!$K$42="","",[2]Entry!$K$42) | AD39: =IF([2]Entry!$L$42="","",[2]Entry!$L$42) | AE39: =IF([2]Entry!$M$42="","",[2]Entry!$M$42) | AF39: =IF([2]Entry!$N$42="","",[2]Entry!$N$42) | AG39: =IF([3]Issues!$B$42="","",[3]Issues!$B$42) | AH39: =IF([3]Issues!$D$42="","",[3]Issues!$D$42) | AI39: =IF([3]Issues!$E$42="","",[3]Issues!$E$42) | AJ39: =IF([2]Entry!$S$42="","",[2]Entry!$S$42) | AK39: =IF([2]Entry!$C$42="","",[2]Entry!$C$42) | AL39: =IF([2]Entry!$D$42="","",[2]Entry!$D$42) | AM39: =IF(AND($F39<>"",$I39<>""),IF($G39="دارایی ثابت",1,0),0) | AN39: =SUM($AM$6:$AM39) | AO39: =IFERROR(INDEX($F$6:$F$565,MATCH(ROW()-5,$AN$6:$AN$565,0)),"") | AP39: =IF(AND($F39<>"",$I39<>""),IF($G39="وام و تسهیلات",1,0),0) | AQ39: =SUM($AP$6:$AP39) | AR39: =IFERROR(INDEX($F$6:$F$565,MATCH(ROW()-5,$AQ$6:$AQ$565,0)),"") | AS39: =IF(AND($F39<>"",$I39<>""),IF($G39="سرمایه و آورده صاحبان",1,0),0) | AT39: =SUM($AS$6:$AS39) | AU39: =IFERROR(INDEX($F$6:$F$565,MATCH(ROW()-5,$AT$6:$AT$565,0)),"") | AW39: =IF([3]Issues!$C$42="","",[3]Issues!$C$42) | AX39: =IF([4]Entry!$E$42="","",[4]Entry!$E$42) | AY39: =IF([4]Entry!$H$42="","",[4]Entry!$H$42) | AZ39: =IF([4]Entry!$I$42="","",[4]Entry!$I$42)
F40: =IF([1]Accounts!$D$41="","",[1]Accounts!$A$41) | G40: =IF([1]Accounts!$D$41="","",[1]Accounts!$B$41) | H40: =IF([1]Accounts!$D$41="","",[1]Accounts!$C$41) | I40: =IF([1]Accounts!$D$41="","",[1]Accounts!$D$41) | K40: =IF([1]SubGroups!$C$41="","",[1]SubGroups!$A$41) | L40: =IF([1]SubGroups!$C$41="","",[1]SubGroups!$B$41) | M40: =IF([1]SubGroups!$C$41="","",[1]SubGroups!$C$41) | N40: =IF([1]SubGroups!$C$41="","",[1]SubGroups!$D$41) | R40: =IF(AND($F40<>"",$I40<>""),IF(OR($G40="دارایی ثابت",$G40="وام و تسهیلات",$G40="سرمایه و آورده صاحبان"),0,1),0) | S40: =SUM($R$6:$R40) | T40: =IFERROR(INDEX($F$6:$F$565,MATCH(ROW()-5,$S$6:$S$565,0)),"") | V40: =IF(AND($K40<>"",$M40<>""),$L40="هزینه",0)*1 | W40: =SUM($V$6:$V40) | X40: =IFERROR(INDEX($M$6:$M$105,MATCH(ROW()-5,$W$6:$W$105,0)),"") | Z40: =IF([2]Entry!$E$43="","",[2]Entry!$E$43) | AA40: =IF([2]Entry!$G$43="","",[2]Entry!$G$43) | AB40: =IF([2]Entry!$J$43="","",[2]Entry!$J$43) | AC40: =IF([2]Entry!$K$43="","",[2]Entry!$K$43) | AD40: =IF([2]Entry!$L$43="","",[2]Entry!$L$43) | AE40: =IF([2]Entry!$M$43="","",[2]Entry!$M$43) | AF40: =IF([2]Entry!$N$43="","",[2]Entry!$N$43) | AG40: =IF([3]Issues!$B$43="","",[3]Issues!$B$43) | AH40: =IF([3]Issues!$D$43="","",[3]Issues!$D$43) | AI40: =IF([3]Issues!$E$43="","",[3]Issues!$E$43) | AJ40: =IF([2]Entry!$S$43="","",[2]Entry!$S$43) | AK40: =IF([2]Entry!$C$43="","",[2]Entry!$C$43) | AL40: =IF([2]Entry!$D$43="","",[2]Entry!$D$43) | AM40: =IF(AND($F40<>"",$I40<>""),IF($G40="دارایی ثابت",1,0),0) | AN40: =SUM($AM$6:$AM40) | AO40: =IFERROR(INDEX($F$6:$F$565,MATCH(ROW()-5,$AN$6:$AN$565,0)),"") | AP40: =IF(AND($F40<>"",$I40<>""),IF($G40="وام و تسهیلات",1,0),0) | AQ40: =SUM($AP$6:$AP40) | AR40: =IFERROR(INDEX($F$6:$F$565,MATCH(ROW()-5,$AQ$6:$AQ$565,0)),"") | AS40: =IF(AND($F40<>"",$I40<>""),IF($G40="سرمایه و آورده صاحبان",1,0),0) | AT40: =SUM($AS$6:$AS40) | AU40: =IFERROR(INDEX($F$6:$F$565,MATCH(ROW()-5,$AT$6:$AT$565,0)),"") | AW40: =IF([3]Issues!$C$43="","",[3]Issues!$C$43) | AX40: =IF([4]Entry!$E$43="","",[4]Entry!$E$43) | AY40: =IF([4]Entry!$H$43="","",[4]Entry!$H$43) | AZ40: =IF([4]Entry!$I$43="","",[4]Entry!$I$43)
F41: =IF([1]Accounts!$D$42="","",[1]Accounts!$A$42) | G41: =IF([1]Accounts!$D$42="","",[1]Accounts!$B$42) | H41: =IF([1]Accounts!$D$42="","",[1]Accounts!$C$42) | I41: =IF([1]Accounts!$D$42="","",[1]Accounts!$D$42) | K41: =IF([1]SubGroups!$C$42="","",[1]SubGroups!$A$42) | L41: =IF([1]SubGroups!$C$42="","",[1]SubGroups!$B$42) | M41: =IF([1]SubGroups!$C$42="","",[1]SubGroups!$C$42) | N41: =IF([1]SubGroups!$C$42="","",[1]SubGroups!$D$42) | R41: =IF(AND($F41<>"",$I41<>""),IF(OR($G41="دارایی ثابت",$G41="وام و تسهیلات",$G41="سرمایه و آورده صاحبان"),0,1),0) | S41: =SUM($R$6:$R41) | T41: =IFERROR(INDEX($F$6:$F$565,MATCH(ROW()-5,$S$6:$S$565,0)),"") | V41: =IF(AND($K41<>"",$M41<>""),$L41="هزینه",0)*1 | W41: =SUM($V$6:$V41) | X41: =IFERROR(INDEX($M$6:$M$105,MATCH(ROW()-5,$W$6:$W$105,0)),"") | Z41: =IF([2]Entry!$E$44="","",[2]Entry!$E$44) | AA41: =IF([2]Entry!$G$44="","",[2]Entry!$G$44) | AB41: =IF([2]Entry!$J$44="","",[2]Entry!$J$44) | AC41: =IF([2]Entry!$K$44="","",[2]Entry!$K$44) | AD41: =IF([2]Entry!$L$44="","",[2]Entry!$L$44) | AE41: =IF([2]Entry!$M$44="","",[2]Entry!$M$44) | AF41: =IF([2]Entry!$N$44="","",[2]Entry!$N$44) | AG41: =IF([3]Issues!$B$44="","",[3]Issues!$B$44) | AH41: =IF([3]Issues!$D$44="","",[3]Issues!$D$44) | AI41: =IF([3]Issues!$E$44="","",[3]Issues!$E$44) | AJ41: =IF([2]Entry!$S$44="","",[2]Entry!$S$44) | AK41: =IF([2]Entry!$C$44="","",[2]Entry!$C$44) | AL41: =IF([2]Entry!$D$44="","",[2]Entry!$D$44) | AM41: =IF(AND($F41<>"",$I41<>""),IF($G41="دارایی ثابت",1,0),0) | AN41: =SUM($AM$6:$AM41) | AO41: =IFERROR(INDEX($F$6:$F$565,MATCH(ROW()-5,$AN$6:$AN$565,0)),"") | AP41: =IF(AND($F41<>"",$I41<>""),IF($G41="وام و تسهیلات",1,0),0) | AQ41: =SUM($AP$6:$AP41) | AR41: =IFERROR(INDEX($F$6:$F$565,MATCH(ROW()-5,$AQ$6:$AQ$565,0)),"") | AS41: =IF(AND($F41<>"",$I41<>""),IF($G41="سرمایه و آورده صاحبان",1,0),0) | AT41: =SUM($AS$6:$AS41) | AU41: =IFERROR(INDEX($F$6:$F$565,MATCH(ROW()-5,$AT$6:$AT$565,0)),"") | AW41: =IF([3]Issues!$C$44="","",[3]Issues!$C$44) | AX41: =IF([4]Entry!$E$44="","",[4]Entry!$E$44) | AY41: =IF([4]Entry!$H$44="","",[4]Entry!$H$44) | AZ41: =IF([4]Entry!$I$44="","",[4]Entry!$I$44)
F42: =IF([1]Accounts!$D$43="","",[1]Accounts!$A$43) | G42: =IF([1]Accounts!$D$43="","",[1]Accounts!$B$43) | H42: =IF([1]Accounts!$D$43="","",[1]Accounts!$C$43) | I42: =IF([1]Accounts!$D$43="","",[1]Accounts!$D$43) | K42: =IF([1]SubGroups!$C$43="","",[1]SubGroups!$A$43) | L42: =IF([1]SubGroups!$C$43="","",[1]SubGroups!$B$43) | M42: =IF([1]SubGroups!$C$43="","",[1]SubGroups!$C$43) | N42: =IF([1]SubGroups!$C$43="","",[1]SubGroups!$D$43) | R42: =IF(AND($F42<>"",$I42<>""),IF(OR($G42="دارایی ثابت",$G42="وام و تسهیلات",$G42="سرمایه و آورده صاحبان"),0,1),0) | S42: =SUM($R$6:$R42) | T42: =IFERROR(INDEX($F$6:$F$565,MATCH(ROW()-5,$S$6:$S$565,0)),"") | V42: =IF(AND($K42<>"",$M42<>""),$L42="هزینه",0)*1 | W42: =SUM($V$6:$V42) | X42: =IFERROR(INDEX($M$6:$M$105,MATCH(ROW()-5,$W$6:$W$105,0)),"") | Z42: =IF([2]Entry!$E$45="","",[2]Entry!$E$45) | AA42: =IF([2]Entry!$G$45="","",[2]Entry!$G$45) | AB42: =IF([2]Entry!$J$45="","",[2]Entry!$J$45) | AC42: =IF([2]Entry!$K$45="","",[2]Entry!$K$45) | AD42: =IF([2]Entry!$L$45="","",[2]Entry!$L$45) | AE42: =IF([2]Entry!$M$45="","",[2]Entry!$M$45) | AF42: =IF([2]Entry!$N$45="","",[2]Entry!$N$45) | AG42: =IF([3]Issues!$B$45="","",[3]Issues!$B$45) | AH42: =IF([3]Issues!$D$45="","",[3]Issues!$D$45) | AI42: =IF([3]Issues!$E$45="","",[3]Issues!$E$45) | AJ42: =IF([2]Entry!$S$45="","",[2]Entry!$S$45) | AK42: =IF([2]Entry!$C$45="","",[2]Entry!$C$45) | AL42: =IF([2]Entry!$D$45="","",[2]Entry!$D$45) | AM42: =IF(AND($F42<>"",$I42<>""),IF($G42="دارایی ثابت",1,0),0) | AN42: =SUM($AM$6:$AM42) | AO42: =IFERROR(INDEX($F$6:$F$565,MATCH(ROW()-5,$AN$6:$AN$565,0)),"") | AP42: =IF(AND($F42<>"",$I42<>""),IF($G42="وام و تسهیلات",1,0),0) | AQ42: =SUM($AP$6:$AP42) | AR42: =IFERROR(INDEX($F$6:$F$565,MATCH(ROW()-5,$AQ$6:$AQ$565,0)),"") | AS42: =IF(AND($F42<>"",$I42<>""),IF($G42="سرمایه و آورده صاحبان",1,0),0) | AT42: =SUM($AS$6:$AS42) | AU42: =IFERROR(INDEX($F$6:$F$565,MATCH(ROW()-5,$AT$6:$AT$565,0)),"") | AW42: =IF([3]Issues!$C$45="","",[3]Issues!$C$45) | AX42: =IF([4]Entry!$E$45="","",[4]Entry!$E$45) | AY42: =IF([4]Entry!$H$45="","",[4]Entry!$H$45) | AZ42: =IF([4]Entry!$I$45="","",[4]Entry!$I$45)
F43: =IF([1]Accounts!$D$44="","",[1]Accounts!$A$44) | G43: =IF([1]Accounts!$D$44="","",[1]Accounts!$B$44) | H43: =IF([1]Accounts!$D$44="","",[1]Accounts!$C$44) | I43: =IF([1]Accounts!$D$44="","",[1]Accounts!$D$44) | K43: =IF([1]SubGroups!$C$44="","",[1]SubGroups!$A$44) | L43: =IF([1]SubGroups!$C$44="","",[1]SubGroups!$B$44) | M43: =IF([1]SubGroups!$C$44="","",[1]SubGroups!$C$44) | N43: =IF([1]SubGroups!$C$44="","",[1]SubGroups!$D$44) | R43: =IF(AND($F43<>"",$I43<>""),IF(OR($G43="دارایی ثابت",$G43="وام و تسهیلات",$G43="سرمایه و آورده صاحبان"),0,1),0) | S43: =SUM($R$6:$R43) | T43: =IFERROR(INDEX($F$6:$F$565,MATCH(ROW()-5,$S$6:$S$565,0)),"") | V43: =IF(AND($K43<>"",$M43<>""),$L43="هزینه",0)*1 | W43: =SUM($V$6:$V43) | X43: =IFERROR(INDEX($M$6:$M$105,MATCH(ROW()-5,$W$6:$W$105,0)),"") | Z43: =IF([2]Entry!$E$46="","",[2]Entry!$E$46) | AA43: =IF([2]Entry!$G$46="","",[2]Entry!$G$46) | AB43: =IF([2]Entry!$J$46="","",[2]Entry!$J$46) | AC43: =IF([2]Entry!$K$46="","",[2]Entry!$K$46) | AD43: =IF([2]Entry!$L$46="","",[2]Entry!$L$46) | AE43: =IF([2]Entry!$M$46="","",[2]Entry!$M$46) | AF43: =IF([2]Entry!$N$46="","",[2]Entry!$N$46) | AG43: =IF([3]Issues!$B$46="","",[3]Issues!$B$46) | AH43: =IF([3]Issues!$D$46="","",[3]Issues!$D$46) | AI43: =IF([3]Issues!$E$46="","",[3]Issues!$E$46) | AJ43: =IF([2]Entry!$S$46="","",[2]Entry!$S$46) | AK43: =IF([2]Entry!$C$46="","",[2]Entry!$C$46) | AL43: =IF([2]Entry!$D$46="","",[2]Entry!$D$46) | AM43: =IF(AND($F43<>"",$I43<>""),IF($G43="دارایی ثابت",1,0),0) | AN43: =SUM($AM$6:$AM43) | AO43: =IFERROR(INDEX($F$6:$F$565,MATCH(ROW()-5,$AN$6:$AN$565,0)),"") | AP43: =IF(AND($F43<>"",$I43<>""),IF($G43="وام و تسهیلات",1,0),0) | AQ43: =SUM($AP$6:$AP43) | AR43: =IFERROR(INDEX($F$6:$F$565,MATCH(ROW()-5,$AQ$6:$AQ$565,0)),"") | AS43: =IF(AND($F43<>"",$I43<>""),IF($G43="سرمایه و آورده صاحبان",1,0),0) | AT43: =SUM($AS$6:$AS43) | AU43: =IFERROR(INDEX($F$6:$F$565,MATCH(ROW()-5,$AT$6:$AT$565,0)),"") | AW43: =IF([3]Issues!$C$46="","",[3]Issues!$C$46) | AX43: =IF([4]Entry!$E$46="","",[4]Entry!$E$46) | AY43: =IF([4]Entry!$H$46="","",[4]Entry!$H$46) | AZ43: =IF([4]Entry!$I$46="","",[4]Entry!$I$46)
F44: =IF([1]Accounts!$D$45="","",[1]Accounts!$A$45) | G44: =IF([1]Accounts!$D$45="","",[1]Accounts!$B$45) | H44: =IF([1]Accounts!$D$45="","",[1]Accounts!$C$45) | I44: =IF([1]Accounts!$D$45="","",[1]Accounts!$D$45) | K44: =IF([1]SubGroups!$C$45="","",[1]SubGroups!$A$45) | L44: =IF([1]SubGroups!$C$45="","",[1]SubGroups!$B$45) | M44: =IF([1]SubGroups!$C$45="","",[1]SubGroups!$C$45) | N44: =IF([1]SubGroups!$C$45="","",[1]SubGroups!$D$45) | R44: =IF(AND($F44<>"",$I44<>""),IF(OR($G44="دارایی ثابت",$G44="وام و تسهیلات",$G44="سرمایه و آورده صاحبان"),0,1),0) | S44: =SUM($R$6:$R44) | T44: =IFERROR(INDEX($F$6:$F$565,MATCH(ROW()-5,$S$6:$S$565,0)),"") | V44: =IF(AND($K44<>"",$M44<>""),$L44="هزینه",0)*1 | W44: =SUM($V$6:$V44) | X44: =IFERROR(INDEX($M$6:$M$105,MATCH(ROW()-5,$W$6:$W$105,0)),"") | Z44: =IF([2]Entry!$E$47="","",[2]Entry!$E$47) | AA44: =IF([2]Entry!$G$47="","",[2]Entry!$G$47) | AB44: =IF([2]Entry!$J$47="","",[2]Entry!$J$47) | AC44: =IF([2]Entry!$K$47="","",[2]Entry!$K$47) | AD44: =IF([2]Entry!$L$47="","",[2]Entry!$L$47) | AE44: =IF([2]Entry!$M$47="","",[2]Entry!$M$47) | AF44: =IF([2]Entry!$N$47="","",[2]Entry!$N$47) | AG44: =IF([3]Issues!$B$47="","",[3]Issues!$B$47) | AH44: =IF([3]Issues!$D$47="","",[3]Issues!$D$47) | AI44: =IF([3]Issues!$E$47="","",[3]Issues!$E$47) | AJ44: =IF([2]Entry!$S$47="","",[2]Entry!$S$47) | AK44: =IF([2]Entry!$C$47="","",[2]Entry!$C$47) | AL44: =IF([2]Entry!$D$47="","",[2]Entry!$D$47) | AM44: =IF(AND($F44<>"",$I44<>""),IF($G44="دارایی ثابت",1,0),0) | AN44: =SUM($AM$6:$AM44) | AO44: =IFERROR(INDEX($F$6:$F$565,MATCH(ROW()-5,$AN$6:$AN$565,0)),"") | AP44: =IF(AND($F44<>"",$I44<>""),IF($G44="وام و تسهیلات",1,0),0) | AQ44: =SUM($AP$6:$AP44) | AR44: =IFERROR(INDEX($F$6:$F$565,MATCH(ROW()-5,$AQ$6:$AQ$565,0)),"") | AS44: =IF(AND($F44<>"",$I44<>""),IF($G44="سرمایه و آورده صاحبان",1,0),0) | AT44: =SUM($AS$6:$AS44) | AU44: =IFERROR(INDEX($F$6:$F$565,MATCH(ROW()-5,$AT$6:$AT$565,0)),"") | AW44: =IF([3]Issues!$C$47="","",[3]Issues!$C$47) | AX44: =IF([4]Entry!$E$47="","",[4]Entry!$E$47) | AY44: =IF([4]Entry!$H$47="","",[4]Entry!$H$47) | AZ44: =IF([4]Entry!$I$47="","",[4]Entry!$I$47)
F45: =IF([1]Accounts!$D$46="","",[1]Accounts!$A$46) | G45: =IF([1]Accounts!$D$46="","",[1]Accounts!$B$46) | H45: =IF([1]Accounts!$D$46="","",[1]Accounts!$C$46) | I45: =IF([1]Accounts!$D$46="","",[1]Accounts!$D$46) | K45: =IF([1]SubGroups!$C$46="","",[1]SubGroups!$A$46) | L45: =IF([1]SubGroups!$C$46="","",[1]SubGroups!$B$46) | M45: =IF([1]SubGroups!$C$46="","",[1]SubGroups!$C$46) | N45: =IF([1]SubGroups!$C$46="","",[1]SubGroups!$D$46) | R45: =IF(AND($F45<>"",$I45<>""),IF(OR($G45="دارایی ثابت",$G45="وام و تسهیلات",$G45="سرمایه و آورده صاحبان"),0,1),0) | S45: =SUM($R$6:$R45) | T45: =IFERROR(INDEX($F$6:$F$565,MATCH(ROW()-5,$S$6:$S$565,0)),"") | V45: =IF(AND($K45<>"",$M45<>""),$L45="هزینه",0)*1 | W45: =SUM($V$6:$V45) | X45: =IFERROR(INDEX($M$6:$M$105,MATCH(ROW()-5,$W$6:$W$105,0)),"") | Z45: =IF([2]Entry!$E$48="","",[2]Entry!$E$48) | AA45: =IF([2]Entry!$G$48="","",[2]Entry!$G$48) | AB45: =IF([2]Entry!$J$48="","",[2]Entry!$J$48) | AC45: =IF([2]Entry!$K$48="","",[2]Entry!$K$48) | AD45: =IF([2]Entry!$L$48="","",[2]Entry!$L$48) | AE45: =IF([2]Entry!$M$48="","",[2]Entry!$M$48) | AF45: =IF([2]Entry!$N$48="","",[2]Entry!$N$48) | AG45: =IF([3]Issues!$B$48="","",[3]Issues!$B$48) | AH45: =IF([3]Issues!$D$48="","",[3]Issues!$D$48) | AI45: =IF([3]Issues!$E$48="","",[3]Issues!$E$48) | AJ45: =IF([2]Entry!$S$48="","",[2]Entry!$S$48) | AK45: =IF([2]Entry!$C$48="","",[2]Entry!$C$48) | AL45: =IF([2]Entry!$D$48="","",[2]Entry!$D$48) | AM45: =IF(AND($F45<>"",$I45<>""),IF($G45="دارایی ثابت",1,0),0) | AN45: =SUM($AM$6:$AM45) | AO45: =IFERROR(INDEX($F$6:$F$565,MATCH(ROW()-5,$AN$6:$AN$565,0)),"") | AP45: =IF(AND($F45<>"",$I45<>""),IF($G45="وام و تسهیلات",1,0),0) | AQ45: =SUM($AP$6:$AP45) | AR45: =IFERROR(INDEX($F$6:$F$565,MATCH(ROW()-5,$AQ$6:$AQ$565,0)),"") | AS45: =IF(AND($F45<>"",$I45<>""),IF($G45="سرمایه و آورده صاحبان",1,0),0) | AT45: =SUM($AS$6:$AS45) | AU45: =IFERROR(INDEX($F$6:$F$565,MATCH(ROW()-5,$AT$6:$AT$565,0)),"") | AW45: =IF([3]Issues!$C$48="","",[3]Issues!$C$48) | AX45: =IF([4]Entry!$E$48="","",[4]Entry!$E$48) | AY45: =IF([4]Entry!$H$48="","",[4]Entry!$H$48) | AZ45: =IF([4]Entry!$I$48="","",[4]Entry!$I$48)
F46: =IF([1]Accounts!$D$47="","",[1]Accounts!$A$47) | G46: =IF([1]Accounts!$D$47="","",[1]Accounts!$B$47) | H46: =IF([1]Accounts!$D$47="","",[1]Accounts!$C$47) | I46: =IF([1]Accounts!$D$47="","",[1]Accounts!$D$47) | K46: =IF([1]SubGroups!$C$47="","",[1]SubGroups!$A$47) | L46: =IF([1]SubGroups!$C$47="","",[1]SubGroups!$B$47) | M46: =IF([1]SubGroups!$C$47="","",[1]SubGroups!$C$47) | N46: =IF([1]SubGroups!$C$47="","",[1]SubGroups!$D$47) | R46: =IF(AND($F46<>"",$I46<>""),IF(OR($G46="دارایی ثابت",$G46="وام و تسهیلات",$G46="سرمایه و آورده صاحبان"),0,1),0) | S46: =SUM($R$6:$R46) | T46: =IFERROR(INDEX($F$6:$F$565,MATCH(ROW()-5,$S$6:$S$565,0)),"") | V46: =IF(AND($K46<>"",$M46<>""),$L46="هزینه",0)*1 | W46: =SUM($V$6:$V46) | X46: =IFERROR(INDEX($M$6:$M$105,MATCH(ROW()-5,$W$6:$W$105,0)),"") | Z46: =IF([2]Entry!$E$49="","",[2]Entry!$E$49) | AA46: =IF([2]Entry!$G$49="","",[2]Entry!$G$49) | AB46: =IF([2]Entry!$J$49="","",[2]Entry!$J$49) | AC46: =IF([2]Entry!$K$49="","",[2]Entry!$K$49) | AD46: =IF([2]Entry!$L$49="","",[2]Entry!$L$49) | AE46: =IF([2]Entry!$M$49="","",[2]Entry!$M$49) | AF46: =IF([2]Entry!$N$49="","",[2]Entry!$N$49) | AG46: =IF([3]Issues!$B$49="","",[3]Issues!$B$49) | AH46: =IF([3]Issues!$D$49="","",[3]Issues!$D$49) | AI46: =IF([3]Issues!$E$49="","",[3]Issues!$E$49) | AJ46: =IF([2]Entry!$S$49="","",[2]Entry!$S$49) | AK46: =IF([2]Entry!$C$49="","",[2]Entry!$C$49) | AL46: =IF([2]Entry!$D$49="","",[2]Entry!$D$49) | AM46: =IF(AND($F46<>"",$I46<>""),IF($G46="دارایی ثابت",1,0),0) | AN46: =SUM($AM$6:$AM46) | AO46: =IFERROR(INDEX($F$6:$F$565,MATCH(ROW()-5,$AN$6:$AN$565,0)),"") | AP46: =IF(AND($F46<>"",$I46<>""),IF($G46="وام و تسهیلات",1,0),0) | AQ46: =SUM($AP$6:$AP46) | AR46: =IFERROR(INDEX($F$6:$F$565,MATCH(ROW()-5,$AQ$6:$AQ$565,0)),"") | AS46: =IF(AND($F46<>"",$I46<>""),IF($G46="سرمایه و آورده صاحبان",1,0),0) | AT46: =SUM($AS$6:$AS46) | AU46: =IFERROR(INDEX($F$6:$F$565,MATCH(ROW()-5,$AT$6:$AT$565,0)),"") | AW46: =IF([3]Issues!$C$49="","",[3]Issues!$C$49) | AX46: =IF([4]Entry!$E$49="","",[4]Entry!$E$49) | AY46: =IF([4]Entry!$H$49="","",[4]Entry!$H$49) | AZ46: =IF([4]Entry!$I$49="","",[4]Entry!$I$49)
F47: =IF([1]Accounts!$D$48="","",[1]Accounts!$A$48) | G47: =IF([1]Accounts!$D$48="","",[1]Accounts!$B$48) | H47: =IF([1]Accounts!$D$48="","",[1]Accounts!$C$48) | I47: =IF([1]Accounts!$D$48="","",[1]Accounts!$D$48) | K47: =IF([1]SubGroups!$C$48="","",[1]SubGroups!$A$48) | L47: =IF([1]SubGroups!$C$48="","",[1]SubGroups!$B$48) | M47: =IF([1]SubGroups!$C$48="","",[1]SubGroups!$C$48) | N47: =IF([1]SubGroups!$C$48="","",[1]SubGroups!$D$48) | R47: =IF(AND($F47<>"",$I47<>""),IF(OR($G47="دارایی ثابت",$G47="وام و تسهیلات",$G47="سرمایه و آورده صاحبان"),0,1),0) | S47: =SUM($R$6:$R47) | T47: =IFERROR(INDEX($F$6:$F$565,MATCH(ROW()-5,$S$6:$S$565,0)),"") | V47: =IF(AND($K47<>"",$M47<>""),$L47="هزینه",0)*1 | W47: =SUM($V$6:$V47) | X47: =IFERROR(INDEX($M$6:$M$105,MATCH(ROW()-5,$W$6:$W$105,0)),"") | Z47: =IF([2]Entry!$E$50="","",[2]Entry!$E$50) | AA47: =IF([2]Entry!$G$50="","",[2]Entry!$G$50) | AB47: =IF([2]Entry!$J$50="","",[2]Entry!$J$50) | AC47: =IF([2]Entry!$K$50="","",[2]Entry!$K$50) | AD47: =IF([2]Entry!$L$50="","",[2]Entry!$L$50) | AE47: =IF([2]Entry!$M$50="","",[2]Entry!$M$50) | AF47: =IF([2]Entry!$N$50="","",[2]Entry!$N$50) | AG47: =IF([3]Issues!$B$50="","",[3]Issues!$B$50) | AH47: =IF([3]Issues!$D$50="","",[3]Issues!$D$50) | AI47: =IF([3]Issues!$E$50="","",[3]Issues!$E$50) | AJ47: =IF([2]Entry!$S$50="","",[2]Entry!$S$50) | AK47: =IF([2]Entry!$C$50="","",[2]Entry!$C$50) | AL47: =IF([2]Entry!$D$50="","",[2]Entry!$D$50) | AM47: =IF(AND($F47<>"",$I47<>""),IF($G47="دارایی ثابت",1,0),0) | AN47: =SUM($AM$6:$AM47) | AO47: =IFERROR(INDEX($F$6:$F$565,MATCH(ROW()-5,$AN$6:$AN$565,0)),"") | AP47: =IF(AND($F47<>"",$I47<>""),IF($G47="وام و تسهیلات",1,0),0) | AQ47: =SUM($AP$6:$AP47) | AR47: =IFERROR(INDEX($F$6:$F$565,MATCH(ROW()-5,$AQ$6:$AQ$565,0)),"") | AS47: =IF(AND($F47<>"",$I47<>""),IF($G47="سرمایه و آورده صاحبان",1,0),0) | AT47: =SUM($AS$6:$AS47) | AU47: =IFERROR(INDEX($F$6:$F$565,MATCH(ROW()-5,$AT$6:$AT$565,0)),"") | AW47: =IF([3]Issues!$C$50="","",[3]Issues!$C$50) | AX47: =IF([4]Entry!$E$50="","",[4]Entry!$E$50) | AY47: =IF([4]Entry!$H$50="","",[4]Entry!$H$50) | AZ47: =IF([4]Entry!$I$50="","",[4]Entry!$I$50)
F48: =IF([1]Accounts!$D$49="","",[1]Accounts!$A$49) | G48: =IF([1]Accounts!$D$49="","",[1]Accounts!$B$49) | H48: =IF([1]Accounts!$D$49="","",[1]Accounts!$C$49) | I48: =IF([1]Accounts!$D$49="","",[1]Accounts!$D$49) | K48: =IF([1]SubGroups!$C$49="","",[1]SubGroups!$A$49) | L48: =IF([1]SubGroups!$C$49="","",[1]SubGroups!$B$49) | M48: =IF([1]SubGroups!$C$49="","",[1]SubGroups!$C$49) | N48: =IF([1]SubGroups!$C$49="","",[1]SubGroups!$D$49) | R48: =IF(AND($F48<>"",$I48<>""),IF(OR($G48="دارایی ثابت",$G48="وام و تسهیلات",$G48="سرمایه و آورده صاحبان"),0,1),0) | S48: =SUM($R$6:$R48) | T48: =IFERROR(INDEX($F$6:$F$565,MATCH(ROW()-5,$S$6:$S$565,0)),"") | V48: =IF(AND($K48<>"",$M48<>""),$L48="هزینه",0)*1 | W48: =SUM($V$6:$V48) | X48: =IFERROR(INDEX($M$6:$M$105,MATCH(ROW()-5,$W$6:$W$105,0)),"") | Z48: =IF([2]Entry!$E$51="","",[2]Entry!$E$51) | AA48: =IF([2]Entry!$G$51="","",[2]Entry!$G$51) | AB48: =IF([2]Entry!$J$51="","",[2]Entry!$J$51) | AC48: =IF([2]Entry!$K$51="","",[2]Entry!$K$51) | AD48: =IF([2]Entry!$L$51="","",[2]Entry!$L$51) | AE48: =IF([2]Entry!$M$51="","",[2]Entry!$M$51) | AF48: =IF([2]Entry!$N$51="","",[2]Entry!$N$51) | AG48: =IF([3]Issues!$B$51="","",[3]Issues!$B$51) | AH48: =IF([3]Issues!$D$51="","",[3]Issues!$D$51) | AI48: =IF([3]Issues!$E$51="","",[3]Issues!$E$51) | AJ48: =IF([2]Entry!$S$51="","",[2]Entry!$S$51) | AK48: =IF([2]Entry!$C$51="","",[2]Entry!$C$51) | AL48: =IF([2]Entry!$D$51="","",[2]Entry!$D$51) | AM48: =IF(AND($F48<>"",$I48<>""),IF($G48="دارایی ثابت",1,0),0) | AN48: =SUM($AM$6:$AM48) | AO48: =IFERROR(INDEX($F$6:$F$565,MATCH(ROW()-5,$AN$6:$AN$565,0)),"") | AP48: =IF(AND($F48<>"",$I48<>""),IF($G48="وام و تسهیلات",1,0),0) | AQ48: =SUM($AP$6:$AP48) | AR48: =IFERROR(INDEX($F$6:$F$565,MATCH(ROW()-5,$AQ$6:$AQ$565,0)),"") | AS48: =IF(AND($F48<>"",$I48<>""),IF($G48="سرمایه و آورده صاحبان",1,0),0) | AT48: =SUM($AS$6:$AS48) | AU48: =IFERROR(INDEX($F$6:$F$565,MATCH(ROW()-5,$AT$6:$AT$565,0)),"") | AW48: =IF([3]Issues!$C$51="","",[3]Issues!$C$51) | AX48: =IF([4]Entry!$E$51="","",[4]Entry!$E$51) | AY48: =IF([4]Entry!$H$51="","",[4]Entry!$H$51) | AZ48: =IF([4]Entry!$I$51="","",[4]Entry!$I$51)
F49: =IF([1]Accounts!$D$50="","",[1]Accounts!$A$50) | G49: =IF([1]Accounts!$D$50="","",[1]Accounts!$B$50) | H49: =IF([1]Accounts!$D$50="","",[1]Accounts!$C$50) | I49: =IF([1]Accounts!$D$50="","",[1]Accounts!$D$50) | K49: =IF([1]SubGroups!$C$50="","",[1]SubGroups!$A$50) | L49: =IF([1]SubGroups!$C$50="","",[1]SubGroups!$B$50) | M49: =IF([1]SubGroups!$C$50="","",[1]SubGroups!$C$50) | N49: =IF([1]SubGroups!$C$50="","",[1]SubGroups!$D$50) | R49: =IF(AND($F49<>"",$I49<>""),IF(OR($G49="دارایی ثابت",$G49="وام و تسهیلات",$G49="سرمایه و آورده صاحبان"),0,1),0) | S49: =SUM($R$6:$R49) | T49: =IFERROR(INDEX($F$6:$F$565,MATCH(ROW()-5,$S$6:$S$565,0)),"") | V49: =IF(AND($K49<>"",$M49<>""),$L49="هزینه",0)*1 | W49: =SUM($V$6:$V49) | X49: =IFERROR(INDEX($M$6:$M$105,MATCH(ROW()-5,$W$6:$W$105,0)),"") | Z49: =IF([2]Entry!$E$52="","",[2]Entry!$E$52) | AA49: =IF([2]Entry!$G$52="","",[2]Entry!$G$52) | AB49: =IF([2]Entry!$J$52="","",[2]Entry!$J$52) | AC49: =IF([2]Entry!$K$52="","",[2]Entry!$K$52) | AD49: =IF([2]Entry!$L$52="","",[2]Entry!$L$52) | AE49: =IF([2]Entry!$M$52="","",[2]Entry!$M$52) | AF49: =IF([2]Entry!$N$52="","",[2]Entry!$N$52) | AG49: =IF([3]Issues!$B$52="","",[3]Issues!$B$52) | AH49: =IF([3]Issues!$D$52="","",[3]Issues!$D$52) | AI49: =IF([3]Issues!$E$52="","",[3]Issues!$E$52) | AJ49: =IF([2]Entry!$S$52="","",[2]Entry!$S$52) | AK49: =IF([2]Entry!$C$52="","",[2]Entry!$C$52) | AL49: =IF([2]Entry!$D$52="","",[2]Entry!$D$52) | AM49: =IF(AND($F49<>"",$I49<>""),IF($G49="دارایی ثابت",1,0),0) | AN49: =SUM($AM$6:$AM49) | AO49: =IFERROR(INDEX($F$6:$F$565,MATCH(ROW()-5,$AN$6:$AN$565,0)),"") | AP49: =IF(AND($F49<>"",$I49<>""),IF($G49="وام و تسهیلات",1,0),0) | AQ49: =SUM($AP$6:$AP49) | AR49: =IFERROR(INDEX($F$6:$F$565,MATCH(ROW()-5,$AQ$6:$AQ$565,0)),"") | AS49: =IF(AND($F49<>"",$I49<>""),IF($G49="سرمایه و آورده صاحبان",1,0),0) | AT49: =SUM($AS$6:$AS49) | AU49: =IFERROR(INDEX($F$6:$F$565,MATCH(ROW()-5,$AT$6:$AT$565,0)),"") | AW49: =IF([3]Issues!$C$52="","",[3]Issues!$C$52) | AX49: =IF([4]Entry!$E$52="","",[4]Entry!$E$52) | AY49: =IF([4]Entry!$H$52="","",[4]Entry!$H$52) | AZ49: =IF([4]Entry!$I$52="","",[4]Entry!$I$52)
F50: =IF([1]Accounts!$D$51="","",[1]Accounts!$A$51) | G50: =IF([1]Accounts!$D$51="","",[1]Accounts!$B$51) | H50: =IF([1]Accounts!$D$51="","",[1]Accounts!$C$51) | I50: =IF([1]Accounts!$D$51="","",[1]Accounts!$D$51) | K50: =IF([1]SubGroups!$C$51="","",[1]SubGroups!$A$51) | L50: =IF([1]SubGroups!$C$51="","",[1]SubGroups!$B$51) | M50: =IF([1]SubGroups!$C$51="","",[1]SubGroups!$C$51) | N50: =IF([1]SubGroups!$C$51="","",[1]SubGroups!$D$51) | R50: =IF(AND($F50<>"",$I50<>""),IF(OR($G50="دارایی ثابت",$G50="وام و تسهیلات",$G50="سرمایه و آورده صاحبان"),0,1),0) | S50: =SUM($R$6:$R50) | T50: =IFERROR(INDEX($F$6:$F$565,MATCH(ROW()-5,$S$6:$S$565,0)),"") | V50: =IF(AND($K50<>"",$M50<>""),$L50="هزینه",0)*1 | W50: =SUM($V$6:$V50) | X50: =IFERROR(INDEX($M$6:$M$105,MATCH(ROW()-5,$W$6:$W$105,0)),"") | Z50: =IF([2]Entry!$E$53="","",[2]Entry!$E$53) | AA50: =IF([2]Entry!$G$53="","",[2]Entry!$G$53) | AB50: =IF([2]Entry!$J$53="","",[2]Entry!$J$53) | AC50: =IF([2]Entry!$K$53="","",[2]Entry!$K$53) | AD50: =IF([2]Entry!$L$53="","",[2]Entry!$L$53) | AE50: =IF([2]Entry!$M$53="","",[2]Entry!$M$53) | AF50: =IF([2]Entry!$N$53="","",[2]Entry!$N$53) | AG50: =IF([3]Issues!$B$53="","",[3]Issues!$B$53) | AH50: =IF([3]Issues!$D$53="","",[3]Issues!$D$53) | AI50: =IF([3]Issues!$E$53="","",[3]Issues!$E$53) | AJ50: =IF([2]Entry!$S$53="","",[2]Entry!$S$53) | AK50: =IF([2]Entry!$C$53="","",[2]Entry!$C$53) | AL50: =IF([2]Entry!$D$53="","",[2]Entry!$D$53) | AM50: =IF(AND($F50<>"",$I50<>""),IF($G50="دارایی ثابت",1,0),0) | AN50: =SUM($AM$6:$AM50) | AO50: =IFERROR(INDEX($F$6:$F$565,MATCH(ROW()-5,$AN$6:$AN$565,0)),"") | AP50: =IF(AND($F50<>"",$I50<>""),IF($G50="وام و تسهیلات",1,0),0) | AQ50: =SUM($AP$6:$AP50) | AR50: =IFERROR(INDEX($F$6:$F$565,MATCH(ROW()-5,$AQ$6:$AQ$565,0)),"") | AS50: =IF(AND($F50<>"",$I50<>""),IF($G50="سرمایه و آورده صاحبان",1,0),0) | AT50: =SUM($AS$6:$AS50) | AU50: =IFERROR(INDEX($F$6:$F$565,MATCH(ROW()-5,$AT$6:$AT$565,0)),"") | AW50: =IF([3]Issues!$C$53="","",[3]Issues!$C$53) | AX50: =IF([4]Entry!$E$53="","",[4]Entry!$E$53) | AY50: =IF([4]Entry!$H$53="","",[4]Entry!$H$53) | AZ50: =IF([4]Entry!$I$53="","",[4]Entry!$I$53)
F51: =IF([1]Accounts!$D$52="","",[1]Accounts!$A$52) | G51: =IF([1]Accounts!$D$52="","",[1]Accounts!$B$52) | H51: =IF([1]Accounts!$D$52="","",[1]Accounts!$C$52) | I51: =IF([1]Accounts!$D$52="","",[1]Accounts!$D$52) | K51: =IF([1]SubGroups!$C$52="","",[1]SubGroups!$A$52) | L51: =IF([1]SubGroups!$C$52="","",[1]SubGroups!$B$52) | M51: =IF([1]SubGroups!$C$52="","",[1]SubGroups!$C$52) | N51: =IF([1]SubGroups!$C$52="","",[1]SubGroups!$D$52) | R51: =IF(AND($F51<>"",$I51<>""),IF(OR($G51="دارایی ثابت",$G51="وام و تسهیلات",$G51="سرمایه و آورده صاحبان"),0,1),0) | S51: =SUM($R$6:$R51) | T51: =IFERROR(INDEX($F$6:$F$565,MATCH(ROW()-5,$S$6:$S$565,0)),"") | V51: =IF(AND($K51<>"",$M51<>""),$L51="هزینه",0)*1 | W51: =SUM($V$6:$V51) | X51: =IFERROR(INDEX($M$6:$M$105,MATCH(ROW()-5,$W$6:$W$105,0)),"") | Z51: =IF([2]Entry!$E$54="","",[2]Entry!$E$54) | AA51: =IF([2]Entry!$G$54="","",[2]Entry!$G$54) | AB51: =IF([2]Entry!$J$54="","",[2]Entry!$J$54) | AC51: =IF([2]Entry!$K$54="","",[2]Entry!$K$54) | AD51: =IF([2]Entry!$L$54="","",[2]Entry!$L$54) | AE51: =IF([2]Entry!$M$54="","",[2]Entry!$M$54) | AF51: =IF([2]Entry!$N$54="","",[2]Entry!$N$54) | AG51: =IF([3]Issues!$B$54="","",[3]Issues!$B$54) | AH51: =IF([3]Issues!$D$54="","",[3]Issues!$D$54) | AI51: =IF([3]Issues!$E$54="","",[3]Issues!$E$54) | AJ51: =IF([2]Entry!$S$54="","",[2]Entry!$S$54) | AK51: =IF([2]Entry!$C$54="","",[2]Entry!$C$54) | AL51: =IF([2]Entry!$D$54="","",[2]Entry!$D$54) | AM51: =IF(AND($F51<>"",$I51<>""),IF($G51="دارایی ثابت",1,0),0) | AN51: =SUM($AM$6:$AM51) | AO51: =IFERROR(INDEX($F$6:$F$565,MATCH(ROW()-5,$AN$6:$AN$565,0)),"") | AP51: =IF(AND($F51<>"",$I51<>""),IF($G51="وام و تسهیلات",1,0),0) | AQ51: =SUM($AP$6:$AP51) | AR51: =IFERROR(INDEX($F$6:$F$565,MATCH(ROW()-5,$AQ$6:$AQ$565,0)),"") | AS51: =IF(AND($F51<>"",$I51<>""),IF($G51="سرمایه و آورده صاحبان",1,0),0) | AT51: =SUM($AS$6:$AS51) | AU51: =IFERROR(INDEX($F$6:$F$565,MATCH(ROW()-5,$AT$6:$AT$565,0)),"") | AW51: =IF([3]Issues!$C$54="","",[3]Issues!$C$54) | AX51: =IF([4]Entry!$E$54="","",[4]Entry!$E$54) | AY51: =IF([4]Entry!$H$54="","",[4]Entry!$H$54) | AZ51: =IF([4]Entry!$I$54="","",[4]Entry!$I$54)
